Workbook

Sheet Instrucciones
A1: VÉRTICE · Ingeniería, Arquitectura y Proyectos
A2: CONTROL DE MAQUINARIA Y EQUIPO PROPIO Y RENTADO
A4: Captura
A5: Celdas amarillas con texto azul = datos que capturas. Texto negro = fórmulas: no escribas encima. La fila de ejemplo muestra el formato esperado; sustitúyela por tus datos.
A7: Para qué sirve:
A8: Inventario de equipo propio y rentado, reporte diario de uso con horómetro, costo horario del equipo propio, conciliación de rentas contra la factura del arrendador y programa de mantenimiento por horómetro.
A9: Cómo se llena:
A10: 1. «Inventario»: una fila por equipo con clave única. Para rentados captura proveedor, tarifa, unidad y mínimo (los del Anexo A del contrato de arrendamiento).
A11: 2. «Uso diario»: una fila por equipo por día con horómetro inicial y final, firmada por el operador y tu representante (cláusula RENTA del contrato de arrendamiento). Anota horas inactivas y su causa: las horas por falla del equipo rentado no se pagan.
A12: 3. «Costo horario propio»: método de costo horario (depreciación, inversión, seguros, mantenimiento, combustible, lubricantes, llantas y operación). El resultado alimenta el inventario y tus APU en VERTICE-CALCULO.
A13: 4. «Control de rentas»: captura el periodo y lo que te facturó el arrendador; el libro calcula lo que debes pagar con el mínimo pactado y marca si la factura no cuadra.
A14: 5. «Mantenimiento»: intervalos por horómetro; el estatus avisa cuándo programar el servicio.

Sheet Inventario
A1: VÉRTICE · Ingeniería, Arquitectura y Proyectos
A2: INVENTARIO DE MAQUINARIA Y EQUIPO
A3: Obra:
A4: Contrato:
A6: Clave | B6: Equipo | C6: Tipo | D6: Marca | E6: Modelo | F6: Serie | G6: Proveedor (si es rentado) | H6: Tarifa (sin IVA) | I6: Unidad de tarifa | J6: Mínimo por día (h o jornadas) | K6: Costo horario propio | L6: Ingreso a obra | M6: Salida de obra | N6: Horómetro actual | O6: Estatus
A7: EQ-01 | B7: Revolvedora de 1 saco | C7: Propio | I7: hora | K7: =IF(C7<>"Propio","",IFERROR(INDEX('Costo horario propio'!$B$29:$F$29,MATCH(A7,'Costo horario propio'!$B$6:$F$6,0)),"Calcula en hoja")) -> 36.072917 | L7: 46314 | N7: =IF(A7="","",_xlfn.MAXIFS('Uso diario'!$F$7:$F$1006,'Uso diario'!$B$7:$B$1006,A7)) -> 0 | O7: =IF(A7="","",IF(M7<>"","Fuera de obra","En obra")) -> En obra
A8: EQ-02 | B8: Vibrador de chicote a gasolina | C8: Propio | I8: hora | K8: =IF(C8<>"Propio","",IFERROR(INDEX('Costo horario propio'!$B$29:$F$29,MATCH(A8,'Costo horario propio'!$B$6:$F$6,0)),"Calcula en hoja")) -> 25.82075 | L8: 46314 | N8: =IF(A8="","",_xlfn.MAXIFS('Uso diario'!$F$7:$F$1006,'Uso diario'!$B$7:$B$1006,A8)) -> 0 | O8: =IF(A8="","",IF(M8<>"","Fuera de obra","En obra")) -> En obra
A9: EQ-03 | C9: Rentado | G9: Arrendador | I9: hora | J9: 8 | K9: =IF(C9<>"Propio","",IFERROR(INDEX('Costo horario propio'!$B$29:$F$29,MATCH(A9,'Costo horario propio'!$B$6:$F$6,0)),"Calcula en hoja")) | L9: 46314 | N9: =IF(A9="","",_xlfn.MAXIFS('Uso diario'!$F$7:$F$1006,'Uso diario'!$B$7:$B$1006,A9)) -> 1264 | O9: =IF(A9="","",IF(M9<>"","Fuera de obra","En obra")) -> En obra
K10: =IF(C10<>"Propio","",IFERROR(INDEX('Costo horario propio'!$B$29:$F$29,MATCH(A10,'Costo horario propio'!$B$6:$F$6,0)),"Calcula en hoja")) | N10: =IF(A10="","",_xlfn.MAXIFS('Uso diario'!$F$7:$F$1006,'Uso diario'!$B$7:$B$1006,A10)) | O10: =IF(A10="","",IF(M10<>"","Fuera de obra","En obra"))
K11: =IF(C11<>"Propio","",IFERROR(INDEX('Costo horario propio'!$B$29:$F$29,MATCH(A11,'Costo horario propio'!$B$6:$F$6,0)),"Calcula en hoja")) | N11: =IF(A11="","",_xlfn.MAXIFS('Uso diario'!$F$7:$F$1006,'Uso diario'!$B$7:$B$1006,A11)) | O11: =IF(A11="","",IF(M11<>"","Fuera de obra","En obra"))
K12: =IF(C12<>"Propio","",IFERROR(INDEX('Costo horario propio'!$B$29:$F$29,MATCH(A12,'Costo horario propio'!$B$6:$F$6,0)),"Calcula en hoja")) | N12: =IF(A12="","",_xlfn.MAXIFS('Uso diario'!$F$7:$F$1006,'Uso diario'!$B$7:$B$1006,A12)) | O12: =IF(A12="","",IF(M12<>"","Fuera de obra","En obra"))
K13: =IF(C13<>"Propio","",IFERROR(INDEX('Costo horario propio'!$B$29:$F$29,MATCH(A13,'Costo horario propio'!$B$6:$F$6,0)),"Calcula en hoja")) | N13: =IF(A13="","",_xlfn.MAXIFS('Uso diario'!$F$7:$F$1006,'Uso diario'!$B$7:$B$1006,A13)) | O13: =IF(A13="","",IF(M13<>"","Fuera de obra","En obra"))
K14: =IF(C14<>"Propio","",IFERROR(INDEX('Costo horario propio'!$B$29:$F$29,MATCH(A14,'Costo horario propio'!$B$6:$F$6,0)),"Calcula en hoja")) | N14: =IF(A14="","",_xlfn.MAXIFS('Uso diario'!$F$7:$F$1006,'Uso diario'!$B$7:$B$1006,A14)) | O14: =IF(A14="","",IF(M14<>"","Fuera de obra","En obra"))
K15: =IF(C15<>"Propio","",IFERROR(INDEX('Costo horario propio'!$B$29:$F$29,MATCH(A15,'Costo horario propio'!$B$6:$F$6,0)),"Calcula en hoja")) | N15: =IF(A15="","",_xlfn.MAXIFS('Uso diario'!$F$7:$F$1006,'Uso diario'!$B$7:$B$1006,A15)) | O15: =IF(A15="","",IF(M15<>"","Fuera de obra","En obra"))
K16: =IF(C16<>"Propio","",IFERROR(INDEX('Costo horario propio'!$B$29:$F$29,MATCH(A16,'Costo horario propio'!$B$6:$F$6,0)),"Calcula en hoja")) | N16: =IF(A16="","",_xlfn.MAXIFS('Uso diario'!$F$7:$F$1006,'Uso diario'!$B$7:$B$1006,A16)) | O16: =IF(A16="","",IF(M16<>"","Fuera de obra","En obra"))
K17: =IF(C17<>"Propio","",IFERROR(INDEX('Costo horario propio'!$B$29:$F$29,MATCH(A17,'Costo horario propio'!$B$6:$F$6,0)),"Calcula en hoja")) | N17: =IF(A17="","",_xlfn.MAXIFS('Uso diario'!$F$7:$F$1006,'Uso diario'!$B$7:$B$1006,A17)) | O17: =IF(A17="","",IF(M17<>"","Fuera de obra","En obra"))
K18: =IF(C18<>"Propio","",IFERROR(INDEX('Costo horario propio'!$B$29:$F$29,MATCH(A18,'Costo horario propio'!$B$6:$F$6,0)),"Calcula en hoja")) | N18: =IF(A18="","",_xlfn.MAXIFS('Uso diario'!$F$7:$F$1006,'Uso diario'!$B$7:$B$1006,A18)) | O18: =IF(A18="","",IF(M18<>"","Fuera de obra","En obra"))
K19: =IF(C19<>"Propio","",IFERROR(INDEX('Costo horario propio'!$B$29:$F$29,MATCH(A19,'Costo horario propio'!$B$6:$F$6,0)),"Calcula en hoja")) | N19: =IF(A19="","",_xlfn.MAXIFS('Uso diario'!$F$7:$F$1006,'Uso diario'!$B$7:$B$1006,A19)) | O19: =IF(A19="","",IF(M19<>"","Fuera de obra","En obra"))
K20: =IF(C20<>"Propio","",IFERROR(INDEX('Costo horario propio'!$B$29:$F$29,MATCH(A20,'Costo horario propio'!$B$6:$F$6,0)),"Calcula en hoja")) | N20: =IF(A20="","",_xlfn.MAXIFS('Uso diario'!$F$7:$F$1006,'Uso diario'!$B$7:$B$1006,A20)) | O20: =IF(A20="","",IF(M20<>"","Fuera de obra","En obra"))
K21: =IF(C21<>"Propio","",IFERROR(INDEX('Costo horario propio'!$B$29:$F$29,MATCH(A21,'Costo horario propio'!$B$6:$F$6,0)),"Calcula en hoja")) | N21: =IF(A21="","",_xlfn.MAXIFS('Uso diario'!$F$7:$F$1006,'Uso diario'!$B$7:$B$1006,A21)) | O21: =IF(A21="","",IF(M21<>"","Fuera de obra","En obra"))
... K46: =IF(C46<>"Propio","",IFERROR(INDEX('Costo horario propio'!$B$29:$F$29,MATCH(A46,'Costo horario propio'!$B$6:$F$6,0)),"Calcula en hoja")) | N46: =IF(A46="","",_xlfn.MAXIFS('Uso diario'!$F$7:$F$1006,'Uso diario'!$B$7:$B$1006,A46)) | O46: =IF(A46="","",IF(M46<>"","Fuera de obra","En obra"))

Sheet Uso diario
A1: VÉRTICE · Ingeniería, Arquitectura y Proyectos
A2: REPORTE DIARIO DE USO DE EQUIPO
A3: Obra:
A4: Contrato:
A6: Fecha | B6: Clave | C6: Equipo | D6: Tipo | E6: Horómetro inicial | F6: Horómetro final | G6: Horas trabajadas | H6: Horas inactivas | I6: Causa de inactividad | J6: Combustible (L) | K6: Rendimiento (L/h) | L6: Frente / concepto | M6: Operador | N6: Firma de conformidad
A7: 46314 | B7: EQ-03 | C7: =IF(B7="","",IFERROR(INDEX(Inventario!$B$7:$B$46,MATCH(B7,Inventario!$A$7:$A$46,0)),"Clave no existe")) -> 0 | D7: =IF(B7="","",IFERROR(INDEX(Inventario!$C$7:$C$46,MATCH(B7,Inventario!$A$7:$A$46,0)),"")) -> Rentado | E7: 1250 | F7: 1258.5 | G7: =IF(OR(E7="",F7=""),IF(B7="","",IF(A7="","",8)),F7-E7) -> 8.5 | H7: 0 | J7: 72 | K7: =IF(OR(J7="",N(G7)=0),"",J7/G7) -> 8.4705882 | L7: Excavación de cepas eje A
A8: 46314 | B8: EQ-04 | C8: =IF(B8="","",IFERROR(INDEX(Inventario!$B$7:$B$46,MATCH(B8,Inventario!$A$7:$A$46,0)),"Clave no existe")) -> Clave no existe | D8: =IF(B8="","",IFERROR(INDEX(Inventario!$C$7:$C$46,MATCH(B8,Inventario!$A$7:$A$46,0)),"")) | G8: =IF(OR(E8="",F8=""),IF(B8="","",IF(A8="","",8)),F8-E8) -> 8 | H8: 0 | J8: 4 | K8: =IF(OR(J8="",N(G8)=0),"",J8/G8) -> 0.5 | L8: Compactación de relleno
A9: 46315 | B9: EQ-03 | C9: =IF(B9="","",IFERROR(INDEX(Inventario!$B$7:$B$46,MATCH(B9,Inventario!$A$7:$A$46,0)),"Clave no existe")) -> 0 | D9: =IF(B9="","",IFERROR(INDEX(Inventario!$C$7:$C$46,MATCH(B9,Inventario!$A$7:$A$46,0)),"")) -> Rentado | E9: 1258.5 | F9: 1264 | G9: =IF(OR(E9="",F9=""),IF(B9="","",IF(A9="","",8)),F9-E9) -> 5.5 | H9: 2.5 | I9: Falla hidráulica (equipo rentado) | J9: 48 | K9: =IF(OR(J9="",N(G9)=0),"",J9/G9) -> 8.7272727 | L9: Excavación de cepas eje B
A10: 46315 | B10: EQ-01 | C10: =IF(B10="","",IFERROR(INDEX(Inventario!$B$7:$B$46,MATCH(B10,Inventario!$A$7:$A$46,0)),"Clave no existe")) -> Revolvedora de 1 saco | D10: =IF(B10="","",IFERROR(INDEX(Inventario!$C$7:$C$46,MATCH(B10,Inventario!$A$7:$A$46,0)),"")) -> Propio | G10: =IF(OR(E10="",F10=""),IF(B10="","",IF(A10="","",8)),F10-E10) -> 8 | H10: 0 | J10: 6 | K10: =IF(OR(J10="",N(G10)=0),"",J10/G10) -> 0.75 | L10: Colado de firmes
C11: =IF(B11="","",IFERROR(INDEX(Inventario!$B$7:$B$46,MATCH(B11,Inventario!$A$7:$A$46,0)),"Clave no existe")) | D11: =IF(B11="","",IFERROR(INDEX(Inventario!$C$7:$C$46,MATCH(B11,Inventario!$A$7:$A$46,0)),"")) | G11: =IF(OR(E11="",F11=""),IF(B11="","",IF(A11="","",8)),F11-E11) | K11: =IF(OR(J11="",N(G11)=0),"",J11/G11)
C12: =IF(B12="","",IFERROR(INDEX(Inventario!$B$7:$B$46,MATCH(B12,Inventario!$A$7:$A$46,0)),"Clave no existe")) | D12: =IF(B12="","",IFERROR(INDEX(Inventario!$C$7:$C$46,MATCH(B12,Inventario!$A$7:$A$46,0)),"")) | G12: =IF(OR(E12="",F12=""),IF(B12="","",IF(A12="","",8)),F12-E12) | K12: =IF(OR(J12="",N(G12)=0),"",J12/G12)
C13: =IF(B13="","",IFERROR(INDEX(Inventario!$B$7:$B$46,MATCH(B13,Inventario!$A$7:$A$46,0)),"Clave no existe")) | D13: =IF(B13="","",IFERROR(INDEX(Inventario!$C$7:$C$46,MATCH(B13,Inventario!$A$7:$A$46,0)),"")) | G13: =IF(OR(E13="",F13=""),IF(B13="","",IF(A13="","",8)),F13-E13) | K13: =IF(OR(J13="",N(G13)=0),"",J13/G13)
C14: =IF(B14="","",IFERROR(INDEX(Inventario!$B$7:$B$46,MATCH(B14,Inventario!$A$7:$A$46,0)),"Clave no existe")) | D14: =IF(B14="","",IFERROR(INDEX(Inventario!$C$7:$C$46,MATCH(B14,Inventario!$A$7:$A$46,0)),"")) | G14: =IF(OR(E14="",F14=""),IF(B14="","",IF(A14="","",8)),F14-E14) | K14: =IF(OR(J14="",N(G14)=0),"",J14/G14)
C15: =IF(B15="","",IFERROR(INDEX(Inventario!$B$7:$B$46,MATCH(B15,Inventario!$A$7:$A$46,0)),"Clave no existe")) | D15: =IF(B15="","",IFERROR(INDEX(Inventario!$C$7:$C$46,MATCH(B15,Inventario!$A$7:$A$46,0)),"")) | G15: =IF(OR(E15="",F15=""),IF(B15="","",IF(A15="","",8)),F15-E15) | K15: =IF(OR(J15="",N(G15)=0),"",J15/G15)
C16: =IF(B16="","",IFERROR(INDEX(Inventario!$B$7:$B$46,MATCH(B16,Inventario!$A$7:$A$46,0)),"Clave no existe")) | D16: =IF(B16="","",IFERROR(INDEX(Inventario!$C$7:$C$46,MATCH(B16,Inventario!$A$7:$A$46,0)),"")) | G16: =IF(OR(E16="",F16=""),IF(B16="","",IF(A16="","",8)),F16-E16) | K16: =IF(OR(J16="",N(G16)=0),"",J16/G16)
C17: =IF(B17="","",IFERROR(INDEX(Inventario!$B$7:$B$46,MATCH(B17,Inventario!$A$7:$A$46,0)),"Clave no existe")) | D17: =IF(B17="","",IFERROR(INDEX(Inventario!$C$7:$C$46,MATCH(B17,Inventario!$A$7:$A$46,0)),"")) | G17: =IF(OR(E17="",F17=""),IF(B17="","",IF(A17="","",8)),F17-E17) | K17: =IF(OR(J17="",N(G17)=0),"",J17/G17)
C18: =IF(B18="","",IFERROR(INDEX(Inventario!$B$7:$B$46,MATCH(B18,Inventario!$A$7:$A$46,0)),"Clave no existe")) | D18: =IF(B18="","",IFERROR(INDEX(Inventario!$C$7:$C$46,MATCH(B18,Inventario!$A$7:$A$46,0)),"")) | G18: =IF(OR(E18="",F18=""),IF(B18="","",IF(A18="","",8)),F18-E18) | K18: =IF(OR(J18="",N(G18)=0),"",J18/G18)
C19: =IF(B19="","",IFERROR(INDEX(Inventario!$B$7:$B$46,MATCH(B19,Inventario!$A$7:$A$46,0)),"Clave no existe")) | D19: =IF(B19="","",IFERROR(INDEX(Inventario!$C$7:$C$46,MATCH(B19,Inventario!$A$7:$A$46,0)),"")) | G19: =IF(OR(E19="",F19=""),IF(B19="","",IF(A19="","",8)),F19-E19) | K19: =IF(OR(J19="",N(G19)=0),"",J19/G19)
C20: =IF(B20="","",IFERROR(INDEX(Inventario!$B$7:$B$46,MATCH(B20,Inventario!$A$7:$A$46,0)),"Clave no existe")) | D20: =IF(B20="","",IFERROR(INDEX(Inventario!$C$7:$C$46,MATCH(B20,Inventario!$A$7:$A$46,0)),"")) | G20: =IF(OR(E20="",F20=""),IF(B20="","",IF(A20="","",8)),F20-E20) | K20: =IF(OR(J20="",N(G20)=0),"",J20/G20)
C21: =IF(B21="","",IFERROR(INDEX(Inventario!$B$7:$B$46,MATCH(B21,Inventario!$A$7:$A$46,0)),"Clave no existe")) | D21: =IF(B21="","",IFERROR(INDEX(Inventario!$C$7:$C$46,MATCH(B21,Inventario!$A$7:$A$46,0)),"")) | G21: =IF(OR(E21="",F21=""),IF(B21="","",IF(A21="","",8)),F21-E21) | K21: =IF(OR(J21="",N(G21)=0),"",J21/G21)
C22: =IF(B22="","",IFERROR(INDEX(Inventario!$B$7:$B$46,MATCH(B22,Inventario!$A$7:$A$46,0)),"Clave no existe")) | D22: =IF(B22="","",IFERROR(INDEX(Inventario!$C$7:$C$46,MATCH(B22,Inventario!$A$7:$A$46,0)),"")) | G22: =IF(OR(E22="",F22=""),IF(B22="","",IF(A22="","",8)),F22-E22) | K22: =IF(OR(J22="",N(G22)=0),"",J22/G22)
... C1006: =IF(B1006="","",IFERROR(INDEX(Inventario!$B$7:$B$46,MATCH(B1006,Inventario!$A$7:$A$46,0)),"Clave no existe")) | D1006: =IF(B1006="","",IFERROR(INDEX(Inventario!$C$7:$C$46,MATCH(B1006,Inventario!$A$7:$A$46,0)),"")) | G1006: =IF(OR(E1006="",F1006=""),IF(B1006="","",IF(A1006="","",8)),F1006-E1006) | K1006: =IF(OR(J1006="",N(G1006)=0),"",J1006/G1006)

Sheet Costo horario propio
A1: VÉRTICE · Ingeniería, Arquitectura y Proyectos
A2: COSTO HORARIO DE EQUIPO PROPIO
A3: Obra:
A4: Contrato:
A6: Clave del equipo (igual al inventario) | B6: EQ-01 | C6: EQ-02
A7: Equipo | B7: Revolvedora 1 saco | C7: Vibrador gasolina
A8: Valor de adquisición Va (sin IVA) | B8: 38000 | C8: 14500
A9: Valor de llantas Pn (si tiene) | B9: 0 | C9: 0
A10: Valor de rescate (% de Va) | B10: 0.15 | C10: 0.1
A11: Vida económica Ve (horas) | B11: 6000 | C11: 3000
A12: Horas trabajadas por año Hea | B12: 1200 | C12: 1000
A13: Tasa de interés anual i | B13: 0.14 | C13: 0.14
A14: Prima anual de seguros s | B14: 0.03 | C14: 0.03
A15: Coeficiente de mantenimiento Ko (× depreciación) | B15: 0.8 | C15: 0.9
A16: Consumo de combustible (L/h) | B16: 0.9 | C16: 0.6
A17: Precio del combustible ($/L sin IVA) | B17: 22.5 | C17: 22.5
A18: Lubricantes (% del costo de combustible) | B18: 0.15 | C18: 0.2
A19: Vida de llantas (horas) | B19: 2000 | C19: 2000
... A21: Horas efectivas por turno | B21: 8 | C21: 8
A22: Valor de rescate Vr | B22: =IF(B$6="","",B8*B10) -> 5700 | C22: =IF(C$6="","",C8*C10) -> 1450 | D22: =IF(D$6="","",D8*D10) | E22: =IF(E$6="","",E8*E10) | F22: =IF(F$6="","",F8*F10)
A23: Depreciación D = (Va − Vr) / Ve | B23: =IF(B$6="","",IF(N(B11)=0,0,(B8-B22)/B11)) -> 5.3833333 | C23: =IF(C$6="","",IF(N(C11)=0,0,(C8-C22)/C11)) -> 4.35 | D23: =IF(D$6="","",IF(N(D11)=0,0,(D8-D22)/D11)) | E23: =IF(E$6="","",IF(N(E11)=0,0,(E8-E22)/E11)) | F23: =IF(F$6="","",IF(N(F11)=0,0,(F8-F22)/F11))
A24: Inversión Im = (Va + Vr) / (2·Hea) · i | B24: =IF(B$6="","",IF(N(B12)=0,0,(B8+B22)/(2*B12)*B13)) -> 2.5491667 | C24: =IF(C$6="","",IF(N(C12)=0,0,(C8+C22)/(2*C12)*C13)) -> 1.1165 | D24: =IF(D$6="","",IF(N(D12)=0,0,(D8+D22)/(2*D12)*D13)) | E24: =IF(E$6="","",IF(N(E12)=0,0,(E8+E22)/(2*E12)*E13)) | F24: =IF(F$6="","",IF(N(F12)=0,0,(F8+F22)/(2*F12)*F13))
A25: Seguros Sm = (Va + Vr) / (2·Hea) · s | B25: =IF(B$6="","",IF(N(B12)=0,0,(B8+B22)/(2*B12)*B14)) -> 0.54625 | C25: =IF(C$6="","",IF(N(C12)=0,0,(C8+C22)/(2*C12)*C14)) -> 0.23925 | D25: =IF(D$6="","",IF(N(D12)=0,0,(D8+D22)/(2*D12)*D14)) | E25: =IF(E$6="","",IF(N(E12)=0,0,(E8+E22)/(2*E12)*E14)) | F25: =IF(F$6="","",IF(N(F12)=0,0,(F8+F22)/(2*F12)*F14))
A26: Mantenimiento Mn = Ko · D | B26: =IF(B$6="","",B15*B23) -> 4.3066667 | C26: =IF(C$6="","",C15*C23) -> 3.915 | D26: =IF(D$6="","",D15*D23) | E26: =IF(E$6="","",E15*E23) | F26: =IF(F$6="","",F15*F23)
A27: Combustible y lubricantes | B27: =IF(B$6="","",B16*B17*(1+B18)) -> 23.2875 | C27: =IF(C$6="","",C16*C17*(1+C18)) -> 16.2 | D27: =IF(D$6="","",D16*D17*(1+D18)) | E27: =IF(E$6="","",E16*E17*(1+E18)) | F27: =IF(F$6="","",F16*F17*(1+F18))
A28: Llantas + operación | B28: =IF(B$6="","",IF(N(B19)=0,0,B9/B19)+IF(N(B21)=0,0,B20/B21)) -> 0 | C28: =IF(C$6="","",IF(N(C19)=0,0,C9/C19)+IF(N(C21)=0,0,C20/C21)) -> 0 | D28: =IF(D$6="","",IF(N(D19)=0,0,D9/D19)+IF(N(D21)=0,0,D20/D21)) | E28: =IF(E$6="","",IF(N(E19)=0,0,E9/E19)+IF(N(E21)=0,0,E20/E21)) | F28: =IF(F$6="","",IF(N(F19)=0,0,F9/F19)+IF(N(F21)=0,0,F20/F21))
A29: COSTO HORARIO DIRECTO | B29: =IF(B$6="","",SUM(B23:B28)) -> 36.072917 | C29: =IF(C$6="","",SUM(C23:C28)) -> 25.82075 | D29: =IF(D$6="","",SUM(D23:D28)) | E29: =IF(E$6="","",SUM(E23:E28)) | F29: =IF(F$6="","",SUM(F23:F28))
A31: Método de costo horario (cargos fijos, consumos y operación), el mismo que usan los análisis de precios unitarios. Si el equipo se usa en APU de VERTICE-CALCULO, captura este costo como Insumo tipo «Equipo».

Sheet Control de rentas
A1: VÉRTICE · Ingeniería, Arquitectura y Proyectos
A2: CONCILIACIÓN DE RENTAS DE EQUIPO
A3: Obra:
A4: Contrato:
A6: Clave | B6: Equipo | C6: Proveedor | D6: Periodo del | E6: Periodo al | F6: Unidad de tarifa | G6: Días con uso | H6: Horas trabajadas | I6: Cantidad mínima del periodo | J6: Cantidad a pagar | K6: Tarifa | L6: Fletes | M6: IMPORTE CORRECTO | N6: Facturado por el proveedor | O6: Diferencia / revisión
A7: EQ-03 | B7: =IF(A7="","",INDEX(Inventario!$B$7:$B$46,MATCH(A7,Inventario!$A$7:$A$46,0))) -> 0 | C7: =IF(A7="","",INDEX(Inventario!$G$7:$G$46,MATCH(A7,Inventario!$A$7:$A$46,0))) -> Arrendador | D7: 46314 | E7: 46327 | F7: =IF(A7="","",INDEX(Inventario!$I$7:$I$46,MATCH(A7,Inventario!$A$7:$A$46,0))) -> hora | G7: =IF(A7="",0,SUMPRODUCT(('Uso diario'!$B$7:$B$1006=A7)*('Uso diario'!$A$7:$A$1006>=D7)*('Uso diario'!$A$7:$A$1006<=E7)*('Uso diario'!$G$7:$G$1006>0))) -> 2 | H7: =IF(A7="",0,SUMIFS('Uso diario'!$G$7:$G$1006,'Uso diario'!$B$7:$B$1006,A7,'Uso diario'!$A$7:$A$1006,">="&D7,'Uso diario'!$A$7:$A$1006,"<="&E7)) -> 14 | I7: =IF(A7="","",G7*INDEX(Inventario!$J$7:$J$46,MATCH(A7,Inventario!$A$7:$A$46,0))) -> 16 | J7: =IF(A7="","",IF(F7="hora",MAX(H7,I7),MAX(G7,I7))) -> 16 | K7: =IF(A7="","",INDEX(Inventario!$H$7:$H$46,MATCH(A7,Inventario!$A$7:$A$46,0))) -> 0 | L7: 0 | M7: =IF(A7="","",J7*K7+N(L7)) -> 0 | O7: =IF(OR(A7="",N7=""),"",IF(ABS(N7-M7)<1,"Cuadra",IF(N7>M7,"Cobro de más: $"&TEXT(N7-M7,"#,##0.00"),"Cobro de menos: $"&TEXT(M7-N7,"#,##0.00"))))
B8: =IF(A8="","",INDEX(Inventario!$B$7:$B$46,MATCH(A8,Inventario!$A$7:$A$46,0))) | C8: =IF(A8="","",INDEX(Inventario!$G$7:$G$46,MATCH(A8,Inventario!$A$7:$A$46,0))) | F8: =IF(A8="","",INDEX(Inventario!$I$7:$I$46,MATCH(A8,Inventario!$A$7:$A$46,0))) | G8: =IF(A8="",0,SUMPRODUCT(('Uso diario'!$B$7:$B$1006=A8)*('Uso diario'!$A$7:$A$1006>=D8)*('Uso diario'!$A$7:$A$1006<=E8)*('Uso diario'!$G$7:$G$1006>0))) -> 0 | H8: =IF(A8="",0,SUMIFS('Uso diario'!$G$7:$G$1006,'Uso diario'!$B$7:$B$1006,A8,'Uso diario'!$A$7:$A$1006,">="&D8,'Uso diario'!$A$7:$A$1006,"<="&E8)) -> 0 | I8: =IF(A8="","",G8*INDEX(Inventario!$J$7:$J$46,MATCH(A8,Inventario!$A$7:$A$46,0))) | J8: =IF(A8="","",IF(F8="hora",MAX(H8,I8),MAX(G8,I8))) | K8: =IF(A8="","",INDEX(Inventario!$H$7:$H$46,MATCH(A8,Inventario!$A$7:$A$46,0))) | M8: =IF(A8="","",J8*K8+N(L8)) | O8: =IF(OR(A8="",N8=""),"",IF(ABS(N8-M8)<1,"Cuadra",IF(N8>M8,"Cobro de más: $"&TEXT(N8-M8,"#,##0.00"),"Cobro de menos: $"&TEXT(M8-N8,"#,##0.00"))))
B9: =IF(A9="","",INDEX(Inventario!$B$7:$B$46,MATCH(A9,Inventario!$A$7:$A$46,0))) | C9: =IF(A9="","",INDEX(Inventario!$G$7:$G$46,MATCH(A9,Inventario!$A$7:$A$46,0))) | F9: =IF(A9="","",INDEX(Inventario!$I$7:$I$46,MATCH(A9,Inventario!$A$7:$A$46,0))) | G9: =IF(A9="",0,SUMPRODUCT(('Uso diario'!$B$7:$B$1006=A9)*('Uso diario'!$A$7:$A$1006>=D9)*('Uso diario'!$A$7:$A$1006<=E9)*('Uso diario'!$G$7:$G$1006>0))) -> 0 | H9: =IF(A9="",0,SUMIFS('Uso diario'!$G$7:$G$1006,'Uso diario'!$B$7:$B$1006,A9,'Uso diario'!$A$7:$A$1006,">="&D9,'Uso diario'!$A$7:$A$1006,"<="&E9)) -> 0 | I9: =IF(A9="","",G9*INDEX(Inventario!$J$7:$J$46,MATCH(A9,Inventario!$A$7:$A$46,0))) | J9: =IF(A9="","",IF(F9="hora",MAX(H9,I9),MAX(G9,I9))) | K9: =IF(A9="","",INDEX(Inventario!$H$7:$H$46,MATCH(A9,Inventario!$A$7:$A$46,0))) | M9: =IF(A9="","",J9*K9+N(L9)) | O9: =IF(OR(A9="",N9=""),"",IF(ABS(N9-M9)<1,"Cuadra",IF(N9>M9,"Cobro de más: $"&TEXT(N9-M9,"#,##0.00"),"Cobro de menos: $"&TEXT(M9-N9,"#,##0.00"))))
B10: =IF(A10="","",INDEX(Inventario!$B$7:$B$46,MATCH(A10,Inventario!$A$7:$A$46,0))) | C10: =IF(A10="","",INDEX(Inventario!$G$7:$G$46,MATCH(A10,Inventario!$A$7:$A$46,0))) | F10: =IF(A10="","",INDEX(Inventario!$I$7:$I$46,MATCH(A10,Inventario!$A$7:$A$46,0))) | G10: =IF(A10="",0,SUMPRODUCT(('Uso diario'!$B$7:$B$1006=A10)*('Uso diario'!$A$7:$A$1006>=D10)*('Uso diario'!$A$7:$A$1006<=E10)*('Uso diario'!$G$7:$G$1006>0))) -> 0 | H10: =IF(A10="",0,SUMIFS('Uso diario'!$G$7:$G$1006,'Uso diario'!$B$7:$B$1006,A10,'Uso diario'!$A$7:$A$1006,">="&D10,'Uso diario'!$A$7:$A$1006,"<="&E10)) -> 0 | I10: =IF(A10="","",G10*INDEX(Inventario!$J$7:$J$46,MATCH(A10,Inventario!$A$7:$A$46,0))) | J10: =IF(A10="","",IF(F10="hora",MAX(H10,I10),MAX(G10,I10))) | K10: =IF(A10="","",INDEX(Inventario!$H$7:$H$46,MATCH(A10,Inventario!$A$7:$A$46,0))) | M10: =IF(A10="","",J10*K10+N(L10)) | O10: =IF(OR(A10="",N10=""),"",IF(ABS(N10-M10)<1,"Cuadra",IF(N10>M10,"Cobro de más: $"&TEXT(N10-M10,"#,##0.00"),"Cobro de menos: $"&TEXT(M10-N10,"#,##0.00"))))
B11: =IF(A11="","",INDEX(Inventario!$B$7:$B$46,MATCH(A11,Inventario!$A$7:$A$46,0))) | C11: =IF(A11="","",INDEX(Inventario!$G$7:$G$46,MATCH(A11,Inventario!$A$7:$A$46,0))) | F11: =IF(A11="","",INDEX(Inventario!$I$7:$I$46,MATCH(A11,Inventario!$A$7:$A$46,0))) | G11: =IF(A11="",0,SUMPRODUCT(('Uso diario'!$B$7:$B$1006=A11)*('Uso diario'!$A$7:$A$1006>=D11)*('Uso diario'!$A$7:$A$1006<=E11)*('Uso diario'!$G$7:$G$1006>0))) -> 0 | H11: =IF(A11="",0,SUMIFS('Uso diario'!$G$7:$G$1006,'Uso diario'!$B$7:$B$1006,A11,'Uso diario'!$A$7:$A$1006,">="&D11,'Uso diario'!$A$7:$A$1006,"<="&E11)) -> 0 | I11: =IF(A11="","",G11*INDEX(Inventario!$J$7:$J$46,MATCH(A11,Inventario!$A$7:$A$46,0))) | J11: =IF(A11="","",IF(F11="hora",MAX(H11,I11),MAX(G11,I11))) | K11: =IF(A11="","",INDEX(Inventario!$H$7:$H$46,MATCH(A11,Inventario!$A$7:$A$46,0))) | M11: =IF(A11="","",J11*K11+N(L11)) | O11: =IF(OR(A11="",N11=""),"",IF(ABS(N11-M11)<1,"Cuadra",IF(N11>M11,"Cobro de más: $"&TEXT(N11-M11,"#,##0.00"),"Cobro de menos: $"&TEXT(M11-N11,"#,##0.00"))))
B12: =IF(A12="","",INDEX(Inventario!$B$7:$B$46,MATCH(A12,Inventario!$A$7:$A$46,0))) | C12: =IF(A12="","",INDEX(Inventario!$G$7:$G$46,MATCH(A12,Inventario!$A$7:$A$46,0))) | F12: =IF(A12="","",INDEX(Inventario!$I$7:$I$46,MATCH(A12,Inventario!$A$7:$A$46,0))) | G12: =IF(A12="",0,SUMPRODUCT(('Uso diario'!$B$7:$B$1006=A12)*('Uso diario'!$A$7:$A$1006>=D12)*('Uso diario'!$A$7:$A$1006<=E12)*('Uso diario'!$G$7:$G$1006>0))) -> 0 | H12: =IF(A12="",0,SUMIFS('Uso diario'!$G$7:$G$1006,'Uso diario'!$B$7:$B$1006,A12,'Uso diario'!$A$7:$A$1006,">="&D12,'Uso diario'!$A$7:$A$1006,"<="&E12)) -> 0 | I12: =IF(A12="","",G12*INDEX(Inventario!$J$7:$J$46,MATCH(A12,Inventario!$A$7:$A$46,0))) | J12: =IF(A12="","",IF(F12="hora",MAX(H12,I12),MAX(G12,I12))) | K12: =IF(A12="","",INDEX(Inventario!$H$7:$H$46,MATCH(A12,Inventario!$A$7:$A$46,0))) | M12: =IF(A12="","",J12*K12+N(L12)) | O12: =IF(OR(A12="",N12=""),"",IF(ABS(N12-M12)<1,"Cuadra",IF(N12>M12,"Cobro de más: $"&TEXT(N12-M12,"#,##0.00"),"Cobro de menos: $"&TEXT(M12-N12,"#,##0.00"))))
B13: =IF(A13="","",INDEX(Inventario!$B$7:$B$46,MATCH(A13,Inventario!$A$7:$A$46,0))) | C13: =IF(A13="","",INDEX(Inventario!$G$7:$G$46,MATCH(A13,Inventario!$A$7:$A$46,0))) | F13: =IF(A13="","",INDEX(Inventario!$I$7:$I$46,MATCH(A13,Inventario!$A$7:$A$46,0))) | G13: =IF(A13="",0,SUMPRODUCT(('Uso diario'!$B$7:$B$1006=A13)*('Uso diario'!$A$7:$A$1006>=D13)*('Uso diario'!$A$7:$A$1006<=E13)*('Uso diario'!$G$7:$G$1006>0))) -> 0 | H13: =IF(A13="",0,SUMIFS('Uso diario'!$G$7:$G$1006,'Uso diario'!$B$7:$B$1006,A13,'Uso diario'!$A$7:$A$1006,">="&D13,'Uso diario'!$A$7:$A$1006,"<="&E13)) -> 0 | I13: =IF(A13="","",G13*INDEX(Inventario!$J$7:$J$46,MATCH(A13,Inventario!$A$7:$A$46,0))) | J13: =IF(A13="","",IF(F13="hora",MAX(H13,I13),MAX(G13,I13))) | K13: =IF(A13="","",INDEX(Inventario!$H$7:$H$46,MATCH(A13,Inventario!$A$7:$A$46,0))) | M13: =IF(A13="","",J13*K13+N(L13)) | O13: =IF(OR(A13="",N13=""),"",IF(ABS(N13-M13)<1,"Cuadra",IF(N13>M13,"Cobro de más: $"&TEXT(N13-M13,"#,##0.00"),"Cobro de menos: $"&TEXT(M13-N13,"#,##0.00"))))
B14: =IF(A14="","",INDEX(Inventario!$B$7:$B$46,MATCH(A14,Inventario!$A$7:$A$46,0))) | C14: =IF(A14="","",INDEX(Inventario!$G$7:$G$46,MATCH(A14,Inventario!$A$7:$A$46,0))) | F14: =IF(A14="","",INDEX(Inventario!$I$7:$I$46,MATCH(A14,Inventario!$A$7:$A$46,0))) | G14: =IF(A14="",0,SUMPRODUCT(('Uso diario'!$B$7:$B$1006=A14)*('Uso diario'!$A$7:$A$1006>=D14)*('Uso diario'!$A$7:$A$1006<=E14)*('Uso diario'!$G$7:$G$1006>0))) -> 0 | H14: =IF(A14="",0,SUMIFS('Uso diario'!$G$7:$G$1006,'Uso diario'!$B$7:$B$1006,A14,'Uso diario'!$A$7:$A$1006,">="&D14,'Uso diario'!$A$7:$A$1006,"<="&E14)) -> 0 | I14: =IF(A14="","",G14*INDEX(Inventario!$J$7:$J$46,MATCH(A14,Inventario!$A$7:$A$46,0))) | J14: =IF(A14="","",IF(F14="hora",MAX(H14,I14),MAX(G14,I14))) | K14: =IF(A14="","",INDEX(Inventario!$H$7:$H$46,MATCH(A14,Inventario!$A$7:$A$46,0))) | M14: =IF(A14="","",J14*K14+N(L14)) | O14: =IF(OR(A14="",N14=""),"",IF(ABS(N14-M14)<1,"Cuadra",IF(N14>M14,"Cobro de más: $"&TEXT(N14-M14,"#,##0.00"),"Cobro de menos: $"&TEXT(M14-N14,"#,##0.00"))))
B15: =IF(A15="","",INDEX(Inventario!$B$7:$B$46,MATCH(A15,Inventario!$A$7:$A$46,0))) | C15: =IF(A15="","",INDEX(Inventario!$G$7:$G$46,MATCH(A15,Inventario!$A$7:$A$46,0))) | F15: =IF(A15="","",INDEX(Inventario!$I$7:$I$46,MATCH(A15,Inventario!$A$7:$A$46,0))) | G15: =IF(A15="",0,SUMPRODUCT(('Uso diario'!$B$7:$B$1006=A15)*('Uso diario'!$A$7:$A$1006>=D15)*('Uso diario'!$A$7:$A$1006<=E15)*('Uso diario'!$G$7:$G$1006>0))) -> 0 | H15: =IF(A15="",0,SUMIFS('Uso diario'!$G$7:$G$1006,'Uso diario'!$B$7:$B$1006,A15,'Uso diario'!$A$7:$A$1006,">="&D15,'Uso diario'!$A$7:$A$1006,"<="&E15)) -> 0 | I15: =IF(A15="","",G15*INDEX(Inventario!$J$7:$J$46,MATCH(A15,Inventario!$A$7:$A$46,0))) | J15: =IF(A15="","",IF(F15="hora",MAX(H15,I15),MAX(G15,I15))) | K15: =IF(A15="","",INDEX(Inventario!$H$7:$H$46,MATCH(A15,Inventario!$A$7:$A$46,0))) | M15: =IF(A15="","",J15*K15+N(L15)) | O15: =IF(OR(A15="",N15=""),"",IF(ABS(N15-M15)<1,"Cuadra",IF(N15>M15,"Cobro de más: $"&TEXT(N15-M15,"#,##0.00"),"Cobro de menos: $"&TEXT(M15-N15,"#,##0.00"))))
B16: =IF(A16="","",INDEX(Inventario!$B$7:$B$46,MATCH(A16,Inventario!$A$7:$A$46,0))) | C16: =IF(A16="","",INDEX(Inventario!$G$7:$G$46,MATCH(A16,Inventario!$A$7:$A$46,0))) | F16: =IF(A16="","",INDEX(Inventario!$I$7:$I$46,MATCH(A16,Inventario!$A$7:$A$46,0))) | G16: =IF(A16="",0,SUMPRODUCT(('Uso diario'!$B$7:$B$1006=A16)*('Uso diario'!$A$7:$A$1006>=D16)*('Uso diario'!$A$7:$A$1006<=E16)*('Uso diario'!$G$7:$G$1006>0))) -> 0 | H16: =IF(A16="",0,SUMIFS('Uso diario'!$G$7:$G$1006,'Uso diario'!$B$7:$B$1006,A16,'Uso diario'!$A$7:$A$1006,">="&D16,'Uso diario'!$A$7:$A$1006,"<="&E16)) -> 0 | I16: =IF(A16="","",G16*INDEX(Inventario!$J$7:$J$46,MATCH(A16,Inventario!$A$7:$A$46,0))) | J16: =IF(A16="","",IF(F16="hora",MAX(H16,I16),MAX(G16,I16))) | K16: =IF(A16="","",INDEX(Inventario!$H$7:$H$46,MATCH(A16,Inventario!$A$7:$A$46,0))) | M16: =IF(A16="","",J16*K16+N(L16)) | O16: =IF(OR(A16="",N16=""),"",IF(ABS(N16-M16)<1,"Cuadra",IF(N16>M16,"Cobro de más: $"&TEXT(N16-M16,"#,##0.00"),"Cobro de menos: $"&TEXT(M16-N16,"#,##0.00"))))
B17: =IF(A17="","",INDEX(Inventario!$B$7:$B$46,MATCH(A17,Inventario!$A$7:$A$46,0))) | C17: =IF(A17="","",INDEX(Inventario!$G$7:$G$46,MATCH(A17,Inventario!$A$7:$A$46,0))) | F17: =IF(A17="","",INDEX(Inventario!$I$7:$I$46,MATCH(A17,Inventario!$A$7:$A$46,0))) | G17: =IF(A17="",0,SUMPRODUCT(('Uso diario'!$B$7:$B$1006=A17)*('Uso diario'!$A$7:$A$1006>=D17)*('Uso diario'!$A$7:$A$1006<=E17)*('Uso diario'!$G$7:$G$1006>0))) -> 0 | H17: =IF(A17="",0,SUMIFS('Uso diario'!$G$7:$G$1006,'Uso diario'!$B$7:$B$1006,A17,'Uso diario'!$A$7:$A$1006,">="&D17,'Uso diario'!$A$7:$A$1006,"<="&E17)) -> 0 | I17: =IF(A17="","",G17*INDEX(Inventario!$J$7:$J$46,MATCH(A17,Inventario!$A$7:$A$46,0))) | J17: =IF(A17="","",IF(F17="hora",MAX(H17,I17),MAX(G17,I17))) | K17: =IF(A17="","",INDEX(Inventario!$H$7:$H$46,MATCH(A17,Inventario!$A$7:$A$46,0))) | M17: =IF(A17="","",J17*K17+N(L17)) | O17: =IF(OR(A17="",N17=""),"",IF(ABS(N17-M17)<1,"Cuadra",IF(N17>M17,"Cobro de más: $"&TEXT(N17-M17,"#,##0.00"),"Cobro de menos: $"&TEXT(M17-N17,"#,##0.00"))))
B18: =IF(A18="","",INDEX(Inventario!$B$7:$B$46,MATCH(A18,Inventario!$A$7:$A$46,0))) | C18: =IF(A18="","",INDEX(Inventario!$G$7:$G$46,MATCH(A18,Inventario!$A$7:$A$46,0))) | F18: =IF(A18="","",INDEX(Inventario!$I$7:$I$46,MATCH(A18,Inventario!$A$7:$A$46,0))) | G18: =IF(A18="",0,SUMPRODUCT(('Uso diario'!$B$7:$B$1006=A18)*('Uso diario'!$A$7:$A$1006>=D18)*('Uso diario'!$A$7:$A$1006<=E18)*('Uso diario'!$G$7:$G$1006>0))) -> 0 | H18: =IF(A18="",0,SUMIFS('Uso diario'!$G$7:$G$1006,'Uso diario'!$B$7:$B$1006,A18,'Uso diario'!$A$7:$A$1006,">="&D18,'Uso diario'!$A$7:$A$1006,"<="&E18)) -> 0 | I18: =IF(A18="","",G18*INDEX(Inventario!$J$7:$J$46,MATCH(A18,Inventario!$A$7:$A$46,0))) | J18: =IF(A18="","",IF(F18="hora",MAX(H18,I18),MAX(G18,I18))) | K18: =IF(A18="","",INDEX(Inventario!$H$7:$H$46,MATCH(A18,Inventario!$A$7:$A$46,0))) | M18: =IF(A18="","",J18*K18+N(L18)) | O18: =IF(OR(A18="",N18=""),"",IF(ABS(N18-M18)<1,"Cuadra",IF(N18>M18,"Cobro de más: $"&TEXT(N18-M18,"#,##0.00"),"Cobro de menos: $"&TEXT(M18-N18,"#,##0.00"))))
B19: =IF(A19="","",INDEX(Inventario!$B$7:$B$46,MATCH(A19,Inventario!$A$7:$A$46,0))) | C19: =IF(A19="","",INDEX(Inventario!$G$7:$G$46,MATCH(A19,Inventario!$A$7:$A$46,0))) | F19: =IF(A19="","",INDEX(Inventario!$I$7:$I$46,MATCH(A19,Inventario!$A$7:$A$46,0))) | G19: =IF(A19="",0,SUMPRODUCT(('Uso diario'!$B$7:$B$1006=A19)*('Uso diario'!$A$7:$A$1006>=D19)*('Uso diario'!$A$7:$A$1006<=E19)*('Uso diario'!$G$7:$G$1006>0))) -> 0 | H19: =IF(A19="",0,SUMIFS('Uso diario'!$G$7:$G$1006,'Uso diario'!$B$7:$B$1006,A19,'Uso diario'!$A$7:$A$1006,">="&D19,'Uso diario'!$A$7:$A$1006,"<="&E19)) -> 0 | I19: =IF(A19="","",G19*INDEX(Inventario!$J$7:$J$46,MATCH(A19,Inventario!$A$7:$A$46,0))) | J19: =IF(A19="","",IF(F19="hora",MAX(H19,I19),MAX(G19,I19))) | K19: =IF(A19="","",INDEX(Inventario!$H$7:$H$46,MATCH(A19,Inventario!$A$7:$A$46,0))) | M19: =IF(A19="","",J19*K19+N(L19)) | O19: =IF(OR(A19="",N19=""),"",IF(ABS(N19-M19)<1,"Cuadra",IF(N19>M19,"Cobro de más: $"&TEXT(N19-M19,"#,##0.00"),"Cobro de menos: $"&TEXT(M19-N19,"#,##0.00"))))
... B36: =IF(A36="","",INDEX(Inventario!$B$7:$B$46,MATCH(A36,Inventario!$A$7:$A$46,0))) | C36: =IF(A36="","",INDEX(Inventario!$G$7:$G$46,MATCH(A36,Inventario!$A$7:$A$46,0))) | F36: =IF(A36="","",INDEX(Inventario!$I$7:$I$46,MATCH(A36,Inventario!$A$7:$A$46,0))) | G36: =IF(A36="",0,SUMPRODUCT(('Uso diario'!$B$7:$B$1006=A36)*('Uso diario'!$A$7:$A$1006>=D36)*('Uso diario'!$A$7:$A$1006<=E36)*('Uso diario'!$G$7:$G$1006>0))) -> 0 | H36: =IF(A36="",0,SUMIFS('Uso diario'!$G$7:$G$1006,'Uso diario'!$B$7:$B$1006,A36,'Uso diario'!$A$7:$A$1006,">="&D36,'Uso diario'!$A$7:$A$1006,"<="&E36)) -> 0 | I36: =IF(A36="","",G36*INDEX(Inventario!$J$7:$J$46,MATCH(A36,Inventario!$A$7:$A$46,0))) | J36: =IF(A36="","",IF(F36="hora",MAX(H36,I36),MAX(G36,I36))) | K36: =IF(A36="","",INDEX(Inventario!$H$7:$H$46,MATCH(A36,Inventario!$A$7:$A$46,0))) | M36: =IF(A36="","",J36*K36+N(L36)) | O36: =IF(OR(A36="",N36=""),"",IF(ABS(N36-M36)<1,"Cuadra",IF(N36>M36,"Cobro de más: $"&TEXT(N36-M36,"#,##0.00"),"Cobro de menos: $"&TEXT(M36-N36,"#,##0.00"))))
A38: Las horas por falla del equipo rentado van en «Horas inactivas» y no se suman a las horas trabajadas, por lo que no se pagan (cláusula de MANTENIMIENTO del contrato de arrendamiento). Los «Días con uso» cuentan días con horas trabajadas mayores a cero. Para tarifas semanales o mensuales ajusta la cantidad a pagar con la factura.

Sheet Mantenimiento
A1: VÉRTICE · Ingeniería, Arquitectura y Proyectos
A2: PROGRAMA DE MANTENIMIENTO POR HORÓMETRO
A3: Obra:
A4: Contrato:
A6: Clave | B6: Equipo | C6: Servicio | D6: Intervalo (horas) | E6: Horómetro del último servicio | F6: Próximo servicio (horómetro) | G6: Horómetro actual | H6: Horas restantes | I6: Estatus
A7: EQ-03 | B7: =IF(A7="","",IFERROR(INDEX(Inventario!$B$7:$B$46,MATCH(A7,Inventario!$A$7:$A$46,0)),"")) -> 0 | C7: Cambio de aceite de motor y filtros | D7: 250 | E7: 1100 | F7: =IF(A7="","",E7+D7) -> 1350 | G7: =IF(A7="","",IFERROR(INDEX(Inventario!$N$7:$N$46,MATCH(A7,Inventario!$A$7:$A$46,0)),0)) -> 1264 | H7: =IF(A7="","",F7-G7) -> 86 | I7: =IF(A7="","",IF(N(G7)=0,"Sin lectura",IF(H7<=0,"VENCIDO",IF(H7<=0.1*D7,"Programar","OK")))) -> OK
A8: EQ-03 | B8: =IF(A8="","",IFERROR(INDEX(Inventario!$B$7:$B$46,MATCH(A8,Inventario!$A$7:$A$46,0)),"")) -> 0 | C8: Engrase general | D8: 50 | E8: 1250 | F8: =IF(A8="","",E8+D8) -> 1300 | G8: =IF(A8="","",IFERROR(INDEX(Inventario!$N$7:$N$46,MATCH(A8,Inventario!$A$7:$A$46,0)),0)) -> 1264 | H8: =IF(A8="","",F8-G8) -> 36 | I8: =IF(A8="","",IF(N(G8)=0,"Sin lectura",IF(H8<=0,"VENCIDO",IF(H8<=0.1*D8,"Programar","OK")))) -> OK
A9: EQ-01 | B9: =IF(A9="","",IFERROR(INDEX(Inventario!$B$7:$B$46,MATCH(A9,Inventario!$A$7:$A$46,0)),"")) -> Revolvedora de 1 saco | C9: Revisión de banda y tambor | D9: 100 | E9: 0 | F9: =IF(A9="","",E9+D9) -> 100 | G9: =IF(A9="","",IFERROR(INDEX(Inventario!$N$7:$N$46,MATCH(A9,Inventario!$A$7:$A$46,0)),0)) -> 0 | H9: =IF(A9="","",F9-G9) -> 100 | I9: =IF(A9="","",IF(N(G9)=0,"Sin lectura",IF(H9<=0,"VENCIDO",IF(H9<=0.1*D9,"Programar","OK")))) -> Sin lectura
B10: =IF(A10="","",IFERROR(INDEX(Inventario!$B$7:$B$46,MATCH(A10,Inventario!$A$7:$A$46,0)),"")) | F10: =IF(A10="","",E10+D10) | G10: =IF(A10="","",IFERROR(INDEX(Inventario!$N$7:$N$46,MATCH(A10,Inventario!$A$7:$A$46,0)),0)) | H10: =IF(A10="","",F10-G10) | I10: =IF(A10="","",IF(N(G10)=0,"Sin lectura",IF(H10<=0,"VENCIDO",IF(H10<=0.1*D10,"Programar","OK"))))
B11: =IF(A11="","",IFERROR(INDEX(Inventario!$B$7:$B$46,MATCH(A11,Inventario!$A$7:$A$46,0)),"")) | F11: =IF(A11="","",E11+D11) | G11: =IF(A11="","",IFERROR(INDEX(Inventario!$N$7:$N$46,MATCH(A11,Inventario!$A$7:$A$46,0)),0)) | H11: =IF(A11="","",F11-G11) | I11: =IF(A11="","",IF(N(G11)=0,"Sin lectura",IF(H11<=0,"VENCIDO",IF(H11<=0.1*D11,"Programar","OK"))))
B12: =IF(A12="","",IFERROR(INDEX(Inventario!$B$7:$B$46,MATCH(A12,Inventario!$A$7:$A$46,0)),"")) | F12: =IF(A12="","",E12+D12) | G12: =IF(A12="","",IFERROR(INDEX(Inventario!$N$7:$N$46,MATCH(A12,Inventario!$A$7:$A$46,0)),0)) | H12: =IF(A12="","",F12-G12) | I12: =IF(A12="","",IF(N(G12)=0,"Sin lectura",IF(H12<=0,"VENCIDO",IF(H12<=0.1*D12,"Programar","OK"))))
B13: =IF(A13="","",IFERROR(INDEX(Inventario!$B$7:$B$46,MATCH(A13,Inventario!$A$7:$A$46,0)),"")) | F13: =IF(A13="","",E13+D13) | G13: =IF(A13="","",IFERROR(INDEX(Inventario!$N$7:$N$46,MATCH(A13,Inventario!$A$7:$A$46,0)),0)) | H13: =IF(A13="","",F13-G13) | I13: =IF(A13="","",IF(N(G13)=0,"Sin lectura",IF(H13<=0,"VENCIDO",IF(H13<=0.1*D13,"Programar","OK"))))
B14: =IF(A14="","",IFERROR(INDEX(Inventario!$B$7:$B$46,MATCH(A14,Inventario!$A$7:$A$46,0)),"")) | F14: =IF(A14="","",E14+D14) | G14: =IF(A14="","",IFERROR(INDEX(Inventario!$N$7:$N$46,MATCH(A14,Inventario!$A$7:$A$46,0)),0)) | H14: =IF(A14="","",F14-G14) | I14: =IF(A14="","",IF(N(G14)=0,"Sin lectura",IF(H14<=0,"VENCIDO",IF(H14<=0.1*D14,"Programar","OK"))))
B15: =IF(A15="","",IFERROR(INDEX(Inventario!$B$7:$B$46,MATCH(A15,Inventario!$A$7:$A$46,0)),"")) | F15: =IF(A15="","",E15+D15) | G15: =IF(A15="","",IFERROR(INDEX(Inventario!$N$7:$N$46,MATCH(A15,Inventario!$A$7:$A$46,0)),0)) | H15: =IF(A15="","",F15-G15) | I15: =IF(A15="","",IF(N(G15)=0,"Sin lectura",IF(H15<=0,"VENCIDO",IF(H15<=0.1*D15,"Programar","OK"))))
B16: =IF(A16="","",IFERROR(INDEX(Inventario!$B$7:$B$46,MATCH(A16,Inventario!$A$7:$A$46,0)),"")) | F16: =IF(A16="","",E16+D16) | G16: =IF(A16="","",IFERROR(INDEX(Inventario!$N$7:$N$46,MATCH(A16,Inventario!$A$7:$A$46,0)),0)) | H16: =IF(A16="","",F16-G16) | I16: =IF(A16="","",IF(N(G16)=0,"Sin lectura",IF(H16<=0,"VENCIDO",IF(H16<=0.1*D16,"Programar","OK"))))
B17: =IF(A17="","",IFERROR(INDEX(Inventario!$B$7:$B$46,MATCH(A17,Inventario!$A$7:$A$46,0)),"")) | F17: =IF(A17="","",E17+D17) | G17: =IF(A17="","",IFERROR(INDEX(Inventario!$N$7:$N$46,MATCH(A17,Inventario!$A$7:$A$46,0)),0)) | H17: =IF(A17="","",F17-G17) | I17: =IF(A17="","",IF(N(G17)=0,"Sin lectura",IF(H17<=0,"VENCIDO",IF(H17<=0.1*D17,"Programar","OK"))))
B18: =IF(A18="","",IFERROR(INDEX(Inventario!$B$7:$B$46,MATCH(A18,Inventario!$A$7:$A$46,0)),"")) | F18: =IF(A18="","",E18+D18) | G18: =IF(A18="","",IFERROR(INDEX(Inventario!$N$7:$N$46,MATCH(A18,Inventario!$A$7:$A$46,0)),0)) | H18: =IF(A18="","",F18-G18) | I18: =IF(A18="","",IF(N(G18)=0,"Sin lectura",IF(H18<=0,"VENCIDO",IF(H18<=0.1*D18,"Programar","OK"))))
B19: =IF(A19="","",IFERROR(INDEX(Inventario!$B$7:$B$46,MATCH(A19,Inventario!$A$7:$A$46,0)),"")) | F19: =IF(A19="","",E19+D19) | G19: =IF(A19="","",IFERROR(INDEX(Inventario!$N$7:$N$46,MATCH(A19,Inventario!$A$7:$A$46,0)),0)) | H19: =IF(A19="","",F19-G19) | I19: =IF(A19="","",IF(N(G19)=0,"Sin lectura",IF(H19<=0,"VENCIDO",IF(H19<=0.1*D19,"Programar","OK"))))
B20: =IF(A20="","",IFERROR(INDEX(Inventario!$B$7:$B$46,MATCH(A20,Inventario!$A$7:$A$46,0)),"")) | F20: =IF(A20="","",E20+D20) | G20: =IF(A20="","",IFERROR(INDEX(Inventario!$N$7:$N$46,MATCH(A20,Inventario!$A$7:$A$46,0)),0)) | H20: =IF(A20="","",F20-G20) | I20: =IF(A20="","",IF(N(G20)=0,"Sin lectura",IF(H20<=0,"VENCIDO",IF(H20<=0.1*D20,"Programar","OK"))))
B21: =IF(A21="","",IFERROR(INDEX(Inventario!$B$7:$B$46,MATCH(A21,Inventario!$A$7:$A$46,0)),"")) | F21: =IF(A21="","",E21+D21) | G21: =IF(A21="","",IFERROR(INDEX(Inventario!$N$7:$N$46,MATCH(A21,Inventario!$A$7:$A$46,0)),0)) | H21: =IF(A21="","",F21-G21) | I21: =IF(A21="","",IF(N(G21)=0,"Sin lectura",IF(H21<=0,"VENCIDO",IF(H21<=0.1*D21,"Programar","OK"))))
... B66: =IF(A66="","",IFERROR(INDEX(Inventario!$B$7:$B$46,MATCH(A66,Inventario!$A$7:$A$46,0)),"")) | F66: =IF(A66="","",E66+D66) | G66: =IF(A66="","",IFERROR(INDEX(Inventario!$N$7:$N$46,MATCH(A66,Inventario!$A$7:$A$46,0)),0)) | H66: =IF(A66="","",F66-G66) | I66: =IF(A66="","",IF(N(G66)=0,"Sin lectura",IF(H66<=0,"VENCIDO",IF(H66<=0.1*D66,"Programar","OK"))))
