Workbook

Sheet Instrucciones
A1: VÉRTICE · Ingeniería, Arquitectura y Proyectos
A2: CONTROL DE PERSONAL, LISTA DE RAYA Y SUBCONTRATISTAS REPSE
A4: Captura
A5: Celdas amarillas con texto azul = datos que capturas. Texto negro = fórmulas: no escribas encima. La fila de ejemplo muestra el formato esperado; sustitúyela por tus datos.
A7: Para qué sirve:
A8: Plantilla de personal en obra, asistencia semanal con horas extra, lista de raya con costo real (FSR) y control documental de subcontratistas REPSE para saber a quién retenerle el pago.
A9: Cómo se llena:
A10: 1. «Datos»: lunes de la semana, jornada máxima semanal y el FSR. El FSR sale de VERTICE-CALCULO (costos.BaseDatos().fsr(sd)) con IMSS, INFONAVIT e ISN B.C. 2026.
A11: 2. «Plantilla»: alta de cada trabajador antes de que entre a obra (alta IMSS previa, SIROC, DC-3 y EPP).
A12: 3. «Asistencia»: horas trabajadas por día. Las horas extra se separan en dobles y triples con las reglas de «Datos».
A13: 4. «Lista de raya»: captura destajos, retenciones de IMSS e ISR (de tu sistema de nómina) y préstamos; el neto y el costo se calculan solos.
A14: 5. «Subcontratistas REPSE»: cada mes marca Sí/No por documento. Si falta uno o el REPSE vence, el estatus dice RETENER PAGO (cláusula de REGISTRO REPSE del subcontrato; art. 15 LFT).
... A18: Este libro tiene datos personales (NSS, CURP). Guárdalo con acceso restringido conforme a la Ley Federal de Protección de Datos Personales en Posesión de los Particulares.

Sheet Datos
A1: VÉRTICE · Ingeniería, Arquitectura y Proyectos
A2: CONTROL DE PERSONAL — PARÁMETROS
A3: Obra:
A4: Contrato:
A6: Semana que inicia (lunes) | B6: 46314
A7: Jornada máxima semanal (horas) | B7: 48 | C7: 48 h en 2026; 46 h desde 2027 (reforma DOF 3-mar-2026)
A8: Horas extra semanales pagadas al doble | B8: 9 | C8: Art. 67-68 LFT vigente; ajusta con la reforma
A9: Horas de la jornada diaria | B9: 8
A10: Salario mínimo diario ZLFN 2026 | B10: 440.87 | C10: Zona Libre de la Frontera Norte (fuente: mano-obra.json de VERTICE-CALCULO)
A11: Factor de salario real (FSR) | B11: 1.62 | C11: Calcúlalo con VERTICE-CALCULO; depende del SD y de tu prima de riesgo

Sheet Plantilla
A1: VÉRTICE · Ingeniería, Arquitectura y Proyectos
A2: PLANTILLA DE PERSONAL EN OBRA
A3: Obra:
A4: Contrato:
A6: No. | B6: Nombre completo | C6: Categoría | D6: Empresa (propio / subcontratista) | E6: NSS | F6: CURP | G6: Fecha alta IMSS | H6: Salario diario | I6: Ingreso a obra | J6: DC-3 vigente | K6: EPP entregado (fecha) | L6: Activo | M6: Alerta
A7: 1 | B7: Maestro de obra (ejemplo) | C7: Maestro | D7: Propio | G7: 46313 | H7: 1050 | I7: 46314 | J7: Sí | K7: 46314 | L7: Sí | M7: =IF(B7="","",IF(H7<Datos!$B$10,"SD menor al mínimo ZLFN",IF(OR(G7="",G7>I7),"Alta IMSS posterior al ingreso",IF(K7="","Sin EPP",""))))
A8: 2 | B8: Oficial albañil (ejemplo) | C8: Oficial albañil | D8: Propio | G8: 46313 | H8: 630 | I8: 46314 | J8: Sí | K8: 46314 | L8: Sí | M8: =IF(B8="","",IF(H8<Datos!$B$10,"SD menor al mínimo ZLFN",IF(OR(G8="",G8>I8),"Alta IMSS posterior al ingreso",IF(K8="","Sin EPP",""))))
A9: 3 | B9: Oficial tablaroquero (ejemplo) | C9: Oficial yesero | D9: Propio | G9: 46313 | H9: 640 | I9: 46314 | J9: Sí | K9: 46314 | L9: Sí | M9: =IF(B9="","",IF(H9<Datos!$B$10,"SD menor al mínimo ZLFN",IF(OR(G9="",G9>I9),"Alta IMSS posterior al ingreso",IF(K9="","Sin EPP",""))))
A10: 4 | B10: Ayudante general (ejemplo) | C10: Peón | D10: Propio | G10: 46313 | H10: 505 | I10: 46314 | J10: Sí | K10: 46314 | L10: Sí | M10: =IF(B10="","",IF(H10<Datos!$B$10,"SD menor al mínimo ZLFN",IF(OR(G10="",G10>I10),"Alta IMSS posterior al ingreso",IF(K10="","Sin EPP",""))))
A11: 5 | B11: Oficial electricista (ejemplo) | C11: Oficial electricista | D11: Propio | G11: 46313 | H11: 710 | I11: 46314 | J11: Sí | K11: 46314 | L11: Sí | M11: =IF(B11="","",IF(H11<Datos!$B$10,"SD menor al mínimo ZLFN",IF(OR(G11="",G11>I11),"Alta IMSS posterior al ingreso",IF(K11="","Sin EPP",""))))
A12: 6 | B12: Ayudante general 2 (ejemplo) | C12: Peón | D12: Propio | G12: 46313 | H12: 430 | I12: 46314 | J12: No | K12: 46314 | L12: Sí | M12: =IF(B12="","",IF(H12<Datos!$B$10,"SD menor al mínimo ZLFN",IF(OR(G12="",G12>I12),"Alta IMSS posterior al ingreso",IF(K12="","Sin EPP","")))) -> SD menor al mínimo ZLFN
A13: 7 | M13: =IF(B13="","",IF(H13<Datos!$B$10,"SD menor al mínimo ZLFN",IF(OR(G13="",G13>I13),"Alta IMSS posterior al ingreso",IF(K13="","Sin EPP",""))))
A14: 8 | M14: =IF(B14="","",IF(H14<Datos!$B$10,"SD menor al mínimo ZLFN",IF(OR(G14="",G14>I14),"Alta IMSS posterior al ingreso",IF(K14="","Sin EPP",""))))
A15: 9 | M15: =IF(B15="","",IF(H15<Datos!$B$10,"SD menor al mínimo ZLFN",IF(OR(G15="",G15>I15),"Alta IMSS posterior al ingreso",IF(K15="","Sin EPP",""))))
A16: 10 | M16: =IF(B16="","",IF(H16<Datos!$B$10,"SD menor al mínimo ZLFN",IF(OR(G16="",G16>I16),"Alta IMSS posterior al ingreso",IF(K16="","Sin EPP",""))))
A17: 11 | M17: =IF(B17="","",IF(H17<Datos!$B$10,"SD menor al mínimo ZLFN",IF(OR(G17="",G17>I17),"Alta IMSS posterior al ingreso",IF(K17="","Sin EPP",""))))
A18: 12 | M18: =IF(B18="","",IF(H18<Datos!$B$10,"SD menor al mínimo ZLFN",IF(OR(G18="",G18>I18),"Alta IMSS posterior al ingreso",IF(K18="","Sin EPP",""))))
A19: 13 | M19: =IF(B19="","",IF(H19<Datos!$B$10,"SD menor al mínimo ZLFN",IF(OR(G19="",G19>I19),"Alta IMSS posterior al ingreso",IF(K19="","Sin EPP",""))))
A20: 14 | M20: =IF(B20="","",IF(H20<Datos!$B$10,"SD menor al mínimo ZLFN",IF(OR(G20="",G20>I20),"Alta IMSS posterior al ingreso",IF(K20="","Sin EPP",""))))
A21: 15 | M21: =IF(B21="","",IF(H21<Datos!$B$10,"SD menor al mínimo ZLFN",IF(OR(G21="",G21>I21),"Alta IMSS posterior al ingreso",IF(K21="","Sin EPP",""))))
A22: 16 | M22: =IF(B22="","",IF(H22<Datos!$B$10,"SD menor al mínimo ZLFN",IF(OR(G22="",G22>I22),"Alta IMSS posterior al ingreso",IF(K22="","Sin EPP",""))))
A23: 17 | M23: =IF(B23="","",IF(H23<Datos!$B$10,"SD menor al mínimo ZLFN",IF(OR(G23="",G23>I23),"Alta IMSS posterior al ingreso",IF(K23="","Sin EPP",""))))
A24: 18 | M24: =IF(B24="","",IF(H24<Datos!$B$10,"SD menor al mínimo ZLFN",IF(OR(G24="",G24>I24),"Alta IMSS posterior al ingreso",IF(K24="","Sin EPP",""))))
... A86: 80 | M86: =IF(B86="","",IF(H86<Datos!$B$10,"SD menor al mínimo ZLFN",IF(OR(G86="",G86>I86),"Alta IMSS posterior al ingreso",IF(K86="","Sin EPP",""))))

Sheet Asistencia
A1: VÉRTICE · Ingeniería, Arquitectura y Proyectos
A2: ASISTENCIA Y HORAS DE LA SEMANA
A3: Obra:
A4: Contrato:
D5: =Datos!$B$6+0 -> 46314 | E5: =Datos!$B$6+1 -> 46315 | F5: =Datos!$B$6+2 -> 46316 | G5: =Datos!$B$6+3 -> 46317 | H5: =Datos!$B$6+4 -> 46318 | I5: =Datos!$B$6+5 -> 46319 | J5: =Datos!$B$6+6 -> 46320
A6: No. | B6: Nombre | C6: Categoría | D6: Lun | E6: Mar | F6: Mié | G6: Jue | H6: Vie | I6: Sáb | J6: Dom | K6: Horas totales | L6: Días trabajados | M6: Horas ordinarias | N6: Extra dobles | O6: Extra triples
A7: =Plantilla!A7 -> 1 | B7: =IF(Plantilla!B7="","",Plantilla!B7) -> Maestro de obra (ejemplo) | C7: =IF(Plantilla!C7="","",Plantilla!C7) -> Maestro | D7: 9 | E7: 9 | F7: 9 | G7: 9 | H7: 9 | I7: 6 | J7: 0 | K7: =SUM(D7:J7) -> 51 | L7: =COUNTIF(D7:J7,">0") -> 6 | M7: =MIN(K7,Datos!$B$7) -> 48 | N7: =MIN(MAX(0,K7-Datos!$B$7),Datos!$B$8) -> 3 | O7: =MAX(0,K7-Datos!$B$7-Datos!$B$8) -> 0
A8: =Plantilla!A8 -> 2 | B8: =IF(Plantilla!B8="","",Plantilla!B8) -> Oficial albañil (ejemplo) | C8: =IF(Plantilla!C8="","",Plantilla!C8) -> Oficial albañil | D8: 9 | E8: 9 | F8: 9 | G8: 9 | H8: 9 | I8: 6 | J8: 0 | K8: =SUM(D8:J8) -> 51 | L8: =COUNTIF(D8:J8,">0") -> 6 | M8: =MIN(K8,Datos!$B$7) -> 48 | N8: =MIN(MAX(0,K8-Datos!$B$7),Datos!$B$8) -> 3 | O8: =MAX(0,K8-Datos!$B$7-Datos!$B$8) -> 0
A9: =Plantilla!A9 -> 3 | B9: =IF(Plantilla!B9="","",Plantilla!B9) -> Oficial tablaroquero (ejemplo) | C9: =IF(Plantilla!C9="","",Plantilla!C9) -> Oficial yesero | D9: 9 | E9: 9 | F9: 9 | G9: 9 | H9: 9 | I9: 6 | J9: 0 | K9: =SUM(D9:J9) -> 51 | L9: =COUNTIF(D9:J9,">0") -> 6 | M9: =MIN(K9,Datos!$B$7) -> 48 | N9: =MIN(MAX(0,K9-Datos!$B$7),Datos!$B$8) -> 3 | O9: =MAX(0,K9-Datos!$B$7-Datos!$B$8) -> 0
A10: =Plantilla!A10 -> 4 | B10: =IF(Plantilla!B10="","",Plantilla!B10) -> Ayudante general (ejemplo) | C10: =IF(Plantilla!C10="","",Plantilla!C10) -> Peón | D10: 9 | E10: 9 | F10: 9 | G10: 9 | H10: 9 | I10: 6 | J10: 0 | K10: =SUM(D10:J10) -> 51 | L10: =COUNTIF(D10:J10,">0") -> 6 | M10: =MIN(K10,Datos!$B$7) -> 48 | N10: =MIN(MAX(0,K10-Datos!$B$7),Datos!$B$8) -> 3 | O10: =MAX(0,K10-Datos!$B$7-Datos!$B$8) -> 0
A11: =Plantilla!A11 -> 5 | B11: =IF(Plantilla!B11="","",Plantilla!B11) -> Oficial electricista (ejemplo) | C11: =IF(Plantilla!C11="","",Plantilla!C11) -> Oficial electricista | D11: 9 | E11: 9 | F11: 9 | G11: 9 | H11: 9 | I11: 6 | J11: 0 | K11: =SUM(D11:J11) -> 51 | L11: =COUNTIF(D11:J11,">0") -> 6 | M11: =MIN(K11,Datos!$B$7) -> 48 | N11: =MIN(MAX(0,K11-Datos!$B$7),Datos!$B$8) -> 3 | O11: =MAX(0,K11-Datos!$B$7-Datos!$B$8) -> 0
A12: =Plantilla!A12 -> 6 | B12: =IF(Plantilla!B12="","",Plantilla!B12) -> Ayudante general 2 (ejemplo) | C12: =IF(Plantilla!C12="","",Plantilla!C12) -> Peón | D12: 9 | E12: 9 | F12: 9 | G12: 9 | H12: 9 | I12: 6 | J12: 0 | K12: =SUM(D12:J12) -> 51 | L12: =COUNTIF(D12:J12,">0") -> 6 | M12: =MIN(K12,Datos!$B$7) -> 48 | N12: =MIN(MAX(0,K12-Datos!$B$7),Datos!$B$8) -> 3 | O12: =MAX(0,K12-Datos!$B$7-Datos!$B$8) -> 0
A13: =Plantilla!A13 -> 7 | B13: =IF(Plantilla!B13="","",Plantilla!B13) | C13: =IF(Plantilla!C13="","",Plantilla!C13) | K13: =SUM(D13:J13) -> 0 | L13: =COUNTIF(D13:J13,">0") -> 0 | M13: =MIN(K13,Datos!$B$7) -> 0 | N13: =MIN(MAX(0,K13-Datos!$B$7),Datos!$B$8) -> 0 | O13: =MAX(0,K13-Datos!$B$7-Datos!$B$8) -> 0
A14: =Plantilla!A14 -> 8 | B14: =IF(Plantilla!B14="","",Plantilla!B14) | C14: =IF(Plantilla!C14="","",Plantilla!C14) | K14: =SUM(D14:J14) -> 0 | L14: =COUNTIF(D14:J14,">0") -> 0 | M14: =MIN(K14,Datos!$B$7) -> 0 | N14: =MIN(MAX(0,K14-Datos!$B$7),Datos!$B$8) -> 0 | O14: =MAX(0,K14-Datos!$B$7-Datos!$B$8) -> 0
A15: =Plantilla!A15 -> 9 | B15: =IF(Plantilla!B15="","",Plantilla!B15) | C15: =IF(Plantilla!C15="","",Plantilla!C15) | K15: =SUM(D15:J15) -> 0 | L15: =COUNTIF(D15:J15,">0") -> 0 | M15: =MIN(K15,Datos!$B$7) -> 0 | N15: =MIN(MAX(0,K15-Datos!$B$7),Datos!$B$8) -> 0 | O15: =MAX(0,K15-Datos!$B$7-Datos!$B$8) -> 0
A16: =Plantilla!A16 -> 10 | B16: =IF(Plantilla!B16="","",Plantilla!B16) | C16: =IF(Plantilla!C16="","",Plantilla!C16) | K16: =SUM(D16:J16) -> 0 | L16: =COUNTIF(D16:J16,">0") -> 0 | M16: =MIN(K16,Datos!$B$7) -> 0 | N16: =MIN(MAX(0,K16-Datos!$B$7),Datos!$B$8) -> 0 | O16: =MAX(0,K16-Datos!$B$7-Datos!$B$8) -> 0
A17: =Plantilla!A17 -> 11 | B17: =IF(Plantilla!B17="","",Plantilla!B17) | C17: =IF(Plantilla!C17="","",Plantilla!C17) | K17: =SUM(D17:J17) -> 0 | L17: =COUNTIF(D17:J17,">0") -> 0 | M17: =MIN(K17,Datos!$B$7) -> 0 | N17: =MIN(MAX(0,K17-Datos!$B$7),Datos!$B$8) -> 0 | O17: =MAX(0,K17-Datos!$B$7-Datos!$B$8) -> 0
A18: =Plantilla!A18 -> 12 | B18: =IF(Plantilla!B18="","",Plantilla!B18) | C18: =IF(Plantilla!C18="","",Plantilla!C18) | K18: =SUM(D18:J18) -> 0 | L18: =COUNTIF(D18:J18,">0") -> 0 | M18: =MIN(K18,Datos!$B$7) -> 0 | N18: =MIN(MAX(0,K18-Datos!$B$7),Datos!$B$8) -> 0 | O18: =MAX(0,K18-Datos!$B$7-Datos!$B$8) -> 0
A19: =Plantilla!A19 -> 13 | B19: =IF(Plantilla!B19="","",Plantilla!B19) | C19: =IF(Plantilla!C19="","",Plantilla!C19) | K19: =SUM(D19:J19) -> 0 | L19: =COUNTIF(D19:J19,">0") -> 0 | M19: =MIN(K19,Datos!$B$7) -> 0 | N19: =MIN(MAX(0,K19-Datos!$B$7),Datos!$B$8) -> 0 | O19: =MAX(0,K19-Datos!$B$7-Datos!$B$8) -> 0
A20: =Plantilla!A20 -> 14 | B20: =IF(Plantilla!B20="","",Plantilla!B20) | C20: =IF(Plantilla!C20="","",Plantilla!C20) | K20: =SUM(D20:J20) -> 0 | L20: =COUNTIF(D20:J20,">0") -> 0 | M20: =MIN(K20,Datos!$B$7) -> 0 | N20: =MIN(MAX(0,K20-Datos!$B$7),Datos!$B$8) -> 0 | O20: =MAX(0,K20-Datos!$B$7-Datos!$B$8) -> 0
A21: =Plantilla!A21 -> 15 | B21: =IF(Plantilla!B21="","",Plantilla!B21) | C21: =IF(Plantilla!C21="","",Plantilla!C21) | K21: =SUM(D21:J21) -> 0 | L21: =COUNTIF(D21:J21,">0") -> 0 | M21: =MIN(K21,Datos!$B$7) -> 0 | N21: =MIN(MAX(0,K21-Datos!$B$7),Datos!$B$8) -> 0 | O21: =MAX(0,K21-Datos!$B$7-Datos!$B$8) -> 0
A22: =Plantilla!A22 -> 16 | B22: =IF(Plantilla!B22="","",Plantilla!B22) | C22: =IF(Plantilla!C22="","",Plantilla!C22) | K22: =SUM(D22:J22) -> 0 | L22: =COUNTIF(D22:J22,">0") -> 0 | M22: =MIN(K22,Datos!$B$7) -> 0 | N22: =MIN(MAX(0,K22-Datos!$B$7),Datos!$B$8) -> 0 | O22: =MAX(0,K22-Datos!$B$7-Datos!$B$8) -> 0
A23: =Plantilla!A23 -> 17 | B23: =IF(Plantilla!B23="","",Plantilla!B23) | C23: =IF(Plantilla!C23="","",Plantilla!C23) | K23: =SUM(D23:J23) -> 0 | L23: =COUNTIF(D23:J23,">0") -> 0 | M23: =MIN(K23,Datos!$B$7) -> 0 | N23: =MIN(MAX(0,K23-Datos!$B$7),Datos!$B$8) -> 0 | O23: =MAX(0,K23-Datos!$B$7-Datos!$B$8) -> 0
A24: =Plantilla!A24 -> 18 | B24: =IF(Plantilla!B24="","",Plantilla!B24) | C24: =IF(Plantilla!C24="","",Plantilla!C24) | K24: =SUM(D24:J24) -> 0 | L24: =COUNTIF(D24:J24,">0") -> 0 | M24: =MIN(K24,Datos!$B$7) -> 0 | N24: =MIN(MAX(0,K24-Datos!$B$7),Datos!$B$8) -> 0 | O24: =MAX(0,K24-Datos!$B$7-Datos!$B$8) -> 0
... A86: =Plantilla!A86 -> 80 | B86: =IF(Plantilla!B86="","",Plantilla!B86) | C86: =IF(Plantilla!C86="","",Plantilla!C86) | K86: =SUM(D86:J86) -> 0 | L86: =COUNTIF(D86:J86,">0") -> 0 | M86: =MIN(K86,Datos!$B$7) -> 0 | N86: =MIN(MAX(0,K86-Datos!$B$7),Datos!$B$8) -> 0 | O86: =MAX(0,K86-Datos!$B$7-Datos!$B$8) -> 0

Sheet Lista de raya
A1: VÉRTICE · Ingeniería, Arquitectura y Proyectos
A2: LISTA DE RAYA SEMANAL
A3: Obra:
A4: Contrato:
A6: No. | B6: Nombre | C6: Salario diario | D6: Días trabajados | E6: Sueldo | F6: Séptimo día | G6: Horas extra | H6: Destajo / bonos | I6: Total percepciones | J6: Retención IMSS | K6: Retención ISR | L6: Préstamos / anticipos | M6: NETO A PAGAR | N6: Costo real empresa | O6: Firma
A7: =Plantilla!A7 -> 1 | B7: =Asistencia!B7 -> Maestro de obra (ejemplo) | C7: =IF(Plantilla!H7="",0,Plantilla!H7) -> 1050 | D7: =MIN(6,Asistencia!L7) -> 6 | E7: =C7*D7 -> 6300 | F7: =C7*D7/6 -> 1050 | G7: =C7/Datos!$B$9*(2*Asistencia!N7+3*Asistencia!O7) -> 787.5 | I7: =SUM(E7:H7) -> 8137.5 | M7: =I7-J7-K7-L7 -> 8137.5 | N7: =(E7+F7)*Datos!$B$11+G7+H7 -> 12694.5
A8: =Plantilla!A8 -> 2 | B8: =Asistencia!B8 -> Oficial albañil (ejemplo) | C8: =IF(Plantilla!H8="",0,Plantilla!H8) -> 630 | D8: =MIN(6,Asistencia!L8) -> 6 | E8: =C8*D8 -> 3780 | F8: =C8*D8/6 -> 630 | G8: =C8/Datos!$B$9*(2*Asistencia!N8+3*Asistencia!O8) -> 472.5 | I8: =SUM(E8:H8) -> 4882.5 | M8: =I8-J8-K8-L8 -> 4882.5 | N8: =(E8+F8)*Datos!$B$11+G8+H8 -> 7616.7
A9: =Plantilla!A9 -> 3 | B9: =Asistencia!B9 -> Oficial tablaroquero (ejemplo) | C9: =IF(Plantilla!H9="",0,Plantilla!H9) -> 640 | D9: =MIN(6,Asistencia!L9) -> 6 | E9: =C9*D9 -> 3840 | F9: =C9*D9/6 -> 640 | G9: =C9/Datos!$B$9*(2*Asistencia!N9+3*Asistencia!O9) -> 480 | I9: =SUM(E9:H9) -> 4960 | M9: =I9-J9-K9-L9 -> 4960 | N9: =(E9+F9)*Datos!$B$11+G9+H9 -> 7737.6
A10: =Plantilla!A10 -> 4 | B10: =Asistencia!B10 -> Ayudante general (ejemplo) | C10: =IF(Plantilla!H10="",0,Plantilla!H10) -> 505 | D10: =MIN(6,Asistencia!L10) -> 6 | E10: =C10*D10 -> 3030 | F10: =C10*D10/6 -> 505 | G10: =C10/Datos!$B$9*(2*Asistencia!N10+3*Asistencia!O10) -> 378.75 | I10: =SUM(E10:H10) -> 3913.75 | M10: =I10-J10-K10-L10 -> 3913.75 | N10: =(E10+F10)*Datos!$B$11+G10+H10 -> 6105.45
A11: =Plantilla!A11 -> 5 | B11: =Asistencia!B11 -> Oficial electricista (ejemplo) | C11: =IF(Plantilla!H11="",0,Plantilla!H11) -> 710 | D11: =MIN(6,Asistencia!L11) -> 6 | E11: =C11*D11 -> 4260 | F11: =C11*D11/6 -> 710 | G11: =C11/Datos!$B$9*(2*Asistencia!N11+3*Asistencia!O11) -> 532.5 | I11: =SUM(E11:H11) -> 5502.5 | M11: =I11-J11-K11-L11 -> 5502.5 | N11: =(E11+F11)*Datos!$B$11+G11+H11 -> 8583.9
A12: =Plantilla!A12 -> 6 | B12: =Asistencia!B12 -> Ayudante general 2 (ejemplo) | C12: =IF(Plantilla!H12="",0,Plantilla!H12) -> 430 | D12: =MIN(6,Asistencia!L12) -> 6 | E12: =C12*D12 -> 2580 | F12: =C12*D12/6 -> 430 | G12: =C12/Datos!$B$9*(2*Asistencia!N12+3*Asistencia!O12) -> 322.5 | I12: =SUM(E12:H12) -> 3332.5 | M12: =I12-J12-K12-L12 -> 3332.5 | N12: =(E12+F12)*Datos!$B$11+G12+H12 -> 5198.7
A13: =Plantilla!A13 -> 7 | B13: =Asistencia!B13 | C13: =IF(Plantilla!H13="",0,Plantilla!H13) -> 0 | D13: =MIN(6,Asistencia!L13) -> 0 | E13: =C13*D13 -> 0 | F13: =C13*D13/6 -> 0 | G13: =C13/Datos!$B$9*(2*Asistencia!N13+3*Asistencia!O13) -> 0 | I13: =SUM(E13:H13) -> 0 | M13: =I13-J13-K13-L13 -> 0 | N13: =(E13+F13)*Datos!$B$11+G13+H13 -> 0
A14: =Plantilla!A14 -> 8 | B14: =Asistencia!B14 | C14: =IF(Plantilla!H14="",0,Plantilla!H14) -> 0 | D14: =MIN(6,Asistencia!L14) -> 0 | E14: =C14*D14 -> 0 | F14: =C14*D14/6 -> 0 | G14: =C14/Datos!$B$9*(2*Asistencia!N14+3*Asistencia!O14) -> 0 | I14: =SUM(E14:H14) -> 0 | M14: =I14-J14-K14-L14 -> 0 | N14: =(E14+F14)*Datos!$B$11+G14+H14 -> 0
A15: =Plantilla!A15 -> 9 | B15: =Asistencia!B15 | C15: =IF(Plantilla!H15="",0,Plantilla!H15) -> 0 | D15: =MIN(6,Asistencia!L15) -> 0 | E15: =C15*D15 -> 0 | F15: =C15*D15/6 -> 0 | G15: =C15/Datos!$B$9*(2*Asistencia!N15+3*Asistencia!O15) -> 0 | I15: =SUM(E15:H15) -> 0 | M15: =I15-J15-K15-L15 -> 0 | N15: =(E15+F15)*Datos!$B$11+G15+H15 -> 0
A16: =Plantilla!A16 -> 10 | B16: =Asistencia!B16 | C16: =IF(Plantilla!H16="",0,Plantilla!H16) -> 0 | D16: =MIN(6,Asistencia!L16) -> 0 | E16: =C16*D16 -> 0 | F16: =C16*D16/6 -> 0 | G16: =C16/Datos!$B$9*(2*Asistencia!N16+3*Asistencia!O16) -> 0 | I16: =SUM(E16:H16) -> 0 | M16: =I16-J16-K16-L16 -> 0 | N16: =(E16+F16)*Datos!$B$11+G16+H16 -> 0
A17: =Plantilla!A17 -> 11 | B17: =Asistencia!B17 | C17: =IF(Plantilla!H17="",0,Plantilla!H17) -> 0 | D17: =MIN(6,Asistencia!L17) -> 0 | E17: =C17*D17 -> 0 | F17: =C17*D17/6 -> 0 | G17: =C17/Datos!$B$9*(2*Asistencia!N17+3*Asistencia!O17) -> 0 | I17: =SUM(E17:H17) -> 0 | M17: =I17-J17-K17-L17 -> 0 | N17: =(E17+F17)*Datos!$B$11+G17+H17 -> 0
A18: =Plantilla!A18 -> 12 | B18: =Asistencia!B18 | C18: =IF(Plantilla!H18="",0,Plantilla!H18) -> 0 | D18: =MIN(6,Asistencia!L18) -> 0 | E18: =C18*D18 -> 0 | F18: =C18*D18/6 -> 0 | G18: =C18/Datos!$B$9*(2*Asistencia!N18+3*Asistencia!O18) -> 0 | I18: =SUM(E18:H18) -> 0 | M18: =I18-J18-K18-L18 -> 0 | N18: =(E18+F18)*Datos!$B$11+G18+H18 -> 0
... A86: =Plantilla!A86 -> 80 | B86: =Asistencia!B86 | C86: =IF(Plantilla!H86="",0,Plantilla!H86) -> 0 | D86: =MIN(6,Asistencia!L86) -> 0 | E86: =C86*D86 -> 0 | F86: =C86*D86/6 -> 0 | G86: =C86/Datos!$B$9*(2*Asistencia!N86+3*Asistencia!O86) -> 0 | I86: =SUM(E86:H86) -> 0 | M86: =I86-J86-K86-L86 -> 0 | N86: =(E86+F86)*Datos!$B$11+G86+H86 -> 0
B87: TOTAL DE LA SEMANA | E87: =SUM(E7:E86) -> 23790 | F87: =SUM(F7:F86) -> 3965 | G87: =SUM(G7:G86) -> 2973.75 | H87: =SUM(H7:H86) -> 0 | I87: =SUM(I7:I86) -> 30728.75 | J87: =SUM(J7:J86) -> 0 | K87: =SUM(K7:K86) -> 0 | L87: =SUM(L7:L86) -> 0 | ... N87: =SUM(N7:N86) -> 47936.85
B88: Séptimo día proporcional (días trabajados / 6). Horas extra = salario por hora × 2 o × 3. El costo real aplica el FSR a sueldo y séptimo día.
B91: ____________________________ | H91: ____________________________
B92: Elaboró — administrador de obra | H92: Autorizó — superintendente

Sheet Subcontratistas REPSE
A1: VÉRTICE · Ingeniería, Arquitectura y Proyectos
A2: CONTROL DOCUMENTAL DE SUBCONTRATISTAS (REPSE)
A3: Obra:
A4: Contrato:
A6: Empresa | B6: RFC | C6: Especialidad | D6: No. REPSE | E6: Vigencia REPSE | F6: Días para vencer | G6: Trabajadores en obra | H6: Vinculado a SIROC | I6: Mes revisado | J6: CFDI nómina | K6: Pago IMSS | L6: Pago INFONAVIT | M6: Decl. ISR retenciones | N6: Decl. IVA y acuse | O6: ICSOE (cuatrim.) | P6: SISUB (cuatrim.) | Q6: Opinión 32-D positiva | R6: ESTATUS | S6: Observaciones
A7: Instalaciones Ejemplo, S.A. de C.V. | C7: Eléctrica | D7: REPSE-EJEMPLO-1 | E7: 46714 | F7: =IF(E7="","",E7-TODAY()) -> 400 | G7: 6 | H7: Sí | I7: 10/2026 | J7: Sí | K7: Sí | L7: Sí | M7: Sí | N7: Sí | O7: Sí | P7: Sí | Q7: Sí | R7: =IF(A7="","",IF(OR(D7="",AND(ISNUMBER(F7),F7<0),COUNTIF(H7:Q7,"No")>0),"RETENER PAGO",IF(AND(ISNUMBER(F7),F7<=30),"Renovar REPSE","OK"))) -> OK
A8: Plafones Ejemplo, S. de R.L. | C8: Tablaroca y plafones | D8: REPSE-EJEMPLO-2 | E8: 46334 | F8: =IF(E8="","",E8-TODAY()) -> 20 | G8: 8 | H8: Sí | I8: 10/2026 | J8: Sí | K8: No | L8: Sí | M8: Sí | N8: Sí | O8: Sí | P8: Sí | Q8: Sí | R8: =IF(A8="","",IF(OR(D8="",AND(ISNUMBER(F8),F8<0),COUNTIF(H8:Q8,"No")>0),"RETENER PAGO",IF(AND(ISNUMBER(F8),F8<=30),"Renovar REPSE","OK"))) -> RETENER PAGO
F9: =IF(E9="","",E9-TODAY()) | R9: =IF(A9="","",IF(OR(D9="",AND(ISNUMBER(F9),F9<0),COUNTIF(H9:Q9,"No")>0),"RETENER PAGO",IF(AND(ISNUMBER(F9),F9<=30),"Renovar REPSE","OK")))
F10: =IF(E10="","",E10-TODAY()) | R10: =IF(A10="","",IF(OR(D10="",AND(ISNUMBER(F10),F10<0),COUNTIF(H10:Q10,"No")>0),"RETENER PAGO",IF(AND(ISNUMBER(F10),F10<=30),"Renovar REPSE","OK")))
F11: =IF(E11="","",E11-TODAY()) | R11: =IF(A11="","",IF(OR(D11="",AND(ISNUMBER(F11),F11<0),COUNTIF(H11:Q11,"No")>0),"RETENER PAGO",IF(AND(ISNUMBER(F11),F11<=30),"Renovar REPSE","OK")))
F12: =IF(E12="","",E12-TODAY()) | R12: =IF(A12="","",IF(OR(D12="",AND(ISNUMBER(F12),F12<0),COUNTIF(H12:Q12,"No")>0),"RETENER PAGO",IF(AND(ISNUMBER(F12),F12<=30),"Renovar REPSE","OK")))
F13: =IF(E13="","",E13-TODAY()) | R13: =IF(A13="","",IF(OR(D13="",AND(ISNUMBER(F13),F13<0),COUNTIF(H13:Q13,"No")>0),"RETENER PAGO",IF(AND(ISNUMBER(F13),F13<=30),"Renovar REPSE","OK")))
F14: =IF(E14="","",E14-TODAY()) | R14: =IF(A14="","",IF(OR(D14="",AND(ISNUMBER(F14),F14<0),COUNTIF(H14:Q14,"No")>0),"RETENER PAGO",IF(AND(ISNUMBER(F14),F14<=30),"Renovar REPSE","OK")))
F15: =IF(E15="","",E15-TODAY()) | R15: =IF(A15="","",IF(OR(D15="",AND(ISNUMBER(F15),F15<0),COUNTIF(H15:Q15,"No")>0),"RETENER PAGO",IF(AND(ISNUMBER(F15),F15<=30),"Renovar REPSE","OK")))
F16: =IF(E16="","",E16-TODAY()) | R16: =IF(A16="","",IF(OR(D16="",AND(ISNUMBER(F16),F16<0),COUNTIF(H16:Q16,"No")>0),"RETENER PAGO",IF(AND(ISNUMBER(F16),F16<=30),"Renovar REPSE","OK")))
F17: =IF(E17="","",E17-TODAY()) | R17: =IF(A17="","",IF(OR(D17="",AND(ISNUMBER(F17),F17<0),COUNTIF(H17:Q17,"No")>0),"RETENER PAGO",IF(AND(ISNUMBER(F17),F17<=30),"Renovar REPSE","OK")))
F18: =IF(E18="","",E18-TODAY()) | R18: =IF(A18="","",IF(OR(D18="",AND(ISNUMBER(F18),F18<0),COUNTIF(H18:Q18,"No")>0),"RETENER PAGO",IF(AND(ISNUMBER(F18),F18<=30),"Renovar REPSE","OK")))
F19: =IF(E19="","",E19-TODAY()) | R19: =IF(A19="","",IF(OR(D19="",AND(ISNUMBER(F19),F19<0),COUNTIF(H19:Q19,"No")>0),"RETENER PAGO",IF(AND(ISNUMBER(F19),F19<=30),"Renovar REPSE","OK")))
F20: =IF(E20="","",E20-TODAY()) | R20: =IF(A20="","",IF(OR(D20="",AND(ISNUMBER(F20),F20<0),COUNTIF(H20:Q20,"No")>0),"RETENER PAGO",IF(AND(ISNUMBER(F20),F20<=30),"Renovar REPSE","OK")))
... F46: =IF(E46="","",E46-TODAY()) | R46: =IF(A46="","",IF(OR(D46="",AND(ISNUMBER(F46),F46<0),COUNTIF(H46:Q46,"No")>0),"RETENER PAGO",IF(AND(ISNUMBER(F46),F46<=30),"Renovar REPSE","OK")))
A48: Base: arts. 13-15 LFT (REPSE y responsabilidad solidaria), 15-A LSS (ICSOE), 29 Bis Ley INFONAVIT (SISUB), 27 fr. V LISR, 5 fr. II LIVA, 15-D y 32-D CFF. Sin REPSE capturado el estatus es RETENER PAGO.
