Workbook

Sheet Instrucciones
A1: VÉRTICE · Ingeniería, Arquitectura y Proyectos
A2: COTIZACIÓN CON ANÁLISIS DE PRECIOS
A4: Captura
A5: Celdas amarillas con texto azul = datos que capturas. Texto negro = fórmulas: no escribas encima. La fila de ejemplo muestra el formato esperado; sustitúyela por tus datos.
A7: Para qué sirve:
A8: Arma la cotización al cliente a partir del costo directo de cada concepto y del factor de sobrecosto (indirectos, financiamiento, utilidad y cargos adicionales), con la misma fórmula de VERTICE-CALCULO (costos.Sobrecosto.factor).
A9: Cómo se llena:
A10: 1. «Datos»: cliente, obra, vigencia, porcentajes de sobrecosto y condiciones comerciales.
A11: 2. «Indirectos»: los gastos de campo de la obra (superintendente, residente, seguridad, renta de oficina, fianzas). Su porcentaje pasa solo a «Datos».
A12: 3. «Análisis»: costo directo unitario de cada concepto por tipo de insumo. Toma los costos de los APU de VERTICE-CALCULO (precios de precios-obra-, FSR 2026 Tijuana) o de la hoja «APU».
A13: 4. «Cotización»: es la hoja que se imprime o exporta a PDF para el cliente. No muestra costos ni márgenes.
A14: Cuidado:
A15: Una cotización aceptada se formaliza con el contrato de obra a precio alzado o a precios unitarios del skill; las condiciones de anticipo, pago y plazo de la cotización deben ser las mismas del contrato.

Sheet Cotización
A1: VÉRTICE · Ingeniería, Arquitectura y Proyectos
A2: COTIZACIÓN
A3: Cotización: | B3: =Datos!B6 -> COT-2026-001
A4: Fecha: | B4: =Datos!B7 -> 46314
A5: Cliente: | B5: =""&Datos!B9
A6: Atención: | B6: =""&Datos!B10
A7: Obra: | B7: =""&Datos!B11
A8: Ubicación: | B8: =""&Datos!B12 -> Tijuana, Baja California
A10: Clave | B10: Descripción | C10: Unidad | D10: Cantidad | E10: P.U. (sin IVA) | F10: Importe
A11: =IF(Análisis!A7="","",Análisis!A7) -> PRE-01 | B11: =IF(Análisis!B7="","",Análisis!B7) -> Demolición de muros de block y retiro de escombro fuera de obra | C11: =IF(Análisis!C7="","",Análisis!C7) -> m² | D11: =IF(Análisis!D7="","",Análisis!D7) -> 45 | E11: =IF(Análisis!A7="","",Análisis!K7) -> 180.16 | F11: =IF(Análisis!A7="","",Análisis!L7) -> 8107.2
A12: =IF(Análisis!A8="","",Análisis!A8) -> TAB-01 | B12: =IF(Análisis!B8="","",Análisis!B8) -> Muro de tablaroca 1 cara, bastidor cal. 26 @ 61 cm, juntas y cinta | C12: =IF(Análisis!C8="","",Análisis!C8) -> m² | D12: =IF(Análisis!D8="","",Análisis!D8) -> 210 | E12: =IF(Análisis!A8="","",Análisis!K8) -> 511.46 | F12: =IF(Análisis!A8="","",Análisis!L8) -> 107406.6
A13: =IF(Análisis!A9="","",Análisis!A9) -> TAB-02 | B13: =IF(Análisis!B9="","",Análisis!B9) -> Plafón de tablaroca a 3.00 m, incluye colgantes y canaleta | C13: =IF(Análisis!C9="","",Análisis!C9) -> m² | D13: =IF(Análisis!D9="","",Análisis!D9) -> 180 | E13: =IF(Análisis!A9="","",Análisis!K9) -> 600.78 | F13: =IF(Análisis!A9="","",Análisis!L9) -> 108140.4
A14: =IF(Análisis!A10="","",Análisis!A10) -> ELE-01 | B14: =IF(Análisis!B10="","",Análisis!B10) -> Salida eléctrica de contacto dúplex, cable cal. 12, tubería conduit | C14: =IF(Análisis!C10="","",Análisis!C10) -> sal | D14: =IF(Análisis!D10="","",Análisis!D10) -> 48 | E14: =IF(Análisis!A10="","",Análisis!K10) -> 894.78 | F14: =IF(Análisis!A10="","",Análisis!L10) -> 42949.44
A15: =IF(Análisis!A11="","",Análisis!A11) -> ELE-02 | B15: =IF(Análisis!B11="","",Análisis!B11) -> Salida de alumbrado con luminaria LED de empotrar 60×60 | C15: =IF(Análisis!C11="","",Análisis!C11) -> sal | D15: =IF(Análisis!D11="","",Análisis!D11) -> 36 | E15: =IF(Análisis!A11="","",Análisis!K11) -> 1633.47 | F15: =IF(Análisis!A11="","",Análisis!L11) -> 58804.92
A16: =IF(Análisis!A12="","",Análisis!A12) -> HID-01 | B16: =IF(Análisis!B12="","",Análisis!B12) -> Salida hidráulica y sanitaria para lavabo, PVC y CPVC | C16: =IF(Análisis!C12="","",Análisis!C12) -> sal | D16: =IF(Análisis!D12="","",Análisis!D12) -> 6 | E16: =IF(Análisis!A12="","",Análisis!K12) -> 2334.85 | F16: =IF(Análisis!A12="","",Análisis!L12) -> 14009.1
A17: =IF(Análisis!A13="","",Análisis!A13) -> PIS-01 | B17: =IF(Análisis!B13="","",Análisis!B13) -> Piso porcelánico 60×60 asentado con adhesivo, incluye boquilla | C17: =IF(Análisis!C13="","",Análisis!C13) -> m² | D17: =IF(Análisis!D13="","",Análisis!D13) -> 175 | E17: =IF(Análisis!A13="","",Análisis!K13) -> 746.2 | F17: =IF(Análisis!A13="","",Análisis!L13) -> 130585
A18: =IF(Análisis!A14="","",Análisis!A14) -> PIN-01 | B18: =IF(Análisis!B14="","",Análisis!B14) -> Pintura vinílica 2 manos sobre tablaroca, incluye sellador | C18: =IF(Análisis!C14="","",Análisis!C14) -> m² | D18: =IF(Análisis!D14="","",Análisis!D14) -> 560 | E18: =IF(Análisis!A14="","",Análisis!K14) -> 93.79 | F18: =IF(Análisis!A14="","",Análisis!L14) -> 52522.4
A19: =IF(Análisis!A15="","",Análisis!A15) | B19: =IF(Análisis!B15="","",Análisis!B15) | C19: =IF(Análisis!C15="","",Análisis!C15) | D19: =IF(Análisis!D15="","",Análisis!D15) | E19: =IF(Análisis!A15="","",Análisis!K15) | F19: =IF(Análisis!A15="","",Análisis!L15)
A20: =IF(Análisis!A16="","",Análisis!A16) | B20: =IF(Análisis!B16="","",Análisis!B16) | C20: =IF(Análisis!C16="","",Análisis!C16) | D20: =IF(Análisis!D16="","",Análisis!D16) | E20: =IF(Análisis!A16="","",Análisis!K16) | F20: =IF(Análisis!A16="","",Análisis!L16)
A21: =IF(Análisis!A17="","",Análisis!A17) | B21: =IF(Análisis!B17="","",Análisis!B17) | C21: =IF(Análisis!C17="","",Análisis!C17) | D21: =IF(Análisis!D17="","",Análisis!D17) | E21: =IF(Análisis!A17="","",Análisis!K17) | F21: =IF(Análisis!A17="","",Análisis!L17)
A22: =IF(Análisis!A18="","",Análisis!A18) | B22: =IF(Análisis!B18="","",Análisis!B18) | C22: =IF(Análisis!C18="","",Análisis!C18) | D22: =IF(Análisis!D18="","",Análisis!D18) | E22: =IF(Análisis!A18="","",Análisis!K18) | F22: =IF(Análisis!A18="","",Análisis!L18)
... A52: =IF(Análisis!A48="","",Análisis!A48) | B52: =IF(Análisis!B48="","",Análisis!B48) | C52: =IF(Análisis!C48="","",Análisis!C48) | D52: =IF(Análisis!D48="","",Análisis!D48) | E52: =IF(Análisis!A48="","",Análisis!K48) | F52: =IF(Análisis!A48="","",Análisis!L48)
E54: Subtotal | F54: =SUM(F11:F52) -> 522525.06
E55: IVA | F55: =ROUND(F54*Datos!B21,2) -> 41802
E56: TOTAL | F56: =F54+F55 -> 564327.06
A58: Condiciones
A59: =Datos!A24 -> Anticipo | B59: =Datos!B24 -> 30 % a la firma del contrato
A60: =Datos!A25 -> Forma de pago | B60: =Datos!B25 -> Estimaciones quincenales por avance, pagaderas a 15 días
A61: =Datos!A26 -> Tiempo de ejecución | B61: =Datos!B26 -> 60 días naturales a partir del anticipo y la entrega del sitio
A62: =Datos!A27 -> Incluye | B62: =Datos!B27 -> Materiales, mano de obra, herramienta, equipo, fletes, limpieza y retiro de escombro
A63: =Datos!A28 -> No incluye | B63: =Datos!B28 -> Licencias y derechos municipales, DRO y corresponsables, proyecto ejecutivo, mobiliario, trabajos no descritos
A64: =Datos!A29 -> Garantía | B64: =Datos!B29 -> 12 meses contra vicios ocultos
A65: Vigencia: | B65: =Datos!B8&" días naturales a partir de la fecha de esta cotización. Precios en moneda nacional, sin IVA salvo donde se indica." -> 15 días naturales a partir de la fecha de esta cotización. Precios en moneda nacional, sin IVA salvo donde se indica.
B66: La aceptación de esta cotización se formaliza mediante el contrato de obra correspondiente.
B69: __________________________________
B70: Ing. Miguel Estrada
B71: Vértice Ingeniería, Arquitectura y Proyectos
B72: Teléfono · correo

Sheet Datos
A1: VÉRTICE · Ingeniería, Arquitectura y Proyectos
A2: COTIZACIÓN — DATOS Y SOBRECOSTO
A3: Obra:
A4: Contrato:
A6: Cotización número | B6: COT-2026-001
A7: Fecha | B7: 46314
A8: Vigencia (días naturales) | B8: 15
A9: Cliente
A10: Atención
A11: Obra
A12: Ubicación | B12: Tijuana, Baja California
A14: SOBRECOSTO
A15: Indirectos de oficina | B15: 0.06
A16: Indirectos de campo | B16: =Indirectos!E20 -> 0.12665869 | C16: Calculado en la hoja Indirectos
A17: Financiamiento | B17: 0.01 | C17: Usa el costo financiero del libro Flujo_de_Caja
A18: Utilidad | B18: 0.1
A19: Cargos adicionales | B19: 0
A20: Factor de sobrecosto | B20: =(1+B15+B16)*(1+B17)*(1+B18)*(1+B19) -> 1.3183778 | C20: (1+ind)(1+fin)(1+util)(1+cargos), igual que VERTICE-CALCULO
A21: IVA | B21: 0.08 | C21: 8 % región fronteriza norte (Decreto vigente hasta 31-dic-2026)
A23: CONDICIONES COMERCIALES
A24: Anticipo | B24: 30 % a la firma del contrato
A25: Forma de pago | B25: Estimaciones quincenales por avance, pagaderas a 15 días
A26: Tiempo de ejecución | B26: 60 días naturales a partir del anticipo y la entrega del sitio
A27: Incluye | B27: Materiales, mano de obra, herramienta, equipo, fletes, limpieza y retiro de escombro
A28: No incluye | B28: Licencias y derechos municipales, DRO y corresponsables, proyecto ejecutivo, mobiliario, trabajos no descritos
A29: Garantía | B29: 12 meses contra vicios ocultos

Sheet Indirectos
A1: VÉRTICE · Ingeniería, Arquitectura y Proyectos
A2: INDIRECTOS DE CAMPO
A3: Obra:
A4: Contrato:
A6: Concepto | B6: Costo mensual / unitario | C6: Cantidad (meses o pzas) | D6: % de dedicación | E6: Total
A7: Superintendente de obra | B7: 45000 | C7: 2 | D7: 0.1 | E7: =N(B7)*N(C7)*N(D7) -> 9000
A8: Residente / auxiliar técnico | B8: 28000 | C8: 2 | D8: 0.2 | E8: =N(B8)*N(C8)*N(D8) -> 11200
A9: Responsable de seguridad (NOM-031) | B9: 22000 | C9: 2 | D9: 0.1 | E9: =N(B9)*N(C9)*N(D9) -> 4400
A10: Bodeguero / velador | B10: 14000 | C10: 2 | D10: 0.2 | E10: =N(B10)*N(C10)*N(D10) -> 5600
A11: Oficina, sanitario y bodega provisionales | B11: 2500 | C11: 2 | D11: 1 | E11: =N(B11)*N(C11)*N(D11) -> 5000
A12: Fianzas (anticipo, cumplimiento y vicios) | B12: 6000 | C12: 1 | D12: 1 | E12: =N(B12)*N(C12)*N(D12) -> 6000
A13: Seguro de responsabilidad civil | B13: 4000 | C13: 1 | D13: 1 | E13: =N(B13)*N(C13)*N(D13) -> 4000
A14: Pruebas de laboratorio | B14: 2000 | C14: 1 | D14: 1 | E14: =N(B14)*N(C14)*N(D14) -> 2000
A15: Limpieza final y señalización | B15: 3000 | C15: 1 | D15: 1 | E15: =N(B15)*N(C15)*N(D15) -> 3000
E16: =N(B16)*N(C16)*N(D16) -> 0
E17: =N(B17)*N(C17)*N(D17) -> 0
E18: =N(B18)*N(C18)*N(D18) -> 0
A19: Total de indirectos de campo | E19: =SUM(E7:E18) -> 50200
A20: Porcentaje sobre costo directo | E20: =IF(Análisis!J49=0,0,E19/Análisis!J49) -> 0.12665869

Sheet Análisis
A1: VÉRTICE · Ingeniería, Arquitectura y Proyectos
A2: ANÁLISIS DE COSTO DIRECTO Y PRECIO UNITARIO
A3: Obra:
A4: Contrato:
A6: Clave | B6: Concepto | C6: Unidad | D6: Cantidad | E6: Materiales | F6: Mano de obra | G6: Equipo | H6: Herramienta menor (3 % MO) | I6: Subcontrato | J6: Costo directo unitario | K6: P.U. de venta | L6: Importe de venta
A7: PRE-01 | B7: Demolición de muros de block y retiro de escombro fuera de obra | C7: m² | D7: 45 | E7: 70 | F7: 55 | G7: 10 | H7: =N(F7)*0.03 -> 1.65 | I7: 0 | J7: =N(E7)+N(F7)+N(G7)+H7+N(I7) -> 136.65 | K7: =ROUND(J7*Datos!$B$20,2) -> 180.16 | L7: =K7*N(D7) -> 8107.2
A8: TAB-01 | B8: Muro de tablaroca 1 cara, bastidor cal. 26 @ 61 cm, juntas y cinta | C8: m² | D8: 210 | E8: 210 | F8: 165 | G8: 8 | H8: =N(F8)*0.03 -> 4.95 | I8: 0 | J8: =N(E8)+N(F8)+N(G8)+H8+N(I8) -> 387.95 | K8: =ROUND(J8*Datos!$B$20,2) -> 511.46 | L8: =K8*N(D8) -> 107406.6
A9: TAB-02 | B9: Plafón de tablaroca a 3.00 m, incluye colgantes y canaleta | C9: m² | D9: 180 | E9: 250 | F9: 190 | G9: 10 | H9: =N(F9)*0.03 -> 5.7 | I9: 0 | J9: =N(E9)+N(F9)+N(G9)+H9+N(I9) -> 455.7 | K9: =ROUND(J9*Datos!$B$20,2) -> 600.78 | L9: =K9*N(D9) -> 108140.4
A10: ELE-01 | B10: Salida eléctrica de contacto dúplex, cable cal. 12, tubería conduit | C10: sal | D10: 48 | E10: 380 | F10: 290 | G10: 0 | H10: =N(F10)*0.03 -> 8.7 | I10: 0 | J10: =N(E10)+N(F10)+N(G10)+H10+N(I10) -> 678.7 | K10: =ROUND(J10*Datos!$B$20,2) -> 894.78 | L10: =K10*N(D10) -> 42949.44
A11: ELE-02 | B11: Salida de alumbrado con luminaria LED de empotrar 60×60 | C11: sal | D11: 36 | E11: 930 | F11: 300 | G11: 0 | H11: =N(F11)*0.03 -> 9 | I11: 0 | J11: =N(E11)+N(F11)+N(G11)+H11+N(I11) -> 1239 | K11: =ROUND(J11*Datos!$B$20,2) -> 1633.47 | L11: =K11*N(D11) -> 58804.92
A12: HID-01 | B12: Salida hidráulica y sanitaria para lavabo, PVC y CPVC | C12: sal | D12: 6 | E12: 1050 | F12: 700 | G12: 0 | H12: =N(F12)*0.03 -> 21 | I12: 0 | J12: =N(E12)+N(F12)+N(G12)+H12+N(I12) -> 1771 | K12: =ROUND(J12*Datos!$B$20,2) -> 2334.85 | L12: =K12*N(D12) -> 14009.1
A13: PIS-01 | B13: Piso porcelánico 60×60 asentado con adhesivo, incluye boquilla | C13: m² | D13: 175 | E13: 360 | F13: 200 | G13: 0 | H13: =N(F13)*0.03 -> 6 | I13: 0 | J13: =N(E13)+N(F13)+N(G13)+H13+N(I13) -> 566 | K13: =ROUND(J13*Datos!$B$20,2) -> 746.2 | L13: =K13*N(D13) -> 130585
A14: PIN-01 | B14: Pintura vinílica 2 manos sobre tablaroca, incluye sellador | C14: m² | D14: 560 | E14: 32 | F14: 38 | G14: 0 | H14: =N(F14)*0.03 -> 1.14 | I14: 0 | J14: =N(E14)+N(F14)+N(G14)+H14+N(I14) -> 71.14 | K14: =ROUND(J14*Datos!$B$20,2) -> 93.79 | L14: =K14*N(D14) -> 52522.4
H15: =N(F15)*0.03 -> 0 | J15: =N(E15)+N(F15)+N(G15)+H15+N(I15) -> 0 | K15: =ROUND(J15*Datos!$B$20,2) -> 0 | L15: =K15*N(D15) -> 0
H16: =N(F16)*0.03 -> 0 | J16: =N(E16)+N(F16)+N(G16)+H16+N(I16) -> 0 | K16: =ROUND(J16*Datos!$B$20,2) -> 0 | L16: =K16*N(D16) -> 0
H17: =N(F17)*0.03 -> 0 | J17: =N(E17)+N(F17)+N(G17)+H17+N(I17) -> 0 | K17: =ROUND(J17*Datos!$B$20,2) -> 0 | L17: =K17*N(D17) -> 0
H18: =N(F18)*0.03 -> 0 | J18: =N(E18)+N(F18)+N(G18)+H18+N(I18) -> 0 | K18: =ROUND(J18*Datos!$B$20,2) -> 0 | L18: =K18*N(D18) -> 0
H19: =N(F19)*0.03 -> 0 | J19: =N(E19)+N(F19)+N(G19)+H19+N(I19) -> 0 | K19: =ROUND(J19*Datos!$B$20,2) -> 0 | L19: =K19*N(D19) -> 0
H20: =N(F20)*0.03 -> 0 | J20: =N(E20)+N(F20)+N(G20)+H20+N(I20) -> 0 | K20: =ROUND(J20*Datos!$B$20,2) -> 0 | L20: =K20*N(D20) -> 0
H21: =N(F21)*0.03 -> 0 | J21: =N(E21)+N(F21)+N(G21)+H21+N(I21) -> 0 | K21: =ROUND(J21*Datos!$B$20,2) -> 0 | L21: =K21*N(D21) -> 0
H22: =N(F22)*0.03 -> 0 | J22: =N(E22)+N(F22)+N(G22)+H22+N(I22) -> 0 | K22: =ROUND(J22*Datos!$B$20,2) -> 0 | L22: =K22*N(D22) -> 0
H23: =N(F23)*0.03 -> 0 | J23: =N(E23)+N(F23)+N(G23)+H23+N(I23) -> 0 | K23: =ROUND(J23*Datos!$B$20,2) -> 0 | L23: =K23*N(D23) -> 0
H24: =N(F24)*0.03 -> 0 | J24: =N(E24)+N(F24)+N(G24)+H24+N(I24) -> 0 | K24: =ROUND(J24*Datos!$B$20,2) -> 0 | L24: =K24*N(D24) -> 0
H25: =N(F25)*0.03 -> 0 | J25: =N(E25)+N(F25)+N(G25)+H25+N(I25) -> 0 | K25: =ROUND(J25*Datos!$B$20,2) -> 0 | L25: =K25*N(D25) -> 0
H26: =N(F26)*0.03 -> 0 | J26: =N(E26)+N(F26)+N(G26)+H26+N(I26) -> 0 | K26: =ROUND(J26*Datos!$B$20,2) -> 0 | L26: =K26*N(D26) -> 0
... H48: =N(F48)*0.03 -> 0 | J48: =N(E48)+N(F48)+N(G48)+H48+N(I48) -> 0 | K48: =ROUND(J48*Datos!$B$20,2) -> 0 | L48: =K48*N(D48) -> 0
B49: TOTALES (costo directo y venta) | J49: =SUMPRODUCT(J7:J48,D7:D48) -> 396340.75 | L49: =SUM(L7:L48) -> 522525.06
B50: Margen bruto sobre venta | L50: =IF(L49=0,0,(L49-J49)/L49) -> 0.24148949

Sheet APU
A1: VÉRTICE · Ingeniería, Arquitectura y Proyectos
A2: ANÁLISIS DE PRECIO UNITARIO (PLANTILLA)
A3: Obra:
A4: Contrato:
A5: Concepto | B5: Muro de tablaroca 1 cara, bastidor cal. 26 @ 61 cm, juntas y cinta | C5: Unidad | D5: m²
A7: MATERIALES
A8: Insumo | B8: Unidad | C8: Cantidad | D8: Precio (sin IVA) | E8: Importe | F8: Fuente / cotización
A9: Panel de yeso 1/2" 1.22×2.44 | B9: m² | C9: 1.05 | D9: 112 | E9: =C9*D9 -> 117.6 | F9: precios-obra- (ago 2026) + 10 % Tijuana
A10: Poste metálico cal. 26 de 3 m | B10: pza | C10: 0.7 | D10: 68 | E10: =C10*D10 -> 47.6 | F10: cotización
A11: Canal metálico cal. 26 de 3 m | B11: pza | C11: 0.3 | D11: 55 | E11: =C11*D11 -> 16.5 | F11: cotización
A12: Tornillo, cinta y compuesto | B12: lote | C12: 1 | D12: 22 | E12: =C12*D12 -> 22 | F12: cotización
D13: Subtotal | E13: =SUM(E9:E12) -> 203.7
A15: MANO DE OBRA
A16: Cuadrilla | B16: Unidad | C16: Cantidad (1/rend.) | D16: Salario real | E16: Importe | F16: Rendimiento (m²/jor)
A17: 1 oficial yesero + 1 ayudante (salario real con FSR) | B17: jor | C17: =1/F17 -> 0.090909091 | D17: 1850 | E17: =C17*D17 -> 168.18182 | F17: 11
D18: Subtotal | E18: =SUM(E17:E17) -> 168.18182
A20: EQUIPO Y HERRAMIENTA
A21: Equipo | B21: Unidad | C21: Cantidad | D21: Costo | E21: Importe | F21: Nota
A22: Andamio tubular (cuerpo) | B22: jornada | C22: 0.09 | D22: 35 | E22: =C22*D22 -> 3.15 | F22: mano-obra.json
A23: Herramienta menor (% de MO) | B23: % | C23: 0.03 | D23: =E18 -> 168.18182 | E23: =C23*D23 -> 5.0454545 | F23: 3 % de la mano de obra
D24: Subtotal | E24: =SUM(E22:E23) -> 8.1954545
D26: COSTO DIRECTO | E26: =E13+E18+E24 -> 380.07727
D27: × Factor de sobrecosto | E27: =Datos!B20 -> 1.3183778
D28: PRECIO UNITARIO | E28: =ROUND(E26*E27,2) -> 501.09
A30: Para APU con base de precios y FSR automáticos usa VERTICE-CALCULO: costos.apu_desde_base(db, rendimiento). Esta hoja es para análisis rápidos en obra.
