Workbook

Sheet Instrucciones
A1: VÉRTICE · Ingeniería, Arquitectura y Proyectos
A2: ESTIMACIÓN DE OBRA CON NÚMEROS GENERADORES
A4: Captura
A5: Celdas amarillas con texto azul = datos que capturas. Texto negro = fórmulas: no escribas encima. La fila de ejemplo muestra el formato esperado; sustitúyela por tus datos.
A7: Para qué sirve:
A8: Integra la estimación (cobro periódico) de un contrato a precios unitarios: catálogo contratado, números generadores, acumulados, carátula con amortización de anticipo, fondo de garantía, IVA y neto a pagar, y reporte fotográfico.
A9: Cómo se llena cada periodo:
A10: 1. «Datos»: número de estimación, periodo, porcentajes del contrato (cláusulas de ANTICIPO y ESTIMACIONES).
A11: 2. «Catálogo»: el catálogo del Anexo B del contrato (clave, concepto, unidad, cantidad y PU). La «cantidad acumulada anterior» es la acumulada de la estimación pasada: copia la columna I de la estimación anterior como valores.
A12: 3. «Generadores»: una fila por medición (eje, nivel, largo, ancho, alto, piezas). Las celdas vacías no cuentan en el producto. Usa signo -1 para descontar huecos. La cantidad de cada clave pasa sola al catálogo.
A13: 4. «Carátula»: revisa y firma. Si el contrato prevé la retención de IVA del art. 1-A fr. IV LIVA, captura 6 % en Datos; si no, déjalo en 0.
A14: Reglas que ya trae el libro:
... A17: Para medir cantidades en campo apóyate en las calculadoras de ObraLab (concreto, block, tablaroca, plafón, pintura, acero).

Sheet Carátula
A1: VÉRTICE · Ingeniería, Arquitectura y Proyectos
A2: CARÁTULA DE ESTIMACIÓN
A3: Obra:
A4: Contrato:
A6: Estimación No. | B6: =Datos!B8 -> 1
A7: Periodo | B7: =TEXT(Datos!B9,"dd/mm/yyyy")&" al "&TEXT(Datos!B10,"dd/mm/yyyy") -> 19/10/2026 al 01/11/2026
A8: Contratista | B8: =Datos!B6 -> Vértice Ingeniería, Arquitectura y Proyectos
A9: Cliente | B9: =Datos!B7 -> 0
D11: RESUMEN DEL CONTRATO
A12: Importe de trabajos ejecutados en el periodo | B12: =Catálogo!J49 -> 115192.35 | D12: Monto del contrato | E12: =Datos!B11 -> 527050
A13: (-) Amortización del anticipo | B13: =-ROUND(B12*Datos!B12,2) -> -34557.71 | D13: Estimado acumulado (incluye ésta) | E13: =Catálogo!K49 -> 196205.85
A14: Subtotal (base del IVA) | B14: =B12+B13 -> 80634.64 | D14: Avance financiero | E14: =IF(E12=0,0,E13/E12) -> 0.3722718
A15: (+) IVA | B15: =ROUND(B14*Datos!B14,2) -> 6450.77 | D15: Anticipo otorgado | E15: =ROUND(E12*Datos!B12,2) -> 158115
A16: Total de la estimación (importe del CFDI) | B16: =B14+B15 -> 87085.41 | D16: Anticipo amortizado acumulado | E16: =ROUND(E13*Datos!B12,2) -> 58861.76
A17: (-) Retención de IVA | B17: =-ROUND(B14*Datos!B15,2) -> 0 | D17: Saldo de anticipo por amortizar | E17: =E15-E16 -> 99253.24
A18: (-) Retención fondo de garantía | B18: =-ROUND(B12*Datos!B13,2) -> -5759.62 | D18: Fondo de garantía acumulado | E18: =ROUND(E13*Datos!B13,2) -> 9810.29
A19: (-) Otras deducciones | B19: =-Datos!B16 -> 0 | D19: Saldo del contrato por estimar | E19: =E12-E13 -> 330844.15
A20: NETO A PAGAR | B20: =SUM(B16:B19) -> 81325.79
A22: Alertas del catálogo: | B22: =IF(COUNTIF(Catálogo!N8:N48,"EXCEDE")=0,"Sin conceptos excedidos",COUNTIF(Catálogo!N8:N48,"EXCEDE")&" concepto(s) exceden lo contratado: requieren orden de cambio") -> Sin conceptos excedidos
A23: El pago de esta estimación no implica la aceptación de los trabajos (ver cláusula de pago del contrato).
A27: ____________________________ | C27: ____________________________ | E27: ____________________________
A28: Elaboró — superintendente del contratista | C28: Revisó — supervisión | E28: Autorizó — propietario

Sheet Datos
A1: VÉRTICE · Ingeniería, Arquitectura y Proyectos
A2: ESTIMACIÓN — DATOS DEL CONTRATO
A3: Obra:
A4: Contrato:
A6: Contratista | B6: Vértice Ingeniería, Arquitectura y Proyectos
A7: Cliente / propietario
A8: Estimación número | B8: 1
A9: Periodo del | B9: 46314
A10: Periodo al | B10: 46327
A11: Monto del contrato (sin IVA) | B11: =Catálogo!F49 -> 527050 | C11: Suma del catálogo contratado
A12: Anticipo otorgado | B12: 0.3
A13: Fondo de garantía | B13: 0.05
A14: IVA | B14: 0.08 | C14: 8 % región fronteriza norte (Decreto vigente hasta 31-dic-2026)
A15: Retención de IVA (si aplica) | B15: 0 | C15: Sólo si aplica art. 1-A fr. IV LIVA; normalmente 0
A16: Otras deducciones (penas, cargos) | B16: 0
A17: Concepto de otras deducciones

Sheet Catálogo
A1: VÉRTICE · Ingeniería, Arquitectura y Proyectos
A2: CATÁLOGO, AVANCE Y ESTIMACIÓN DEL PERIODO
A3: Obra:
A4: Contrato:
A7: Clave | B7: Concepto | C7: Unidad | D7: Cantidad contratada | E7: P.U. (sin IVA) | F7: Importe contratado | G7: Cant. acumulada anterior | H7: Cant. esta estimación | I7: Cant. acumulada actual | J7: Importe esta estimación | K7: Importe acumulado | L7: Cant. por ejecutar | M7: % avance | N7: Alerta
A8: PRE-01 | B8: Demolición de muros de block y retiro de escombro fuera de obra | C8: m² | D8: 45 | E8: 185 | F8: =D8*E8 -> 8325 | G8: 13.5 | H8: =IF(A8="",0,SUMIF(Generadores!$A$8:$A$307,A8,Generadores!$J$8:$J$307)) -> 23.31 | I8: =G8+H8 -> 36.81 | J8: =H8*E8 -> 4312.35 | K8: =I8*E8 -> 6809.85 | L8: =D8-I8 -> 8.19 | M8: =IF(D8=0,0,I8/D8) -> 0.818 | N8: =IF(AND(D8>0,I8>D8+0.0001),"EXCEDE","")
A9: TAB-01 | B9: Muro de tablaroca 1 cara, bastidor cal. 26 @ 61 cm, juntas y cinta | C9: m² | D9: 210 | E9: 520 | F9: =D9*E9 -> 109200 | G9: 63 | H9: =IF(A9="",0,SUMIF(Generadores!$A$8:$A$307,A9,Generadores!$J$8:$J$307)) -> 37.5 | I9: =G9+H9 -> 100.5 | J9: =H9*E9 -> 19500 | K9: =I9*E9 -> 52260 | L9: =D9-I9 -> 109.5 | M9: =IF(D9=0,0,I9/D9) -> 0.47857143 | N9: =IF(AND(D9>0,I9>D9+0.0001),"EXCEDE","")
A10: TAB-02 | B10: Plafón de tablaroca a 3.00 m, incluye colgantes y canaleta | C10: m² | D10: 180 | E10: 610 | F10: =D10*E10 -> 109800 | G10: 54 | H10: =IF(A10="",0,SUMIF(Generadores!$A$8:$A$307,A10,Generadores!$J$8:$J$307)) -> 60 | I10: =G10+H10 -> 114 | J10: =H10*E10 -> 36600 | K10: =I10*E10 -> 69540 | L10: =D10-I10 -> 66 | M10: =IF(D10=0,0,I10/D10) -> 0.63333333 | N10: =IF(AND(D10>0,I10>D10+0.0001),"EXCEDE","")
A11: ELE-01 | B11: Salida eléctrica de contacto dúplex, cable cal. 12, tubería conduit | C11: sal | D11: 48 | E11: 890 | F11: =D11*E11 -> 42720 | G11: 14.4 | H11: =IF(A11="",0,SUMIF(Generadores!$A$8:$A$307,A11,Generadores!$J$8:$J$307)) -> 12 | I11: =G11+H11 -> 26.4 | J11: =H11*E11 -> 10680 | K11: =I11*E11 -> 23496 | L11: =D11-I11 -> 21.6 | M11: =IF(D11=0,0,I11/D11) -> 0.55 | N11: =IF(AND(D11>0,I11>D11+0.0001),"EXCEDE","")
A12: ELE-02 | B12: Salida de alumbrado con luminaria LED de empotrar 60×60 | C12: sal | D12: 36 | E12: 1650 | F12: =D12*E12 -> 59400 | G12: 0 | H12: =IF(A12="",0,SUMIF(Generadores!$A$8:$A$307,A12,Generadores!$J$8:$J$307)) -> 0 | I12: =G12+H12 -> 0 | J12: =H12*E12 -> 0 | K12: =I12*E12 -> 0 | L12: =D12-I12 -> 36 | M12: =IF(D12=0,0,I12/D12) -> 0 | N12: =IF(AND(D12>0,I12>D12+0.0001),"EXCEDE","")
A13: HID-01 | B13: Salida hidráulica y sanitaria para lavabo, PVC y CPVC | C13: sal | D13: 6 | E13: 2350 | F13: =D13*E13 -> 14100 | G13: 0 | H13: =IF(A13="",0,SUMIF(Generadores!$A$8:$A$307,A13,Generadores!$J$8:$J$307)) -> 0 | I13: =G13+H13 -> 0 | J13: =H13*E13 -> 0 | K13: =I13*E13 -> 0 | L13: =D13-I13 -> 6 | M13: =IF(D13=0,0,I13/D13) -> 0 | N13: =IF(AND(D13>0,I13>D13+0.0001),"EXCEDE","")
A14: PIS-01 | B14: Piso porcelánico 60×60 asentado con adhesivo, incluye boquilla | C14: m² | D14: 175 | E14: 735 | F14: =D14*E14 -> 128625 | G14: 0 | H14: =IF(A14="",0,SUMIF(Generadores!$A$8:$A$307,A14,Generadores!$J$8:$J$307)) -> 60 | I14: =G14+H14 -> 60 | J14: =H14*E14 -> 44100 | K14: =I14*E14 -> 44100 | L14: =D14-I14 -> 115 | M14: =IF(D14=0,0,I14/D14) -> 0.34285714 | N14: =IF(AND(D14>0,I14>D14+0.0001),"EXCEDE","")
A15: PIN-01 | B15: Pintura vinílica 2 manos sobre tablaroca, incluye sellador | C15: m² | D15: 560 | E15: 98 | F15: =D15*E15 -> 54880 | G15: 0 | H15: =IF(A15="",0,SUMIF(Generadores!$A$8:$A$307,A15,Generadores!$J$8:$J$307)) -> 0 | I15: =G15+H15 -> 0 | J15: =H15*E15 -> 0 | K15: =I15*E15 -> 0 | L15: =D15-I15 -> 560 | M15: =IF(D15=0,0,I15/D15) -> 0 | N15: =IF(AND(D15>0,I15>D15+0.0001),"EXCEDE","")
F16: =D16*E16 -> 0 | H16: =IF(A16="",0,SUMIF(Generadores!$A$8:$A$307,A16,Generadores!$J$8:$J$307)) -> 0 | I16: =G16+H16 -> 0 | J16: =H16*E16 -> 0 | K16: =I16*E16 -> 0 | L16: =D16-I16 -> 0 | M16: =IF(D16=0,0,I16/D16) -> 0 | N16: =IF(AND(D16>0,I16>D16+0.0001),"EXCEDE","")
F17: =D17*E17 -> 0 | H17: =IF(A17="",0,SUMIF(Generadores!$A$8:$A$307,A17,Generadores!$J$8:$J$307)) -> 0 | I17: =G17+H17 -> 0 | J17: =H17*E17 -> 0 | K17: =I17*E17 -> 0 | L17: =D17-I17 -> 0 | M17: =IF(D17=0,0,I17/D17) -> 0 | N17: =IF(AND(D17>0,I17>D17+0.0001),"EXCEDE","")
F18: =D18*E18 -> 0 | H18: =IF(A18="",0,SUMIF(Generadores!$A$8:$A$307,A18,Generadores!$J$8:$J$307)) -> 0 | I18: =G18+H18 -> 0 | J18: =H18*E18 -> 0 | K18: =I18*E18 -> 0 | L18: =D18-I18 -> 0 | M18: =IF(D18=0,0,I18/D18) -> 0 | N18: =IF(AND(D18>0,I18>D18+0.0001),"EXCEDE","")
F19: =D19*E19 -> 0 | H19: =IF(A19="",0,SUMIF(Generadores!$A$8:$A$307,A19,Generadores!$J$8:$J$307)) -> 0 | I19: =G19+H19 -> 0 | J19: =H19*E19 -> 0 | K19: =I19*E19 -> 0 | L19: =D19-I19 -> 0 | M19: =IF(D19=0,0,I19/D19) -> 0 | N19: =IF(AND(D19>0,I19>D19+0.0001),"EXCEDE","")
F20: =D20*E20 -> 0 | H20: =IF(A20="",0,SUMIF(Generadores!$A$8:$A$307,A20,Generadores!$J$8:$J$307)) -> 0 | I20: =G20+H20 -> 0 | J20: =H20*E20 -> 0 | K20: =I20*E20 -> 0 | L20: =D20-I20 -> 0 | M20: =IF(D20=0,0,I20/D20) -> 0 | N20: =IF(AND(D20>0,I20>D20+0.0001),"EXCEDE","")
F21: =D21*E21 -> 0 | H21: =IF(A21="",0,SUMIF(Generadores!$A$8:$A$307,A21,Generadores!$J$8:$J$307)) -> 0 | I21: =G21+H21 -> 0 | J21: =H21*E21 -> 0 | K21: =I21*E21 -> 0 | L21: =D21-I21 -> 0 | M21: =IF(D21=0,0,I21/D21) -> 0 | N21: =IF(AND(D21>0,I21>D21+0.0001),"EXCEDE","")
F22: =D22*E22 -> 0 | H22: =IF(A22="",0,SUMIF(Generadores!$A$8:$A$307,A22,Generadores!$J$8:$J$307)) -> 0 | I22: =G22+H22 -> 0 | J22: =H22*E22 -> 0 | K22: =I22*E22 -> 0 | L22: =D22-I22 -> 0 | M22: =IF(D22=0,0,I22/D22) -> 0 | N22: =IF(AND(D22>0,I22>D22+0.0001),"EXCEDE","")
F23: =D23*E23 -> 0 | H23: =IF(A23="",0,SUMIF(Generadores!$A$8:$A$307,A23,Generadores!$J$8:$J$307)) -> 0 | I23: =G23+H23 -> 0 | J23: =H23*E23 -> 0 | K23: =I23*E23 -> 0 | L23: =D23-I23 -> 0 | M23: =IF(D23=0,0,I23/D23) -> 0 | N23: =IF(AND(D23>0,I23>D23+0.0001),"EXCEDE","")
F24: =D24*E24 -> 0 | H24: =IF(A24="",0,SUMIF(Generadores!$A$8:$A$307,A24,Generadores!$J$8:$J$307)) -> 0 | I24: =G24+H24 -> 0 | J24: =H24*E24 -> 0 | K24: =I24*E24 -> 0 | L24: =D24-I24 -> 0 | M24: =IF(D24=0,0,I24/D24) -> 0 | N24: =IF(AND(D24>0,I24>D24+0.0001),"EXCEDE","")
F25: =D25*E25 -> 0 | H25: =IF(A25="",0,SUMIF(Generadores!$A$8:$A$307,A25,Generadores!$J$8:$J$307)) -> 0 | I25: =G25+H25 -> 0 | J25: =H25*E25 -> 0 | K25: =I25*E25 -> 0 | L25: =D25-I25 -> 0 | M25: =IF(D25=0,0,I25/D25) -> 0 | N25: =IF(AND(D25>0,I25>D25+0.0001),"EXCEDE","")
F26: =D26*E26 -> 0 | H26: =IF(A26="",0,SUMIF(Generadores!$A$8:$A$307,A26,Generadores!$J$8:$J$307)) -> 0 | I26: =G26+H26 -> 0 | J26: =H26*E26 -> 0 | K26: =I26*E26 -> 0 | L26: =D26-I26 -> 0 | M26: =IF(D26=0,0,I26/D26) -> 0 | N26: =IF(AND(D26>0,I26>D26+0.0001),"EXCEDE","")
F27: =D27*E27 -> 0 | H27: =IF(A27="",0,SUMIF(Generadores!$A$8:$A$307,A27,Generadores!$J$8:$J$307)) -> 0 | I27: =G27+H27 -> 0 | J27: =H27*E27 -> 0 | K27: =I27*E27 -> 0 | L27: =D27-I27 -> 0 | M27: =IF(D27=0,0,I27/D27) -> 0 | N27: =IF(AND(D27>0,I27>D27+0.0001),"EXCEDE","")
... F48: =D48*E48 -> 0 | H48: =IF(A48="",0,SUMIF(Generadores!$A$8:$A$307,A48,Generadores!$J$8:$J$307)) -> 0 | I48: =G48+H48 -> 0 | J48: =H48*E48 -> 0 | K48: =I48*E48 -> 0 | L48: =D48-I48 -> 0 | M48: =IF(D48=0,0,I48/D48) -> 0 | N48: =IF(AND(D48>0,I48>D48+0.0001),"EXCEDE","")
B49: TOTALES | F49: =SUM(F8:F48) -> 527050 | J49: =SUM(J8:J48) -> 115192.35 | K49: =SUM(K8:K48) -> 196205.85 | M49: =IF(F49=0,0,K49/F49) -> 0.3722718

Sheet Generadores
A1: VÉRTICE · Ingeniería, Arquitectura y Proyectos
A2: NÚMEROS GENERADORES
A3: Obra:
A4: Contrato:
A7: Clave | B7: Eje / nivel / ubicación | C7: Descripción de la medición | D7: Largo | E7: Ancho | F7: Alto / espesor | G7: Piezas | H7: Signo (1 / -1) | I7: Parcial | J7: Cantidad | K7: Croquis / foto
A8: PRE-01 | B8: Eje 1 / A-C | C8: Muro divisorio a demoler | D8: 9 | F8: 2.8 | G8: 1 | H8: 1 | I8: =IF(COUNT(D8:G8)=0,0,PRODUCT(D8:G8)) -> 25.2 | J8: =I8*IF(H8="",1,H8) -> 25.2
A9: PRE-01 | B9: Eje 1 / A-C | C9: Hueco de puerta existente | D9: 0.9 | F9: 2.1 | G9: 1 | H9: -1 | I9: =IF(COUNT(D9:G9)=0,0,PRODUCT(D9:G9)) -> 1.89 | J9: =I9*IF(H9="",1,H9) -> -1.89
A10: TAB-01 | B10: Ejes B-D / 2 | C10: Muro de tablaroca sala de juntas | D10: 12.5 | F10: 3 | G10: 1 | H10: 1 | I10: =IF(COUNT(D10:G10)=0,0,PRODUCT(D10:G10)) -> 37.5 | J10: =I10*IF(H10="",1,H10) -> 37.5
A11: TAB-02 | B11: Área de ventas | C11: Plafón zona A | D11: 8 | E11: 7.5 | G11: 1 | H11: 1 | I11: =IF(COUNT(D11:G11)=0,0,PRODUCT(D11:G11)) -> 60 | J11: =I11*IF(H11="",1,H11) -> 60
A12: ELE-01 | B12: Muro eje C | C12: Contactos dúplex | G12: 12 | H12: 1 | I12: =IF(COUNT(D12:G12)=0,0,PRODUCT(D12:G12)) -> 12 | J12: =I12*IF(H12="",1,H12) -> 12
A13: PIS-01 | B13: Área de ventas | C13: Piso porcelánico zona A | D13: 8 | E13: 7.5 | G13: 1 | H13: 1 | I13: =IF(COUNT(D13:G13)=0,0,PRODUCT(D13:G13)) -> 60 | J13: =I13*IF(H13="",1,H13) -> 60
I14: =IF(COUNT(D14:G14)=0,0,PRODUCT(D14:G14)) -> 0 | J14: =I14*IF(H14="",1,H14) -> 0
I15: =IF(COUNT(D15:G15)=0,0,PRODUCT(D15:G15)) -> 0 | J15: =I15*IF(H15="",1,H15) -> 0
I16: =IF(COUNT(D16:G16)=0,0,PRODUCT(D16:G16)) -> 0 | J16: =I16*IF(H16="",1,H16) -> 0
I17: =IF(COUNT(D17:G17)=0,0,PRODUCT(D17:G17)) -> 0 | J17: =I17*IF(H17="",1,H17) -> 0
I18: =IF(COUNT(D18:G18)=0,0,PRODUCT(D18:G18)) -> 0 | J18: =I18*IF(H18="",1,H18) -> 0
I19: =IF(COUNT(D19:G19)=0,0,PRODUCT(D19:G19)) -> 0 | J19: =I19*IF(H19="",1,H19) -> 0
I20: =IF(COUNT(D20:G20)=0,0,PRODUCT(D20:G20)) -> 0 | J20: =I20*IF(H20="",1,H20) -> 0
I21: =IF(COUNT(D21:G21)=0,0,PRODUCT(D21:G21)) -> 0 | J21: =I21*IF(H21="",1,H21) -> 0
I22: =IF(COUNT(D22:G22)=0,0,PRODUCT(D22:G22)) -> 0 | J22: =I22*IF(H22="",1,H22) -> 0
I23: =IF(COUNT(D23:G23)=0,0,PRODUCT(D23:G23)) -> 0 | J23: =I23*IF(H23="",1,H23) -> 0
I24: =IF(COUNT(D24:G24)=0,0,PRODUCT(D24:G24)) -> 0 | J24: =I24*IF(H24="",1,H24) -> 0
I25: =IF(COUNT(D25:G25)=0,0,PRODUCT(D25:G25)) -> 0 | J25: =I25*IF(H25="",1,H25) -> 0
... I307: =IF(COUNT(D307:G307)=0,0,PRODUCT(D307:G307)) -> 0 | J307: =I307*IF(H307="",1,H307) -> 0

Sheet Reporte fotográfico
A1: VÉRTICE · Ingeniería, Arquitectura y Proyectos
A2: REPORTE FOTOGRÁFICO DE LA ESTIMACIÓN
A3: Obra:
A4: Contrato:
A6: Foto 1 (inserta la imagen aquí) | C6: Foto 2 (inserta la imagen aquí)
A19: Clave / ubicación: | C19: Clave / ubicación:
A20: Descripción: | C20: Descripción:
A22: Foto 3 (inserta la imagen aquí) | C22: Foto 4 (inserta la imagen aquí)
A35: Clave / ubicación: | C35: Clave / ubicación:
A36: Descripción: | C36: Descripción:
A38: Foto 5 (inserta la imagen aquí) | C38: Foto 6 (inserta la imagen aquí)
A51: Clave / ubicación: | C51: Clave / ubicación:
A52: Descripción: | C52: Descripción:
A54: Foto 7 (inserta la imagen aquí) | C54: Foto 8 (inserta la imagen aquí)
A67: Clave / ubicación: | C67: Clave / ubicación:
A68: Descripción: | C68: Descripción:
