Workbook

Sheet Instrucciones
A1: VÉRTICE · Ingeniería, Arquitectura y Proyectos
A2: FLUJO DE CAJA SEMANAL DE OBRA
A4: Captura
A5: Celdas amarillas con texto azul = datos que capturas. Texto negro = fórmulas: no escribas encima. La fila de ejemplo muestra el formato esperado; sustitúyela por tus datos.
A7: Para qué sirve:
A8: Proyecta cobros y pagos semana a semana a partir del costo programado, el anticipo, las estimaciones, la retención del fondo de garantía y el crédito de proveedores; calcula cuánto dinero tienes que poner (necesidad máxima de financiamiento) y lo que cuesta.
A9: Cómo se llena:
A10: 1. En «Datos» captura el monto del contrato, el costo presupuestado y las condiciones de pago del contrato (mismas cláusulas de ANTICIPO, ESTIMACIONES y FONDO DE GARANTÍA).
A11: 2. En «Flujo semanal», columna C, captura el costo programado de cada semana (sale del programa de obra de VERTICE-CALCULO: programa.costo_por_semana()). La celda de control debajo de la tabla debe coincidir con el costo presupuestado.
A12: 3. Cada semana captura en Q y R lo que realmente cobraste y pagaste: el libro compara el acumulado real contra el proyectado.
A13: Notas:
A14: Todo está SIN IVA: el IVA se traslada y acredita aparte. Para el IVA en la frontera norte usa la tasa del Decreto vigente (8 % hasta el 31-dic-2026).
A15: La lógica es la misma de vertice/programa.py → flujo_de_caja(): anticipo en la semana 1, estimaciones cada N semanas, cobro con desfase, material con crédito, nómina la misma semana y el resto con una semana de desfase.

Sheet Datos
A1: VÉRTICE · Ingeniería, Arquitectura y Proyectos
A2: FLUJO DE CAJA — DATOS
A3: Obra:
A4: Contrato:
A6: Fecha de inicio de obra | B6: 46314
A7: Monto del contrato (sin IVA) | B7: 1000000
A8: Costo total presupuestado (sin IVA) | B8: 800000 | C8: Costo directo + indirectos de campo, sin utilidad (de tu presupuesto)
A9: Anticipo | B9: 0.3
A10: Fondo de garantía retenido | B10: 0.05
A11: Periodo de estimación (semanas) | B11: 2
A12: Semanas que tarda el cliente en pagar | B12: 2
A13: Semanas después del fin para devolver el fondo | B13: 4
A14: Fracción del costo que es material | B14: 0.55
A15: Crédito de proveedores (semanas) | B15: 2
A16: Fracción del costo que es mano de obra | B16: 0.35 | C16: Se paga la misma semana (nómina)
A17: Resto (subcontratos e indirectos), 1 semana de desfase | B17: =1-B14-B16 -> 0.1
A18: Tasa anual de financiamiento | B18: 0.14
A19: IVA (sólo informativo) | B19: 0.08
A21: RESULTADOS
A22: Semana final de obra | B22: =SUMPRODUCT(MAX(('Flujo semanal'!C8:C59>0)*'Flujo semanal'!A8:A59)) -> 10
A23: Necesidad máxima de financiamiento | B23: =MAX(0,-MIN('Flujo semanal'!O8:O59)) -> 0
A24: Semana de mayor necesidad | B24: =IF(B23=0,"-",INDEX('Flujo semanal'!A8:A59,MATCH(MIN('Flujo semanal'!O8:O59),'Flujo semanal'!O8:O59,0))) -> -
A25: Costo financiero estimado | B25: =SUM('Flujo semanal'!P8:P59) -> 0
A26: Utilidad bruta proyectada (antes de financiamiento) | B26: ='Flujo semanal'!O59 -> 200000
A27: Utilidad neta proyectada | B27: =B26-B25 -> 200000
A28: Margen sobre contrato | B28: =IF(B7=0,0,B27/B7) -> 0.2
A29: Última semana con captura real | B29: =IFERROR(LOOKUP(2,1/('Flujo semanal'!S8:S59<>""),'Flujo semanal'!A8:A59),"-") -> -
A30: Diferencia real vs proyectado a esa semana | B30: =IFERROR(LOOKUP(2,1/('Flujo semanal'!T8:T59<>""),'Flujo semanal'!T8:T59),0) -> 0 | C30: Negativo = traes menos caja de la proyectada

Sheet Flujo semanal
A1: VÉRTICE · Ingeniería, Arquitectura y Proyectos
A2: FLUJO DE CAJA SEMANAL (SIN IVA)
A3: Obra:
A4: Contrato:
A7: Semana | B7: Inicia | C7: Costo programado | D7: % avance semanal | E7: Estimación | F7: Amortiz. anticipo | G7: Fondo garantía | H7: Neto a cobrar | I7: COBROS proyectados | J7: Pago material | K7: Pago mano de obra | L7: Otros pagos | M7: PAGOS proyectados | N7: Saldo semanal | O7: Acumulado proyectado | P7: Costo financiero | Q7: Cobro REAL | R7: Pago REAL | S7: Acumulado REAL | T7: Real − proyectado
A8: 1 | B8: =Datos!$B$6+7*(A8-1) -> 46314 | C8: 24000 | D8: =IF(Datos!$B$8=0,0,C8/Datos!$B$8) -> 0.03 | E8: =IF(AND(A8<=Datos!$B$22,OR(MOD(A8,Datos!$B$11)=0,A8=Datos!$B$22)),SUMIFS($D$8:$D$59,$A$8:$A$59,">"&(A8-IF(MOD(A8,Datos!$B$11)=0,Datos!$B$11,MOD(A8,Datos!$B$11))),$A$8:$A$59,"<="&A8)*Datos!$B$7,0) -> 0 | F8: =E8*Datos!$B$9 -> 0 | G8: =E8*Datos!$B$10 -> 0 | H8: =E8-F8-G8 -> 0 | I8: =IF(A8=1,Datos!$B$7*Datos!$B$9,0)+IF(A8-Datos!$B$12>=1,INDEX($H$8:$H$59,A8-Datos!$B$12),0)+IF(A8=Datos!$B$22+Datos!$B$12+Datos!$B$13,SUM($G$8:$G$59),0) -> 300000 | J8: =IF(A8-Datos!$B$15>=1,INDEX($C$8:$C$59,A8-Datos!$B$15),0)*Datos!$B$14 -> 0 | K8: =C8*Datos!$B$16 -> 8400 | L8: =IF(A8>1,INDEX($C$8:$C$59,A8-1),0)*Datos!$B$17 -> 0 | M8: =J8+K8+L8 -> 8400 | N8: =I8-M8 -> 291600 | O8: =N8 -> 291600 | P8: =MAX(0,-O8)*((1+Datos!$B$18)^(1/52)-1) -> 0 | S8: =IF(AND(Q8="",R8=""),"",SUM($Q$8:Q8)-SUM($R$8:R8)) | T8: =IF(S8="","",S8-O8)
A9: 2 | B9: =Datos!$B$6+7*(A9-1) -> 46321 | C9: 56000 | D9: =IF(Datos!$B$8=0,0,C9/Datos!$B$8) -> 0.07 | E9: =IF(AND(A9<=Datos!$B$22,OR(MOD(A9,Datos!$B$11)=0,A9=Datos!$B$22)),SUMIFS($D$8:$D$59,$A$8:$A$59,">"&(A9-IF(MOD(A9,Datos!$B$11)=0,Datos!$B$11,MOD(A9,Datos!$B$11))),$A$8:$A$59,"<="&A9)*Datos!$B$7,0) -> 100000 | F9: =E9*Datos!$B$9 -> 30000 | G9: =E9*Datos!$B$10 -> 5000 | H9: =E9-F9-G9 -> 65000 | I9: =IF(A9=1,Datos!$B$7*Datos!$B$9,0)+IF(A9-Datos!$B$12>=1,INDEX($H$8:$H$59,A9-Datos!$B$12),0)+IF(A9=Datos!$B$22+Datos!$B$12+Datos!$B$13,SUM($G$8:$G$59),0) -> 0 | J9: =IF(A9-Datos!$B$15>=1,INDEX($C$8:$C$59,A9-Datos!$B$15),0)*Datos!$B$14 -> 0 | K9: =C9*Datos!$B$16 -> 19600 | L9: =IF(A9>1,INDEX($C$8:$C$59,A9-1),0)*Datos!$B$17 -> 2400 | M9: =J9+K9+L9 -> 22000 | N9: =I9-M9 -> -22000 | O9: =O8+N9 -> 269600 | P9: =MAX(0,-O9)*((1+Datos!$B$18)^(1/52)-1) -> 0 | S9: =IF(AND(Q9="",R9=""),"",SUM($Q$8:Q9)-SUM($R$8:R9)) | T9: =IF(S9="","",S9-O9)
A10: 3 | B10: =Datos!$B$6+7*(A10-1) -> 46328 | C10: 88000 | D10: =IF(Datos!$B$8=0,0,C10/Datos!$B$8) -> 0.11 | E10: =IF(AND(A10<=Datos!$B$22,OR(MOD(A10,Datos!$B$11)=0,A10=Datos!$B$22)),SUMIFS($D$8:$D$59,$A$8:$A$59,">"&(A10-IF(MOD(A10,Datos!$B$11)=0,Datos!$B$11,MOD(A10,Datos!$B$11))),$A$8:$A$59,"<="&A10)*Datos!$B$7,0) -> 0 | F10: =E10*Datos!$B$9 -> 0 | G10: =E10*Datos!$B$10 -> 0 | H10: =E10-F10-G10 -> 0 | I10: =IF(A10=1,Datos!$B$7*Datos!$B$9,0)+IF(A10-Datos!$B$12>=1,INDEX($H$8:$H$59,A10-Datos!$B$12),0)+IF(A10=Datos!$B$22+Datos!$B$12+Datos!$B$13,SUM($G$8:$G$59),0) -> 0 | J10: =IF(A10-Datos!$B$15>=1,INDEX($C$8:$C$59,A10-Datos!$B$15),0)*Datos!$B$14 -> 13200 | K10: =C10*Datos!$B$16 -> 30800 | L10: =IF(A10>1,INDEX($C$8:$C$59,A10-1),0)*Datos!$B$17 -> 5600 | M10: =J10+K10+L10 -> 49600 | N10: =I10-M10 -> -49600 | O10: =O9+N10 -> 220000 | P10: =MAX(0,-O10)*((1+Datos!$B$18)^(1/52)-1) -> 0 | S10: =IF(AND(Q10="",R10=""),"",SUM($Q$8:Q10)-SUM($R$8:R10)) | T10: =IF(S10="","",S10-O10)
A11: 4 | B11: =Datos!$B$6+7*(A11-1) -> 46335 | C11: 112000 | D11: =IF(Datos!$B$8=0,0,C11/Datos!$B$8) -> 0.14 | E11: =IF(AND(A11<=Datos!$B$22,OR(MOD(A11,Datos!$B$11)=0,A11=Datos!$B$22)),SUMIFS($D$8:$D$59,$A$8:$A$59,">"&(A11-IF(MOD(A11,Datos!$B$11)=0,Datos!$B$11,MOD(A11,Datos!$B$11))),$A$8:$A$59,"<="&A11)*Datos!$B$7,0) -> 250000 | F11: =E11*Datos!$B$9 -> 75000 | G11: =E11*Datos!$B$10 -> 12500 | H11: =E11-F11-G11 -> 162500 | I11: =IF(A11=1,Datos!$B$7*Datos!$B$9,0)+IF(A11-Datos!$B$12>=1,INDEX($H$8:$H$59,A11-Datos!$B$12),0)+IF(A11=Datos!$B$22+Datos!$B$12+Datos!$B$13,SUM($G$8:$G$59),0) -> 65000 | J11: =IF(A11-Datos!$B$15>=1,INDEX($C$8:$C$59,A11-Datos!$B$15),0)*Datos!$B$14 -> 30800 | K11: =C11*Datos!$B$16 -> 39200 | L11: =IF(A11>1,INDEX($C$8:$C$59,A11-1),0)*Datos!$B$17 -> 8800 | M11: =J11+K11+L11 -> 78800 | N11: =I11-M11 -> -13800 | O11: =O10+N11 -> 206200 | P11: =MAX(0,-O11)*((1+Datos!$B$18)^(1/52)-1) -> 0 | S11: =IF(AND(Q11="",R11=""),"",SUM($Q$8:Q11)-SUM($R$8:R11)) | T11: =IF(S11="","",S11-O11)
A12: 5 | B12: =Datos!$B$6+7*(A12-1) -> 46342 | C12: 120000 | D12: =IF(Datos!$B$8=0,0,C12/Datos!$B$8) -> 0.15 | E12: =IF(AND(A12<=Datos!$B$22,OR(MOD(A12,Datos!$B$11)=0,A12=Datos!$B$22)),SUMIFS($D$8:$D$59,$A$8:$A$59,">"&(A12-IF(MOD(A12,Datos!$B$11)=0,Datos!$B$11,MOD(A12,Datos!$B$11))),$A$8:$A$59,"<="&A12)*Datos!$B$7,0) -> 0 | F12: =E12*Datos!$B$9 -> 0 | G12: =E12*Datos!$B$10 -> 0 | H12: =E12-F12-G12 -> 0 | I12: =IF(A12=1,Datos!$B$7*Datos!$B$9,0)+IF(A12-Datos!$B$12>=1,INDEX($H$8:$H$59,A12-Datos!$B$12),0)+IF(A12=Datos!$B$22+Datos!$B$12+Datos!$B$13,SUM($G$8:$G$59),0) -> 0 | J12: =IF(A12-Datos!$B$15>=1,INDEX($C$8:$C$59,A12-Datos!$B$15),0)*Datos!$B$14 -> 48400 | K12: =C12*Datos!$B$16 -> 42000 | L12: =IF(A12>1,INDEX($C$8:$C$59,A12-1),0)*Datos!$B$17 -> 11200 | M12: =J12+K12+L12 -> 101600 | N12: =I12-M12 -> -101600 | O12: =O11+N12 -> 104600 | P12: =MAX(0,-O12)*((1+Datos!$B$18)^(1/52)-1) -> 0 | S12: =IF(AND(Q12="",R12=""),"",SUM($Q$8:Q12)-SUM($R$8:R12)) | T12: =IF(S12="","",S12-O12)
A13: 6 | B13: =Datos!$B$6+7*(A13-1) -> 46349 | C13: 120000 | D13: =IF(Datos!$B$8=0,0,C13/Datos!$B$8) -> 0.15 | E13: =IF(AND(A13<=Datos!$B$22,OR(MOD(A13,Datos!$B$11)=0,A13=Datos!$B$22)),SUMIFS($D$8:$D$59,$A$8:$A$59,">"&(A13-IF(MOD(A13,Datos!$B$11)=0,Datos!$B$11,MOD(A13,Datos!$B$11))),$A$8:$A$59,"<="&A13)*Datos!$B$7,0) -> 300000 | F13: =E13*Datos!$B$9 -> 90000 | G13: =E13*Datos!$B$10 -> 15000 | H13: =E13-F13-G13 -> 195000 | I13: =IF(A13=1,Datos!$B$7*Datos!$B$9,0)+IF(A13-Datos!$B$12>=1,INDEX($H$8:$H$59,A13-Datos!$B$12),0)+IF(A13=Datos!$B$22+Datos!$B$12+Datos!$B$13,SUM($G$8:$G$59),0) -> 162500 | J13: =IF(A13-Datos!$B$15>=1,INDEX($C$8:$C$59,A13-Datos!$B$15),0)*Datos!$B$14 -> 61600 | K13: =C13*Datos!$B$16 -> 42000 | L13: =IF(A13>1,INDEX($C$8:$C$59,A13-1),0)*Datos!$B$17 -> 12000 | M13: =J13+K13+L13 -> 115600 | N13: =I13-M13 -> 46900 | O13: =O12+N13 -> 151500 | P13: =MAX(0,-O13)*((1+Datos!$B$18)^(1/52)-1) -> 0 | S13: =IF(AND(Q13="",R13=""),"",SUM($Q$8:Q13)-SUM($R$8:R13)) | T13: =IF(S13="","",S13-O13)
A14: 7 | B14: =Datos!$B$6+7*(A14-1) -> 46356 | C14: 104000 | D14: =IF(Datos!$B$8=0,0,C14/Datos!$B$8) -> 0.13 | E14: =IF(AND(A14<=Datos!$B$22,OR(MOD(A14,Datos!$B$11)=0,A14=Datos!$B$22)),SUMIFS($D$8:$D$59,$A$8:$A$59,">"&(A14-IF(MOD(A14,Datos!$B$11)=0,Datos!$B$11,MOD(A14,Datos!$B$11))),$A$8:$A$59,"<="&A14)*Datos!$B$7,0) -> 0 | F14: =E14*Datos!$B$9 -> 0 | G14: =E14*Datos!$B$10 -> 0 | H14: =E14-F14-G14 -> 0 | I14: =IF(A14=1,Datos!$B$7*Datos!$B$9,0)+IF(A14-Datos!$B$12>=1,INDEX($H$8:$H$59,A14-Datos!$B$12),0)+IF(A14=Datos!$B$22+Datos!$B$12+Datos!$B$13,SUM($G$8:$G$59),0) -> 0 | J14: =IF(A14-Datos!$B$15>=1,INDEX($C$8:$C$59,A14-Datos!$B$15),0)*Datos!$B$14 -> 66000 | K14: =C14*Datos!$B$16 -> 36400 | L14: =IF(A14>1,INDEX($C$8:$C$59,A14-1),0)*Datos!$B$17 -> 12000 | M14: =J14+K14+L14 -> 114400 | N14: =I14-M14 -> -114400 | O14: =O13+N14 -> 37100 | P14: =MAX(0,-O14)*((1+Datos!$B$18)^(1/52)-1) -> 0 | S14: =IF(AND(Q14="",R14=""),"",SUM($Q$8:Q14)-SUM($R$8:R14)) | T14: =IF(S14="","",S14-O14)
A15: 8 | B15: =Datos!$B$6+7*(A15-1) -> 46363 | C15: 80000 | D15: =IF(Datos!$B$8=0,0,C15/Datos!$B$8) -> 0.1 | E15: =IF(AND(A15<=Datos!$B$22,OR(MOD(A15,Datos!$B$11)=0,A15=Datos!$B$22)),SUMIFS($D$8:$D$59,$A$8:$A$59,">"&(A15-IF(MOD(A15,Datos!$B$11)=0,Datos!$B$11,MOD(A15,Datos!$B$11))),$A$8:$A$59,"<="&A15)*Datos!$B$7,0) -> 230000 | F15: =E15*Datos!$B$9 -> 69000 | G15: =E15*Datos!$B$10 -> 11500 | H15: =E15-F15-G15 -> 149500 | I15: =IF(A15=1,Datos!$B$7*Datos!$B$9,0)+IF(A15-Datos!$B$12>=1,INDEX($H$8:$H$59,A15-Datos!$B$12),0)+IF(A15=Datos!$B$22+Datos!$B$12+Datos!$B$13,SUM($G$8:$G$59),0) -> 195000 | J15: =IF(A15-Datos!$B$15>=1,INDEX($C$8:$C$59,A15-Datos!$B$15),0)*Datos!$B$14 -> 66000 | K15: =C15*Datos!$B$16 -> 28000 | L15: =IF(A15>1,INDEX($C$8:$C$59,A15-1),0)*Datos!$B$17 -> 10400 | M15: =J15+K15+L15 -> 104400 | N15: =I15-M15 -> 90600 | O15: =O14+N15 -> 127700 | P15: =MAX(0,-O15)*((1+Datos!$B$18)^(1/52)-1) -> 0 | S15: =IF(AND(Q15="",R15=""),"",SUM($Q$8:Q15)-SUM($R$8:R15)) | T15: =IF(S15="","",S15-O15)
A16: 9 | B16: =Datos!$B$6+7*(A16-1) -> 46370 | C16: 56000 | D16: =IF(Datos!$B$8=0,0,C16/Datos!$B$8) -> 0.07 | E16: =IF(AND(A16<=Datos!$B$22,OR(MOD(A16,Datos!$B$11)=0,A16=Datos!$B$22)),SUMIFS($D$8:$D$59,$A$8:$A$59,">"&(A16-IF(MOD(A16,Datos!$B$11)=0,Datos!$B$11,MOD(A16,Datos!$B$11))),$A$8:$A$59,"<="&A16)*Datos!$B$7,0) -> 0 | F16: =E16*Datos!$B$9 -> 0 | G16: =E16*Datos!$B$10 -> 0 | H16: =E16-F16-G16 -> 0 | I16: =IF(A16=1,Datos!$B$7*Datos!$B$9,0)+IF(A16-Datos!$B$12>=1,INDEX($H$8:$H$59,A16-Datos!$B$12),0)+IF(A16=Datos!$B$22+Datos!$B$12+Datos!$B$13,SUM($G$8:$G$59),0) -> 0 | J16: =IF(A16-Datos!$B$15>=1,INDEX($C$8:$C$59,A16-Datos!$B$15),0)*Datos!$B$14 -> 57200 | K16: =C16*Datos!$B$16 -> 19600 | L16: =IF(A16>1,INDEX($C$8:$C$59,A16-1),0)*Datos!$B$17 -> 8000 | M16: =J16+K16+L16 -> 84800 | N16: =I16-M16 -> -84800 | O16: =O15+N16 -> 42900 | P16: =MAX(0,-O16)*((1+Datos!$B$18)^(1/52)-1) -> 0 | S16: =IF(AND(Q16="",R16=""),"",SUM($Q$8:Q16)-SUM($R$8:R16)) | T16: =IF(S16="","",S16-O16)
A17: 10 | B17: =Datos!$B$6+7*(A17-1) -> 46377 | C17: 40000 | D17: =IF(Datos!$B$8=0,0,C17/Datos!$B$8) -> 0.05 | E17: =IF(AND(A17<=Datos!$B$22,OR(MOD(A17,Datos!$B$11)=0,A17=Datos!$B$22)),SUMIFS($D$8:$D$59,$A$8:$A$59,">"&(A17-IF(MOD(A17,Datos!$B$11)=0,Datos!$B$11,MOD(A17,Datos!$B$11))),$A$8:$A$59,"<="&A17)*Datos!$B$7,0) -> 120000 | F17: =E17*Datos!$B$9 -> 36000 | G17: =E17*Datos!$B$10 -> 6000 | H17: =E17-F17-G17 -> 78000 | I17: =IF(A17=1,Datos!$B$7*Datos!$B$9,0)+IF(A17-Datos!$B$12>=1,INDEX($H$8:$H$59,A17-Datos!$B$12),0)+IF(A17=Datos!$B$22+Datos!$B$12+Datos!$B$13,SUM($G$8:$G$59),0) -> 149500 | J17: =IF(A17-Datos!$B$15>=1,INDEX($C$8:$C$59,A17-Datos!$B$15),0)*Datos!$B$14 -> 44000 | K17: =C17*Datos!$B$16 -> 14000 | L17: =IF(A17>1,INDEX($C$8:$C$59,A17-1),0)*Datos!$B$17 -> 5600 | M17: =J17+K17+L17 -> 63600 | N17: =I17-M17 -> 85900 | O17: =O16+N17 -> 128800 | P17: =MAX(0,-O17)*((1+Datos!$B$18)^(1/52)-1) -> 0 | S17: =IF(AND(Q17="",R17=""),"",SUM($Q$8:Q17)-SUM($R$8:R17)) | T17: =IF(S17="","",S17-O17)
A18: 11 | B18: =Datos!$B$6+7*(A18-1) -> 46384 | D18: =IF(Datos!$B$8=0,0,C18/Datos!$B$8) -> 0 | E18: =IF(AND(A18<=Datos!$B$22,OR(MOD(A18,Datos!$B$11)=0,A18=Datos!$B$22)),SUMIFS($D$8:$D$59,$A$8:$A$59,">"&(A18-IF(MOD(A18,Datos!$B$11)=0,Datos!$B$11,MOD(A18,Datos!$B$11))),$A$8:$A$59,"<="&A18)*Datos!$B$7,0) -> 0 | F18: =E18*Datos!$B$9 -> 0 | G18: =E18*Datos!$B$10 -> 0 | H18: =E18-F18-G18 -> 0 | I18: =IF(A18=1,Datos!$B$7*Datos!$B$9,0)+IF(A18-Datos!$B$12>=1,INDEX($H$8:$H$59,A18-Datos!$B$12),0)+IF(A18=Datos!$B$22+Datos!$B$12+Datos!$B$13,SUM($G$8:$G$59),0) -> 0 | J18: =IF(A18-Datos!$B$15>=1,INDEX($C$8:$C$59,A18-Datos!$B$15),0)*Datos!$B$14 -> 30800 | K18: =C18*Datos!$B$16 -> 0 | L18: =IF(A18>1,INDEX($C$8:$C$59,A18-1),0)*Datos!$B$17 -> 4000 | M18: =J18+K18+L18 -> 34800 | N18: =I18-M18 -> -34800 | O18: =O17+N18 -> 94000 | P18: =MAX(0,-O18)*((1+Datos!$B$18)^(1/52)-1) -> 0 | S18: =IF(AND(Q18="",R18=""),"",SUM($Q$8:Q18)-SUM($R$8:R18)) | T18: =IF(S18="","",S18-O18)
A19: 12 | B19: =Datos!$B$6+7*(A19-1) -> 46391 | D19: =IF(Datos!$B$8=0,0,C19/Datos!$B$8) -> 0 | E19: =IF(AND(A19<=Datos!$B$22,OR(MOD(A19,Datos!$B$11)=0,A19=Datos!$B$22)),SUMIFS($D$8:$D$59,$A$8:$A$59,">"&(A19-IF(MOD(A19,Datos!$B$11)=0,Datos!$B$11,MOD(A19,Datos!$B$11))),$A$8:$A$59,"<="&A19)*Datos!$B$7,0) -> 0 | F19: =E19*Datos!$B$9 -> 0 | G19: =E19*Datos!$B$10 -> 0 | H19: =E19-F19-G19 -> 0 | I19: =IF(A19=1,Datos!$B$7*Datos!$B$9,0)+IF(A19-Datos!$B$12>=1,INDEX($H$8:$H$59,A19-Datos!$B$12),0)+IF(A19=Datos!$B$22+Datos!$B$12+Datos!$B$13,SUM($G$8:$G$59),0) -> 78000 | J19: =IF(A19-Datos!$B$15>=1,INDEX($C$8:$C$59,A19-Datos!$B$15),0)*Datos!$B$14 -> 22000 | K19: =C19*Datos!$B$16 -> 0 | L19: =IF(A19>1,INDEX($C$8:$C$59,A19-1),0)*Datos!$B$17 -> 0 | M19: =J19+K19+L19 -> 22000 | N19: =I19-M19 -> 56000 | O19: =O18+N19 -> 150000 | P19: =MAX(0,-O19)*((1+Datos!$B$18)^(1/52)-1) -> 0 | S19: =IF(AND(Q19="",R19=""),"",SUM($Q$8:Q19)-SUM($R$8:R19)) | T19: =IF(S19="","",S19-O19)
A20: 13 | B20: =Datos!$B$6+7*(A20-1) -> 46398 | D20: =IF(Datos!$B$8=0,0,C20/Datos!$B$8) -> 0 | E20: =IF(AND(A20<=Datos!$B$22,OR(MOD(A20,Datos!$B$11)=0,A20=Datos!$B$22)),SUMIFS($D$8:$D$59,$A$8:$A$59,">"&(A20-IF(MOD(A20,Datos!$B$11)=0,Datos!$B$11,MOD(A20,Datos!$B$11))),$A$8:$A$59,"<="&A20)*Datos!$B$7,0) -> 0 | F20: =E20*Datos!$B$9 -> 0 | G20: =E20*Datos!$B$10 -> 0 | H20: =E20-F20-G20 -> 0 | I20: =IF(A20=1,Datos!$B$7*Datos!$B$9,0)+IF(A20-Datos!$B$12>=1,INDEX($H$8:$H$59,A20-Datos!$B$12),0)+IF(A20=Datos!$B$22+Datos!$B$12+Datos!$B$13,SUM($G$8:$G$59),0) -> 0 | J20: =IF(A20-Datos!$B$15>=1,INDEX($C$8:$C$59,A20-Datos!$B$15),0)*Datos!$B$14 -> 0 | K20: =C20*Datos!$B$16 -> 0 | L20: =IF(A20>1,INDEX($C$8:$C$59,A20-1),0)*Datos!$B$17 -> 0 | M20: =J20+K20+L20 -> 0 | N20: =I20-M20 -> 0 | O20: =O19+N20 -> 150000 | P20: =MAX(0,-O20)*((1+Datos!$B$18)^(1/52)-1) -> 0 | S20: =IF(AND(Q20="",R20=""),"",SUM($Q$8:Q20)-SUM($R$8:R20)) | T20: =IF(S20="","",S20-O20)
A21: 14 | B21: =Datos!$B$6+7*(A21-1) -> 46405 | D21: =IF(Datos!$B$8=0,0,C21/Datos!$B$8) -> 0 | E21: =IF(AND(A21<=Datos!$B$22,OR(MOD(A21,Datos!$B$11)=0,A21=Datos!$B$22)),SUMIFS($D$8:$D$59,$A$8:$A$59,">"&(A21-IF(MOD(A21,Datos!$B$11)=0,Datos!$B$11,MOD(A21,Datos!$B$11))),$A$8:$A$59,"<="&A21)*Datos!$B$7,0) -> 0 | F21: =E21*Datos!$B$9 -> 0 | G21: =E21*Datos!$B$10 -> 0 | H21: =E21-F21-G21 -> 0 | I21: =IF(A21=1,Datos!$B$7*Datos!$B$9,0)+IF(A21-Datos!$B$12>=1,INDEX($H$8:$H$59,A21-Datos!$B$12),0)+IF(A21=Datos!$B$22+Datos!$B$12+Datos!$B$13,SUM($G$8:$G$59),0) -> 0 | J21: =IF(A21-Datos!$B$15>=1,INDEX($C$8:$C$59,A21-Datos!$B$15),0)*Datos!$B$14 -> 0 | K21: =C21*Datos!$B$16 -> 0 | L21: =IF(A21>1,INDEX($C$8:$C$59,A21-1),0)*Datos!$B$17 -> 0 | M21: =J21+K21+L21 -> 0 | N21: =I21-M21 -> 0 | O21: =O20+N21 -> 150000 | P21: =MAX(0,-O21)*((1+Datos!$B$18)^(1/52)-1) -> 0 | S21: =IF(AND(Q21="",R21=""),"",SUM($Q$8:Q21)-SUM($R$8:R21)) | T21: =IF(S21="","",S21-O21)
A22: 15 | B22: =Datos!$B$6+7*(A22-1) -> 46412 | D22: =IF(Datos!$B$8=0,0,C22/Datos!$B$8) -> 0 | E22: =IF(AND(A22<=Datos!$B$22,OR(MOD(A22,Datos!$B$11)=0,A22=Datos!$B$22)),SUMIFS($D$8:$D$59,$A$8:$A$59,">"&(A22-IF(MOD(A22,Datos!$B$11)=0,Datos!$B$11,MOD(A22,Datos!$B$11))),$A$8:$A$59,"<="&A22)*Datos!$B$7,0) -> 0 | F22: =E22*Datos!$B$9 -> 0 | G22: =E22*Datos!$B$10 -> 0 | H22: =E22-F22-G22 -> 0 | I22: =IF(A22=1,Datos!$B$7*Datos!$B$9,0)+IF(A22-Datos!$B$12>=1,INDEX($H$8:$H$59,A22-Datos!$B$12),0)+IF(A22=Datos!$B$22+Datos!$B$12+Datos!$B$13,SUM($G$8:$G$59),0) -> 0 | J22: =IF(A22-Datos!$B$15>=1,INDEX($C$8:$C$59,A22-Datos!$B$15),0)*Datos!$B$14 -> 0 | K22: =C22*Datos!$B$16 -> 0 | L22: =IF(A22>1,INDEX($C$8:$C$59,A22-1),0)*Datos!$B$17 -> 0 | M22: =J22+K22+L22 -> 0 | N22: =I22-M22 -> 0 | O22: =O21+N22 -> 150000 | P22: =MAX(0,-O22)*((1+Datos!$B$18)^(1/52)-1) -> 0 | S22: =IF(AND(Q22="",R22=""),"",SUM($Q$8:Q22)-SUM($R$8:R22)) | T22: =IF(S22="","",S22-O22)
A23: 16 | B23: =Datos!$B$6+7*(A23-1) -> 46419 | D23: =IF(Datos!$B$8=0,0,C23/Datos!$B$8) -> 0 | E23: =IF(AND(A23<=Datos!$B$22,OR(MOD(A23,Datos!$B$11)=0,A23=Datos!$B$22)),SUMIFS($D$8:$D$59,$A$8:$A$59,">"&(A23-IF(MOD(A23,Datos!$B$11)=0,Datos!$B$11,MOD(A23,Datos!$B$11))),$A$8:$A$59,"<="&A23)*Datos!$B$7,0) -> 0 | F23: =E23*Datos!$B$9 -> 0 | G23: =E23*Datos!$B$10 -> 0 | H23: =E23-F23-G23 -> 0 | I23: =IF(A23=1,Datos!$B$7*Datos!$B$9,0)+IF(A23-Datos!$B$12>=1,INDEX($H$8:$H$59,A23-Datos!$B$12),0)+IF(A23=Datos!$B$22+Datos!$B$12+Datos!$B$13,SUM($G$8:$G$59),0) -> 50000 | J23: =IF(A23-Datos!$B$15>=1,INDEX($C$8:$C$59,A23-Datos!$B$15),0)*Datos!$B$14 -> 0 | K23: =C23*Datos!$B$16 -> 0 | L23: =IF(A23>1,INDEX($C$8:$C$59,A23-1),0)*Datos!$B$17 -> 0 | M23: =J23+K23+L23 -> 0 | N23: =I23-M23 -> 50000 | O23: =O22+N23 -> 200000 | P23: =MAX(0,-O23)*((1+Datos!$B$18)^(1/52)-1) -> 0 | S23: =IF(AND(Q23="",R23=""),"",SUM($Q$8:Q23)-SUM($R$8:R23)) | T23: =IF(S23="","",S23-O23)
A24: 17 | B24: =Datos!$B$6+7*(A24-1) -> 46426 | D24: =IF(Datos!$B$8=0,0,C24/Datos!$B$8) -> 0 | E24: =IF(AND(A24<=Datos!$B$22,OR(MOD(A24,Datos!$B$11)=0,A24=Datos!$B$22)),SUMIFS($D$8:$D$59,$A$8:$A$59,">"&(A24-IF(MOD(A24,Datos!$B$11)=0,Datos!$B$11,MOD(A24,Datos!$B$11))),$A$8:$A$59,"<="&A24)*Datos!$B$7,0) -> 0 | F24: =E24*Datos!$B$9 -> 0 | G24: =E24*Datos!$B$10 -> 0 | H24: =E24-F24-G24 -> 0 | I24: =IF(A24=1,Datos!$B$7*Datos!$B$9,0)+IF(A24-Datos!$B$12>=1,INDEX($H$8:$H$59,A24-Datos!$B$12),0)+IF(A24=Datos!$B$22+Datos!$B$12+Datos!$B$13,SUM($G$8:$G$59),0) -> 0 | J24: =IF(A24-Datos!$B$15>=1,INDEX($C$8:$C$59,A24-Datos!$B$15),0)*Datos!$B$14 -> 0 | K24: =C24*Datos!$B$16 -> 0 | L24: =IF(A24>1,INDEX($C$8:$C$59,A24-1),0)*Datos!$B$17 -> 0 | M24: =J24+K24+L24 -> 0 | N24: =I24-M24 -> 0 | O24: =O23+N24 -> 200000 | P24: =MAX(0,-O24)*((1+Datos!$B$18)^(1/52)-1) -> 0 | S24: =IF(AND(Q24="",R24=""),"",SUM($Q$8:Q24)-SUM($R$8:R24)) | T24: =IF(S24="","",S24-O24)
A25: 18 | B25: =Datos!$B$6+7*(A25-1) -> 46433 | D25: =IF(Datos!$B$8=0,0,C25/Datos!$B$8) -> 0 | E25: =IF(AND(A25<=Datos!$B$22,OR(MOD(A25,Datos!$B$11)=0,A25=Datos!$B$22)),SUMIFS($D$8:$D$59,$A$8:$A$59,">"&(A25-IF(MOD(A25,Datos!$B$11)=0,Datos!$B$11,MOD(A25,Datos!$B$11))),$A$8:$A$59,"<="&A25)*Datos!$B$7,0) -> 0 | F25: =E25*Datos!$B$9 -> 0 | G25: =E25*Datos!$B$10 -> 0 | H25: =E25-F25-G25 -> 0 | I25: =IF(A25=1,Datos!$B$7*Datos!$B$9,0)+IF(A25-Datos!$B$12>=1,INDEX($H$8:$H$59,A25-Datos!$B$12),0)+IF(A25=Datos!$B$22+Datos!$B$12+Datos!$B$13,SUM($G$8:$G$59),0) -> 0 | J25: =IF(A25-Datos!$B$15>=1,INDEX($C$8:$C$59,A25-Datos!$B$15),0)*Datos!$B$14 -> 0 | K25: =C25*Datos!$B$16 -> 0 | L25: =IF(A25>1,INDEX($C$8:$C$59,A25-1),0)*Datos!$B$17 -> 0 | M25: =J25+K25+L25 -> 0 | N25: =I25-M25 -> 0 | O25: =O24+N25 -> 200000 | P25: =MAX(0,-O25)*((1+Datos!$B$18)^(1/52)-1) -> 0 | S25: =IF(AND(Q25="",R25=""),"",SUM($Q$8:Q25)-SUM($R$8:R25)) | T25: =IF(S25="","",S25-O25)
A26: 19 | B26: =Datos!$B$6+7*(A26-1) -> 46440 | D26: =IF(Datos!$B$8=0,0,C26/Datos!$B$8) -> 0 | E26: =IF(AND(A26<=Datos!$B$22,OR(MOD(A26,Datos!$B$11)=0,A26=Datos!$B$22)),SUMIFS($D$8:$D$59,$A$8:$A$59,">"&(A26-IF(MOD(A26,Datos!$B$11)=0,Datos!$B$11,MOD(A26,Datos!$B$11))),$A$8:$A$59,"<="&A26)*Datos!$B$7,0) -> 0 | F26: =E26*Datos!$B$9 -> 0 | G26: =E26*Datos!$B$10 -> 0 | H26: =E26-F26-G26 -> 0 | I26: =IF(A26=1,Datos!$B$7*Datos!$B$9,0)+IF(A26-Datos!$B$12>=1,INDEX($H$8:$H$59,A26-Datos!$B$12),0)+IF(A26=Datos!$B$22+Datos!$B$12+Datos!$B$13,SUM($G$8:$G$59),0) -> 0 | J26: =IF(A26-Datos!$B$15>=1,INDEX($C$8:$C$59,A26-Datos!$B$15),0)*Datos!$B$14 -> 0 | K26: =C26*Datos!$B$16 -> 0 | L26: =IF(A26>1,INDEX($C$8:$C$59,A26-1),0)*Datos!$B$17 -> 0 | M26: =J26+K26+L26 -> 0 | N26: =I26-M26 -> 0 | O26: =O25+N26 -> 200000 | P26: =MAX(0,-O26)*((1+Datos!$B$18)^(1/52)-1) -> 0 | S26: =IF(AND(Q26="",R26=""),"",SUM($Q$8:Q26)-SUM($R$8:R26)) | T26: =IF(S26="","",S26-O26)
A27: 20 | B27: =Datos!$B$6+7*(A27-1) -> 46447 | D27: =IF(Datos!$B$8=0,0,C27/Datos!$B$8) -> 0 | E27: =IF(AND(A27<=Datos!$B$22,OR(MOD(A27,Datos!$B$11)=0,A27=Datos!$B$22)),SUMIFS($D$8:$D$59,$A$8:$A$59,">"&(A27-IF(MOD(A27,Datos!$B$11)=0,Datos!$B$11,MOD(A27,Datos!$B$11))),$A$8:$A$59,"<="&A27)*Datos!$B$7,0) -> 0 | F27: =E27*Datos!$B$9 -> 0 | G27: =E27*Datos!$B$10 -> 0 | H27: =E27-F27-G27 -> 0 | I27: =IF(A27=1,Datos!$B$7*Datos!$B$9,0)+IF(A27-Datos!$B$12>=1,INDEX($H$8:$H$59,A27-Datos!$B$12),0)+IF(A27=Datos!$B$22+Datos!$B$12+Datos!$B$13,SUM($G$8:$G$59),0) -> 0 | J27: =IF(A27-Datos!$B$15>=1,INDEX($C$8:$C$59,A27-Datos!$B$15),0)*Datos!$B$14 -> 0 | K27: =C27*Datos!$B$16 -> 0 | L27: =IF(A27>1,INDEX($C$8:$C$59,A27-1),0)*Datos!$B$17 -> 0 | M27: =J27+K27+L27 -> 0 | N27: =I27-M27 -> 0 | O27: =O26+N27 -> 200000 | P27: =MAX(0,-O27)*((1+Datos!$B$18)^(1/52)-1) -> 0 | S27: =IF(AND(Q27="",R27=""),"",SUM($Q$8:Q27)-SUM($R$8:R27)) | T27: =IF(S27="","",S27-O27)
A28: 21 | B28: =Datos!$B$6+7*(A28-1) -> 46454 | D28: =IF(Datos!$B$8=0,0,C28/Datos!$B$8) -> 0 | E28: =IF(AND(A28<=Datos!$B$22,OR(MOD(A28,Datos!$B$11)=0,A28=Datos!$B$22)),SUMIFS($D$8:$D$59,$A$8:$A$59,">"&(A28-IF(MOD(A28,Datos!$B$11)=0,Datos!$B$11,MOD(A28,Datos!$B$11))),$A$8:$A$59,"<="&A28)*Datos!$B$7,0) -> 0 | F28: =E28*Datos!$B$9 -> 0 | G28: =E28*Datos!$B$10 -> 0 | H28: =E28-F28-G28 -> 0 | I28: =IF(A28=1,Datos!$B$7*Datos!$B$9,0)+IF(A28-Datos!$B$12>=1,INDEX($H$8:$H$59,A28-Datos!$B$12),0)+IF(A28=Datos!$B$22+Datos!$B$12+Datos!$B$13,SUM($G$8:$G$59),0) -> 0 | J28: =IF(A28-Datos!$B$15>=1,INDEX($C$8:$C$59,A28-Datos!$B$15),0)*Datos!$B$14 -> 0 | K28: =C28*Datos!$B$16 -> 0 | L28: =IF(A28>1,INDEX($C$8:$C$59,A28-1),0)*Datos!$B$17 -> 0 | M28: =J28+K28+L28 -> 0 | N28: =I28-M28 -> 0 | O28: =O27+N28 -> 200000 | P28: =MAX(0,-O28)*((1+Datos!$B$18)^(1/52)-1) -> 0 | S28: =IF(AND(Q28="",R28=""),"",SUM($Q$8:Q28)-SUM($R$8:R28)) | T28: =IF(S28="","",S28-O28)
A29: 22 | B29: =Datos!$B$6+7*(A29-1) -> 46461 | D29: =IF(Datos!$B$8=0,0,C29/Datos!$B$8) -> 0 | E29: =IF(AND(A29<=Datos!$B$22,OR(MOD(A29,Datos!$B$11)=0,A29=Datos!$B$22)),SUMIFS($D$8:$D$59,$A$8:$A$59,">"&(A29-IF(MOD(A29,Datos!$B$11)=0,Datos!$B$11,MOD(A29,Datos!$B$11))),$A$8:$A$59,"<="&A29)*Datos!$B$7,0) -> 0 | F29: =E29*Datos!$B$9 -> 0 | G29: =E29*Datos!$B$10 -> 0 | H29: =E29-F29-G29 -> 0 | I29: =IF(A29=1,Datos!$B$7*Datos!$B$9,0)+IF(A29-Datos!$B$12>=1,INDEX($H$8:$H$59,A29-Datos!$B$12),0)+IF(A29=Datos!$B$22+Datos!$B$12+Datos!$B$13,SUM($G$8:$G$59),0) -> 0 | J29: =IF(A29-Datos!$B$15>=1,INDEX($C$8:$C$59,A29-Datos!$B$15),0)*Datos!$B$14 -> 0 | K29: =C29*Datos!$B$16 -> 0 | L29: =IF(A29>1,INDEX($C$8:$C$59,A29-1),0)*Datos!$B$17 -> 0 | M29: =J29+K29+L29 -> 0 | N29: =I29-M29 -> 0 | O29: =O28+N29 -> 200000 | P29: =MAX(0,-O29)*((1+Datos!$B$18)^(1/52)-1) -> 0 | S29: =IF(AND(Q29="",R29=""),"",SUM($Q$8:Q29)-SUM($R$8:R29)) | T29: =IF(S29="","",S29-O29)
... A59: 52 | B59: =Datos!$B$6+7*(A59-1) -> 46671 | D59: =IF(Datos!$B$8=0,0,C59/Datos!$B$8) -> 0 | E59: =IF(AND(A59<=Datos!$B$22,OR(MOD(A59,Datos!$B$11)=0,A59=Datos!$B$22)),SUMIFS($D$8:$D$59,$A$8:$A$59,">"&(A59-IF(MOD(A59,Datos!$B$11)=0,Datos!$B$11,MOD(A59,Datos!$B$11))),$A$8:$A$59,"<="&A59)*Datos!$B$7,0) -> 0 | F59: =E59*Datos!$B$9 -> 0 | G59: =E59*Datos!$B$10 -> 0 | H59: =E59-F59-G59 -> 0 | I59: =IF(A59=1,Datos!$B$7*Datos!$B$9,0)+IF(A59-Datos!$B$12>=1,INDEX($H$8:$H$59,A59-Datos!$B$12),0)+IF(A59=Datos!$B$22+Datos!$B$12+Datos!$B$13,SUM($G$8:$G$59),0) -> 0 | J59: =IF(A59-Datos!$B$15>=1,INDEX($C$8:$C$59,A59-Datos!$B$15),0)*Datos!$B$14 -> 0 | K59: =C59*Datos!$B$16 -> 0 | L59: =IF(A59>1,INDEX($C$8:$C$59,A59-1),0)*Datos!$B$17 -> 0 | M59: =J59+K59+L59 -> 0 | N59: =I59-M59 -> 0 | O59: =O58+N59 -> 200000 | P59: =MAX(0,-O59)*((1+Datos!$B$18)^(1/52)-1) -> 0 | S59: =IF(AND(Q59="",R59=""),"",SUM($Q$8:Q59)-SUM($R$8:R59)) | T59: =IF(S59="","",S59-O59)
A60: TOTAL | C60: =SUM(C8:C59) -> 800000 | E60: =SUM(E8:E59) -> 1000000 | F60: =SUM(F8:F59) -> 300000 | G60: =SUM(G8:G59) -> 50000 | H60: =SUM(H8:H59) -> 650000 | I60: =SUM(I8:I59) -> 1000000 | J60: =SUM(J8:J59) -> 440000 | K60: =SUM(K8:K59) -> 280000 | L60: =SUM(L8:L59) -> 80000 | ... N60: =SUM(N8:N59) -> 200000 | P60: =SUM(P8:P59) -> 0 | Q60: =SUM(Q8:Q59) -> 0 | R60: =SUM(R8:R59) -> 0
B61: Control: | C61: =IF(ABS(C60-Datos!B8)<1,"Cuadra con el presupuesto","No cuadra: revisa C") -> Cuadra con el presupuesto
B62: Columnas Q y R: captura lo cobrado y pagado cada semana; S y T se llenan solas y comparan contra lo proyectado.
