Workbook

Sheet Resumen
A1: Resumen por partida — Casa habitación 2 niveles — ejemplo
A3: Partida | B3: Importe sin IVA | C3: % del total | D3: Costo por m²
A4: Cimentación | B4: =SUMIF('Catálogo'!A5:A23,A4,'Catálogo'!H5:H23) | C4: =B4/B9 | D4: =IF(160>0,B4/160,0)
A5: Estructura | B5: =SUMIF('Catálogo'!A5:A23,A5,'Catálogo'!H5:H23) | C5: =B5/B9 | D5: =IF(160>0,B5/160,0)
A6: Albañilería | B6: =SUMIF('Catálogo'!A5:A23,A6,'Catálogo'!H5:H23) | C6: =B6/B9 | D6: =IF(160>0,B6/160,0)
A7: Acabados | B7: =SUMIF('Catálogo'!A5:A23,A7,'Catálogo'!H5:H23) | C7: =B7/B9 | D7: =IF(160>0,B7/160,0)
A8: Instalaciones | B8: =SUMIF('Catálogo'!A5:A23,A8,'Catálogo'!H5:H23) | C8: =B8/B9 | D8: =IF(160>0,B8/160,0)
A9: Total sin IVA | B9: =SUM(B4:B8) | D9: =IF(160>0,B9/160,0)
A10: Total con IVA | B10: =B9*(1+Sobrecosto!B7/100)
A12: Para revisión del DRO. Precios de referencia; sustituir por cotizaciones antes de contratar.

Sheet Catálogo
A1: Presupuesto — Casa habitación 2 niveles — ejemplo
A2: (ejemplo) · Tijuana, B.C. · Vértice Ingeniería, Arquitectura y Proyectos
A4: Partida | B4: Clave | C4: Concepto | D4: Unidad | E4: Cantidad | F4: Costo directo | G4: P.U. | H4: Importe
A5: Cimentación | B5: 001 | C5: Excavación a mano en material tipo II hasta 2 m | D5: m³ | E5: 46.47 | F5: =APU!F5 | G5: =ROUND(F5*Sobrecosto!$B$8,2) | H5: =E5*G5
A6: Cimentación | B6: 002 | C6: Plantilla de concreto f'c=100 kg/cm² de 5 cm | D6: m² | E6: 21.6 | F6: =APU!F14 | G6: =ROUND(F6*Sobrecosto!$B$8,2) | H6: =E6*G6
A7: Cimentación | B7: 003 | C7: Cimbra común en zapatas y contratrabes | D7: m² | E7: 43.2 | F7: =APU!F20 | G7: =ROUND(F7*Sobrecosto!$B$8,2) | H7: =E7*G7
A8: Estructura | B8: 004 | C8: Habilitado y armado de acero #3 y #4 | D8: kg | E8: 2200 | F8: =APU!F28 | G8: =ROUND(F8*Sobrecosto!$B$8,2) | H8: =E8*G8
A9: Estructura | B9: 005 | C9: Habilitado y armado de acero #5 a #8 | D9: kg | E9: 900 | F9: =APU!F36 | G9: =ROUND(F9*Sobrecosto!$B$8,2) | H9: =E9*G9
A10: Estructura | B10: 006 | C10: Colado de concreto premezclado bombeado y vibrado | D10: m³ | E10: 25.8 | F10: =APU!F45 | G10: =ROUND(F10*Sobrecosto!$B$8,2) | H10: =E10*G10
A11: Estructura | B11: 007 | C11: Cimbra de losa maciza con puntales | D11: m² | E11: 160 | F11: =APU!F51 | G11: =ROUND(F11*Sobrecosto!$B$8,2) | H11: =E11*G11
A12: Estructura | B12: 008 | C12: Cimbra de columnas acabado común | D12: m² | E12: 6.72 | F12: =APU!F57 | G12: =ROUND(F12*Sobrecosto!$B$8,2) | H12: =E12*G12
A13: Estructura | B13: 009 | C13: Cimbra de trabes acabado común | D13: m² | E13: 12.5 | F13: =APU!F63 | G13: =ROUND(F13*Sobrecosto!$B$8,2) | H13: =E13*G13
A14: Albañilería | B14: 010 | C14: Muro de block 15x20x40 junteado con mortero | D14: m² | E14: 238.68 | F14: =APU!F72 | G14: =ROUND(F14*Sobrecosto!$B$8,2) | H14: =E14*G14
A15: Albañilería | B15: 011 | C15: Castillo 15x15 armado, cimbrado y colado | D15: ml | E15: 124.8 | F15: =APU!F82 | G15: =ROUND(F15*Sobrecosto!$B$8,2) | H15: =E15*G15
A16: Albañilería | B16: 012 | C16: Dala o cadena 15x20 armada, cimbrada y colada | D16: ml | E16: 108 | F16: =APU!F88 | G16: =ROUND(F16*Sobrecosto!$B$8,2) | H16: =E16*G16
A17: Albañilería | B17: 013 | C17: Firme de concreto de 10 cm acabado pulido | D17: m² | E17: 80 | F17: =APU!F96 | G17: =ROUND(F17*Sobrecosto!$B$8,2) | H17: =E17*G17
A18: Acabados | B18: 014 | C18: Aplanado de mortero en muros, acabado fino | D18: m² | E18: 358.02 | F18: =APU!F105 | G18: =ROUND(F18*Sobrecosto!$B$8,2) | H18: =E18*G18
A19: Acabados | B19: 015 | C19: Piso cerámico/porcelanato pegado con adhesivo y boquilla | D19: m² | E19: 150 | F19: =APU!F111 | G19: =ROUND(F19*Sobrecosto!$B$8,2) | H19: =E19*G19
A20: Acabados | B20: 016 | C20: Pintura vinílica dos manos con sellador | D20: m² | E20: 637.36 | F20: =APU!F117 | G20: =ROUND(F20*Sobrecosto!$B$8,2) | H20: =E20*G20
A21: Acabados | B21: 017 | C21: Impermeabilización con sistema prefabricado | D21: m² | E21: 85 | F21: =APU!F123 | G21: =ROUND(F21*Sobrecosto!$B$8,2) | H21: =E21*G21
A22: Instalaciones | B22: 018 | C22: Salida eléctrica (contacto o apagador) con tubería y cableado | D22: sal | E22: 70 | F22: =APU!F129 | G22: =ROUND(F22*Sobrecosto!$B$8,2) | H22: =E22*G22
A23: Instalaciones | B23: 019 | C23: Salida hidráulica o sanitaria por mueble | D23: sal | E23: 18 | F23: =APU!F135 | G23: =ROUND(F23*Sobrecosto!$B$8,2) | H23: =E23*G23
G25: Subtotal | H25: =SUM(H5:H23)
G26: IVA | H26: =H25*Sobrecosto!B7/100
G27: Total | H27: =H25+H26

Sheet Sobrecosto
A1: Concepto | B1: Valor
A2: Indirectos de oficina % | B2: 6
A3: Indirectos de campo % | B3: 6
A4: Financiamiento % | B4: 1
A5: Utilidad % | B5: 10
A6: Cargos adicionales % | B6: 0
A7: IVA % | B7: 8
A8: Factor de sobrecosto | B8: =(1+(B2+B3)/100)*(1+B4/100)*(1+B5/100)*(1+B6/100)

Sheet APU
A1: 001 | B1: Excavación a mano en material tipo II hasta 2 m | E1: m³
A2: Tipo | B2: Insumo | C2: Unidad | D2: Cantidad | E2: Precio | F2: Importe | G2: Fuente
A3: Mano de obra | B3: 1 peón (rend. 3.75 m³/jor) | C3: jor | D3: 0.266667 | E3: 908.43 | F3: =D3*E3 | G3: FSR 2026 Tijuana
A4: Herramienta | B4: Herramienta menor (3% de M.O.) | C4: % | D4: 0.03 | E4: =SUMIF(A3:A3,"Mano de obra",F3:F3) | F4: =D4*E4
E5: Costo directo | F5: =SUM(F3:F4)
A7: 002 | B7: Plantilla de concreto f'c=100 kg/cm² de 5 cm | E7: m²
A8: Tipo | B8: Insumo | C8: Unidad | D8: Cantidad | E8: Precio | F8: Importe | G8: Fuente
A9: Material | B9: Cemento gris CPC 30R Bulto 50 kg, menudeo | C9: bulto | D9: 0.28 | E9: 253 | F9: =D9*E9 | G9: Promedio nacional de referencia (CDMX, Monterrey, Guadalajara, Querétaro), publicado en agosto 2026 (ago 2026) + 10% Tijuana
A10: Material | B10: Arena de mina / río Varía por banco | C10: m³ | D10: 0.03 | E10: 715 | F10: =D10*E10 | G10: Promedio nacional de referencia (CDMX, Monterrey, Guadalajara, Querétaro), publicado en agosto 2026 (ago 2026) + 10% Tijuana
A11: Material | B11: Grava 3/4" Triturada o de banco | C11: m³ | D11: 0.04 | E11: 792 | F11: =D11*E11 | G11: Promedio nacional de referencia (CDMX, Monterrey, Guadalajara, Querétaro), publicado en agosto 2026 (ago 2026) + 10% Tijuana
A12: Mano de obra | B12: 1 oficial albañil + 2 peones (+0.1 cabo) (rend. 30 m²/jor) | C12: jor | D12: 0.033333 | E12: 3095.05 | F12: =D12*E12 | G12: FSR 2026 Tijuana
A13: Herramienta | B13: Herramienta menor (3% de M.O.) | C13: % | D13: 0.03 | E13: =SUMIF(A9:A12,"Mano de obra",F9:F12) | F13: =D13*E13
E14: Costo directo | F14: =SUM(F9:F13)
A16: 003 | B16: Cimbra común en zapatas y contratrabes | E16: m²
A17: Tipo | B17: Insumo | C17: Unidad | D17: Cantidad | E17: Precio | F17: Importe | G17: Fuente
A18: Mano de obra | B18: 1 carpintero + 1 ayudante (+0.1 cabo) (rend. 9.5 m²/jor) | C18: jor | D18: 0.105263 | E18: 2221.6 | F18: =D18*E18 | G18: FSR 2026 Tijuana
A19: Herramienta | B19: Herramienta menor (3% de M.O.) | C19: % | D19: 0.03 | E19: =SUMIF(A18:A18,"Mano de obra",F18:F18) | F19: =D19*E19
E20: Costo directo | F20: =SUM(F18:F19)
A22: 004 | B22: Habilitado y armado de acero #3 y #4 | E22: kg
A23: Tipo | B23: Insumo | C23: Unidad | D23: Cantidad | E23: Precio | F23: Importe | G23: Fuente
A24: Material | B24: Varilla corrugada 3/8" (#3) Grado 42, por tonelada | C24: ton | D24: 0.00105 | E24: 28215 | F24: =D24*E24 | G24: Promedio nacional de referencia (CDMX, Monterrey, Guadalajara, Querétaro), publicado en agosto 2026 (ago 2026) + 10% Tijuana
A25: Material | B25: Alambre recocido Cal. 18 | C25: kg | D25: 0.02 | E25: 36.3 | F25: =D25*E25 | G25: Promedio nacional de referencia (CDMX, Monterrey, Guadalajara, Querétaro), publicado en agosto 2026 (ago 2026) + 10% Tijuana
A26: Mano de obra | B26: 1 fierrero + 1 ayudante (+0.1 cabo) (rend. 215 kg/jor) | C26: jor | D26: 0.004651 | E26: 2221.6 | F26: =D26*E26 | G26: FSR 2026 Tijuana
A27: Herramienta | B27: Herramienta menor (3% de M.O.) | C27: % | D27: 0.03 | E27: =SUMIF(A24:A26,"Mano de obra",F24:F26) | F27: =D27*E27
E28: Costo directo | F28: =SUM(F24:F27)
A30: 005 | B30: Habilitado y armado de acero #5 a #8 | E30: kg
A31: Tipo | B31: Insumo | C31: Unidad | D31: Cantidad | E31: Precio | F31: Importe | G31: Fuente
A32: Material | B32: Varilla corrugada 1/2" (#4) Grado 42, por tonelada | C32: ton | D32: 0.00105 | E32: 27885 | F32: =D32*E32 | G32: Promedio nacional de referencia (CDMX, Monterrey, Guadalajara, Querétaro), publicado en agosto 2026 (ago 2026) + 10% Tijuana
A33: Material | B33: Alambre recocido Cal. 18 | C33: kg | D33: 0.015 | E33: 36.3 | F33: =D33*E33 | G33: Promedio nacional de referencia (CDMX, Monterrey, Guadalajara, Querétaro), publicado en agosto 2026 (ago 2026) + 10% Tijuana
A34: Mano de obra | B34: 1 fierrero + 1 ayudante (+0.1 cabo) (rend. 330 kg/jor) | C34: jor | D34: 0.00303 | E34: 2221.6 | F34: =D34*E34 | G34: FSR 2026 Tijuana
A35: Herramienta | B35: Herramienta menor (3% de M.O.) | C35: % | D35: 0.03 | E35: =SUMIF(A32:A34,"Mano de obra",F32:F34) | F35: =D35*E35
E36: Costo directo | F36: =SUM(F32:F35)
A38: 006 | B38: Colado de concreto premezclado bombeado y vibrado | E38: m³
A39: Tipo | B39: Insumo | C39: Unidad | D39: Cantidad | E39: Precio | F39: Importe | G39: Fuente
A40: Material | B40: Concreto premezclado f'c 250 Solo suministro | C40: m³ | D40: 1.03 | E40: 3135 | F40: =D40*E40 | G40: Promedio nacional de referencia (CDMX, Monterrey, Guadalajara, Querétaro), publicado en agosto 2026 (2025-26) + 10% Tijuana
A41: Mano de obra | B41: Colado: 2 oficiales + 6 peones + cabo (rend. 47.5 m³/jor) | C41: jor | D41: 0.021053 | E41: 9216.35 | F41: =D41*E41 | G41: FSR 2026 Tijuana
A42: Equipo | B42: Vibrador de chicote a gasolina | C42: jornada | D42: 0.022222 | E42: 425 | F42: =D42*E42 | G42: Renta estimada Tijuana (Vértice, oct 2026); confirma con cotización.
A43: Equipo | B43: Bomba de concreto con pluma (cargo por m³) | C43: m³ | D43: 1 | E43: 350 | F43: =D43*E43 | G43: Renta estimada Tijuana (Vértice, oct 2026); confirma con cotización.
A44: Herramienta | B44: Herramienta menor (3% de M.O.) | C44: % | D44: 0.03 | E44: =SUMIF(A40:A43,"Mano de obra",F40:F43) | F44: =D44*E44
E45: Costo directo | F45: =SUM(F40:F44)
A47: 007 | B47: Cimbra de losa maciza con puntales | E47: m²
A48: Tipo | B48: Insumo | C48: Unidad | D48: Cantidad | E48: Precio | F48: Importe | G48: Fuente
A49: Mano de obra | B49: 1 carpintero + 1 ayudante (+0.1 cabo) (rend. 12 m²/jor) | C49: jor | D49: 0.083333 | E49: 2221.6 | F49: =D49*E49 | G49: FSR 2026 Tijuana
A50: Herramienta | B50: Herramienta menor (3% de M.O.) | C50: % | D50: 0.03 | E50: =SUMIF(A49:A49,"Mano de obra",F49:F49) | F50: =D50*E50
E51: Costo directo | F51: =SUM(F49:F50)
A53: 008 | B53: Cimbra de columnas acabado común | E53: m²
A54: Tipo | B54: Insumo | C54: Unidad | D54: Cantidad | E54: Precio | F54: Importe | G54: Fuente
A55: Mano de obra | B55: 1 carpintero + 1 ayudante (+0.1 cabo) (rend. 8 m²/jor) | C55: jor | D55: 0.125 | E55: 2221.6 | F55: =D55*E55 | G55: FSR 2026 Tijuana
A56: Herramienta | B56: Herramienta menor (3% de M.O.) | C56: % | D56: 0.03 | E56: =SUMIF(A55:A55,"Mano de obra",F55:F55) | F56: =D56*E56
E57: Costo directo | F57: =SUM(F55:F56)
A59: 009 | B59: Cimbra de trabes acabado común | E59: m²
A60: Tipo | B60: Insumo | C60: Unidad | D60: Cantidad | E60: Precio | F60: Importe | G60: Fuente
A61: Mano de obra | B61: 1 carpintero + 1 ayudante (+0.1 cabo) (rend. 8.5 m²/jor) | C61: jor | D61: 0.117647 | E61: 2221.6 | F61: =D61*E61 | G61: FSR 2026 Tijuana
A62: Herramienta | B62: Herramienta menor (3% de M.O.) | C62: % | D62: 0.03 | E62: =SUMIF(A61:A61,"Mano de obra",F61:F61) | F62: =D62*E62
E63: Costo directo | F63: =SUM(F61:F62)
A65: 010 | B65: Muro de block 15x20x40 junteado con mortero | E65: m²
A66: Tipo | B66: Insumo | C66: Unidad | D66: Cantidad | E66: Precio | F66: Importe | G66: Fuente
A67: Material | B67: Block de concreto hueco 15x20x40 cm | C67: pza | D67: 12.9 | E67: 19.8 | F67: =D67*E67 | G67: Promedio nacional de referencia (CDMX, Monterrey, Guadalajara, Querétaro), publicado en agosto 2026 (ago 2026) + 10% Tijuana
A68: Material | B68: Cemento gris CPC 30R Bulto 50 kg, menudeo | C68: bulto | D68: 0.1 | E68: 253 | F68: =D68*E68 | G68: Promedio nacional de referencia (CDMX, Monterrey, Guadalajara, Querétaro), publicado en agosto 2026 (ago 2026) + 10% Tijuana
A69: Material | B69: Arena de mina / río Varía por banco | C69: m³ | D69: 0.014 | E69: 715 | F69: =D69*E69 | G69: Promedio nacional de referencia (CDMX, Monterrey, Guadalajara, Querétaro), publicado en agosto 2026 (ago 2026) + 10% Tijuana
A70: Mano de obra | B70: 1 oficial albañil + 1 peón (+0.1 cabo) (rend. 10.5 m²/jor) | C70: jor | D70: 0.095238 | E70: 2186.62 | F70: =D70*E70 | G70: FSR 2026 Tijuana
A71: Herramienta | B71: Herramienta menor (3% de M.O.) | C71: % | D71: 0.03 | E71: =SUMIF(A67:A70,"Mano de obra",F67:F70) | F71: =D71*E71
E72: Costo directo | F72: =SUM(F67:F71)
A74: 011 | B74: Castillo 15x15 armado, cimbrado y colado | E74: ml
A75: Tipo | B75: Insumo | C75: Unidad | D75: Cantidad | E75: Precio | F75: Importe | G75: Fuente
A76: Material | B76: Armex castillo prefabricado 15x15-4, tramo 6 m | C76: tramo | D76: 0.175 | E76: 332.75 | F76: =D76*E76 | G76: Promedio nacional de referencia (CDMX, Monterrey, Guadalajara, Querétaro), publicado en agosto 2026 (ago 2026) + 10% Tijuana
A77: Material | B77: Cemento gris CPC 30R Bulto 50 kg, menudeo | C77: bulto | D77: 0.17 | E77: 253 | F77: =D77*E77 | G77: Promedio nacional de referencia (CDMX, Monterrey, Guadalajara, Querétaro), publicado en agosto 2026 (ago 2026) + 10% Tijuana
A78: Material | B78: Arena de mina / río Varía por banco | C78: m³ | D78: 0.011 | E78: 715 | F78: =D78*E78 | G78: Promedio nacional de referencia (CDMX, Monterrey, Guadalajara, Querétaro), publicado en agosto 2026 (ago 2026) + 10% Tijuana
A79: Material | B79: Grava 3/4" Triturada o de banco | C79: m³ | D79: 0.015 | E79: 792 | F79: =D79*E79 | G79: Promedio nacional de referencia (CDMX, Monterrey, Guadalajara, Querétaro), publicado en agosto 2026 (ago 2026) + 10% Tijuana
A80: Mano de obra | B80: 1 oficial albañil + 1 peón (+0.1 cabo) (rend. 7 ml/jor) | C80: jor | D80: 0.142857 | E80: 2186.62 | F80: =D80*E80 | G80: FSR 2026 Tijuana
A81: Herramienta | B81: Herramienta menor (3% de M.O.) | C81: % | D81: 0.03 | E81: =SUMIF(A76:A80,"Mano de obra",F76:F80) | F81: =D81*E81
E82: Costo directo | F82: =SUM(F76:F81)
A84: 012 | B84: Dala o cadena 15x20 armada, cimbrada y colada | E84: ml
A85: Tipo | B85: Insumo | C85: Unidad | D85: Cantidad | E85: Precio | F85: Importe | G85: Fuente
A86: Mano de obra | B86: 1 oficial albañil + 1 peón (+0.1 cabo) (rend. 7 ml/jor) | C86: jor | D86: 0.142857 | E86: 2186.62 | F86: =D86*E86 | G86: FSR 2026 Tijuana
A87: Herramienta | B87: Herramienta menor (3% de M.O.) | C87: % | D87: 0.03 | E87: =SUMIF(A86:A86,"Mano de obra",F86:F86) | F87: =D87*E87
E88: Costo directo | F88: =SUM(F86:F87)
A90: 013 | B90: Firme de concreto de 10 cm acabado pulido | E90: m²
A91: Tipo | B91: Insumo | C91: Unidad | D91: Cantidad | E91: Precio | F91: Importe | G91: Fuente
A92: Material | B92: Concreto premezclado f'c 200 Solo suministro | C92: m³ | D92: 0.105 | E92: 2750 | F92: =D92*E92 | G92: Promedio nacional de referencia (CDMX, Monterrey, Guadalajara, Querétaro), publicado en agosto 2026 (2025-26) + 10% Tijuana
A93: Material | B93: Malla electrosoldada 6-6/10-10 | C93: m² | D93: 1.05 | E93: 71.5 | F93: =D93*E93 | G93: Promedio nacional de referencia (CDMX, Monterrey, Guadalajara, Querétaro), publicado en agosto 2026 (ago 2026) + 10% Tijuana
A94: Mano de obra | B94: 1 oficial albañil + 2 peones (+0.1 cabo) (rend. 30 m²/jor) | C94: jor | D94: 0.033333 | E94: 3095.05 | F94: =D94*E94 | G94: FSR 2026 Tijuana
A95: Herramienta | B95: Herramienta menor (3% de M.O.) | C95: % | D95: 0.03 | E95: =SUMIF(A92:A94,"Mano de obra",F92:F94) | F95: =D95*E95
E96: Costo directo | F96: =SUM(F92:F95)
A98: 014 | B98: Aplanado de mortero en muros, acabado fino | E98: m²
A99: Tipo | B99: Insumo | C99: Unidad | D99: Cantidad | E99: Precio | F99: Importe | G99: Fuente
A100: Material | B100: Cemento gris CPC 30R Bulto 50 kg, menudeo | C100: bulto | D100: 0.15 | E100: 253 | F100: =D100*E100 | G100: Promedio nacional de referencia (CDMX, Monterrey, Guadalajara, Querétaro), publicado en agosto 2026 (ago 2026) + 10% Tijuana
A101: Material | B101: Cal hidratada Bulto 25 kg | C101: bulto | D101: 0.05 | E101: 115.5 | F101: =D101*E101 | G101: Promedio nacional de referencia (CDMX, Monterrey, Guadalajara, Querétaro), publicado en agosto 2026 (ago 2026) + 10% Tijuana
A102: Material | B102: Arena de mina / río Varía por banco | C102: m³ | D102: 0.024 | E102: 715 | F102: =D102*E102 | G102: Promedio nacional de referencia (CDMX, Monterrey, Guadalajara, Querétaro), publicado en agosto 2026 (ago 2026) + 10% Tijuana
A103: Mano de obra | B103: 1 oficial albañil + 1 peón (+0.1 cabo) (rend. 12 m²/jor) | C103: jor | D103: 0.083333 | E103: 2186.62 | F103: =D103*E103 | G103: FSR 2026 Tijuana
A104: Herramienta | B104: Herramienta menor (3% de M.O.) | C104: % | D104: 0.03 | E104: =SUMIF(A100:A103,"Mano de obra",F100:F103) | F104: =D104*E104
E105: Costo directo | F105: =SUM(F100:F104)
A107: 015 | B107: Piso cerámico/porcelanato pegado con adhesivo y boquilla | E107: m²
A108: Tipo | B108: Insumo | C108: Unidad | D108: Cantidad | E108: Precio | F108: Importe | G108: Fuente
A109: Mano de obra | B109: 1 azulejero + 1 ayudante (rend. 15 m²/jor) | C109: jor | D109: 0.066667 | E109: 2087.91 | F109: =D109*E109 | G109: FSR 2026 Tijuana
A110: Herramienta | B110: Herramienta menor (3% de M.O.) | C110: % | D110: 0.03 | E110: =SUMIF(A109:A109,"Mano de obra",F109:F109) | F110: =D110*E110
E111: Costo directo | F111: =SUM(F109:F110)
A113: 016 | B113: Pintura vinílica dos manos con sellador | E113: m²
A114: Tipo | B114: Insumo | C114: Unidad | D114: Cantidad | E114: Precio | F114: Importe | G114: Fuente
A115: Mano de obra | B115: 1 pintor (rend. 50 m²/jor) | C115: jor | D115: 0.02 | E115: 1092.04 | F115: =D115*E115 | G115: FSR 2026 Tijuana
...

Sheet Insumos
A1: Tipo | B1: Insumo | C1: Unidad | D1: Cantidad total | E1: Importe (costo directo)
A2: Equipo | B2: Bomba de concreto con pluma (cargo por m³) | C2: m³ | D2: 25.8 | E2: 9030
A3: Equipo | B3: Vibrador de chicote a gasolina | C3: jornada | D3: 0.573 | E3: 243.67
A4: Mano de obra | B4: 1 azulejero + 1 ayudante (rend. 15 m²/jor) | C4: jor | D4: 10 | E4: 20879.1
A5: Mano de obra | B5: 1 carpintero + 1 ayudante (+0.1 cabo) (rend. 12 m²/jor) | C5: jor | D5: 13.333 | E5: 29621.28
A6: Mano de obra | B6: 1 carpintero + 1 ayudante (+0.1 cabo) (rend. 8 m²/jor) | C6: jor | D6: 0.84 | E6: 1866.14
A7: Mano de obra | B7: 1 carpintero + 1 ayudante (+0.1 cabo) (rend. 8.5 m²/jor) | C7: jor | D7: 1.471 | E7: 3267.05
A8: Mano de obra | B8: 1 carpintero + 1 ayudante (+0.1 cabo) (rend. 9.5 m²/jor) | C8: jor | D8: 4.547 | E8: 10102.42
A9: Mano de obra | B9: 1 electricista + 1 ayudante (rend. 5 sal/jor) | C9: jor | D9: 14 | E9: 30454.83
A10: Mano de obra | B10: 1 fierrero + 1 ayudante (+0.1 cabo) (rend. 215 kg/jor) | C10: jor | D10: 10.233 | E10: 22732.61
A11: Mano de obra | B11: 1 fierrero + 1 ayudante (+0.1 cabo) (rend. 330 kg/jor) | C11: jor | D11: 2.727 | E11: 6058.9
A12: Mano de obra | B12: 1 impermeabilizador + 1 ayudante (rend. 50 m²/jor) | C12: jor | D12: 1.7 | E12: 3400.81
A13: Mano de obra | B13: 1 oficial albañil + 1 peón (+0.1 cabo) (rend. 10.5 m²/jor) | C13: jor | D13: 22.731 | E13: 49705.04
... A32: Material | B32: Varilla corrugada 3/8" (#3) Grado 42, por tonelada | C32: ton | D32: 2.31 | E32: 65176.65
